Workbook

Sheet Dordrecth_Finland_600LPF_125Ah
A1: Time (sec) | B1: Load Profile (kW) | C1: Battery power (kW) | D1: Total Batt Power (kW) | E1: Fuel cell power (kW) | F1: Abs(Pfc(t)-Pfc(t-1) | G1: TotalFC power (kW) | H1: Battery SoC (%) | AJ1: Sampling_dt(sec) | AK1: Sampling_dt(hrs) | AL1: Fuel consumption (f(pfc)) for 1 FC (kW) | AM1: Addit_Ploss(kW) | AN1: Fctotal(kw) | AP1: FC_total*hrs(kwh) | AQ1: Ke-m ( kg/kwh) | AR1: Fuel consumption (kg) | AS1: H2 in $/kg | AT1: Fuel cost ($) | AU1: H2 price in $/kwh | AW1: Fuel cost ($)
A2: 0 | B2: 0 | C2: 12.350136 | D2: =C2*$K$3 -> 24.700273 | E2: 0 | F2: 0 | G2: =E2*$J$3 -> 0 | H2: 50 | J2: Nfc | K2: Nbat | AJ2: 300 | AK2: =AJ2/3600 -> 0.083333333 | AL2: =$AE$26*E2^2+$AF$26*E2+$AG$26 -> 0.8595 | AN2: =J3*AL2052+AM2 -> 2242198.5 | AP2: =AN2*AK2 -> 186849.88 | AQ2: 0.03 | AR2: =AP2*AQ2 -> 5605.4963 | AS2: 4 | AT2: =AR2*AS2 -> 22421.985 | AU2: =AS2/33.35 -> 0.11994003 | AW2: =AP2*AU2 -> 22410.78
A3: 300 | B3: 0 | C3: -0.075000176 | D3: =C3*$K$3 -> -0.15000035 | E3: 0.016667063 | F3: =ABS(E3-E2) -> 0.016667063 | G3: =E3*$J$3 -> 0.15000356 | H3: 50.542869 | J3: 9 | K3: 2 | AL3: =$AE$26*E3^2+$AF$26*E3+$AG$26 -> 0.88475741
A4: 600 | B4: 23 | C4: 11.499906 | D4: =C4*$K$3 -> 22.999812 | E4: 2.9795083e-05 | F4: =ABS(E4-E3) -> 0.016637268 | G4: =E4*$J$3 -> 0.00026815575 | H4: 50.098241 | AF4: Fuel consumption | AL4: =$AE$26*E4^2+$AF$26*E4+$AG$26 -> 0.85954515 | AQ4: *Source: Cost-effective control of Roll-on/Roll-off Emission-Free Ships
A5: 900 | B5: 87 | C5: 30.399895 | D5: =C5*$K$3 -> 60.79979 | E5: 2.9110887 | F5: =ABS(E5-E4) -> 2.9110589 | G5: =E5*$J$3 -> 26.199798 | H5: 48.21439 | AL5: =$AE$26*E5^2+$AF$26*E5+$AG$26 -> 5.2956306 | AQ5: CHECK END OF LIFE INCREASE IN kg | AR5: =AR2+25.29%*AR2 -> 7023.1264
A6: 1200 | B6: 128 | C6: 29.913923 | D6: =C6*$K$3 -> 59.827845 | E6: 7.574639 | F6: =ABS(E6-E5) -> 4.6635503 | G6: =E6*$J$3 -> 68.171751 | H6: 45.843224 | K6: DC BUS VOLTAGE | AL6: =$AE$26*E6^2+$AF$26*E6+$AG$26 -> 12.505597 | AQ6: 25.29% increase in kg due to FC degrad
A7: 1500 | B7: 149 | C7: 20.211456 | D7: =C7*$K$3 -> 40.422912 | E7: 12.06406 | F7: =ABS(E7-E6) -> 4.4894211 | G7: =E7*$J$3 -> 108.57654 | H7: 43.915621 | AL7: =$AE$26*E7^2+$AF$26*E7+$AG$26 -> 19.566527
A8: 1800 | B8: 260 | C8: 47.01338 | D8: =C8*$K$3 -> 94.026759 | E8: 18.441271 | F8: =ABS(E8-E7) -> 6.3772107 | G8: =E8*$J$3 -> 165.97144 | H8: 41.163769 | AL8: =$AE$26*E8^2+$AF$26*E8+$AG$26 -> 29.799223
A9: 2100 | B9: 233 | C9: 8.1230848 | D9: =C9*$K$3 -> 16.24617 | E9: 24.083625 | F9: =ABS(E9-E8) -> 5.642354 | G9: =E9*$J$3 -> 216.75262 | H9: 39.150735 | AL9: =$AE$26*E9^2+$AF$26*E9+$AG$26 -> 39.051121
A10: 2400 | B10: 188 | C10: -20.269163 | D10: =C10*$K$3 -> -40.538325 | E10: 25.39302 | F10: =ABS(E10-E9) -> 1.3093955 | G10: =E10*$J$3 -> 228.53718 | H10: 39.7331 | AL10: =$AE$26*E10^2+$AF$26*E10+$AG$26 -> 41.224788
A11: 2700 | B11: 152 | C11: -31.461293 | D11: =C11*$K$3 -> -62.922586 | E11: 23.88016 | F11: =ABS(E11-E10) -> 1.5128602 | G11: =E11*$J$3 -> 214.92144 | H11: 41.785562 | AL11: =$AE$26*E11^2+$AF$26*E11+$AG$26 -> 38.714259
A12: 3000 | B12: 197 | C12: -5.669451 | D12: =C12*$K$3 -> -11.338902 | E12: 23.148587 | F12: =ABS(E12-E11) -> 0.73157307 | G12: =E12*$J$3 -> 208.33728 | H12: 43.129592 | AL12: =$AE$26*E12^2+$AF$26*E12+$AG$26 -> 37.505046
A13: 3300 | B13: 225 | C13: 2.5229465 | D13: =C13*$K$3 -> 5.045893 | E13: 24.439161 | F13: =ABS(E13-E12) -> 1.2905742 | G13: =E13*$J$3 -> 219.95245 | H13: 43.220634 | AL13: =$AE$26*E13^2+$AF$26*E13+$AG$26 -> 39.640339
A14: 3600 | B14: 280 | C14: 16.992358 | D14: =C14*$K$3 -> 33.984715 | E14: 27.33477 | F14: =ABS(E14-E13) -> 2.8956083 | G14: =E14*$J$3 -> 246.01293 | H14: 42.401817 | AL14: =$AE$26*E14^2+$AF$26*E14+$AG$26 -> 44.466657
A15: 3900 | B15: 480 | C15: 60.503773 | D15: =C15*$K$3 -> 121.00755 | E15: 38.359204 | F15: =ABS(E15-E14) -> 11.024434 | G15: =E15*$J$3 -> 345.23283 | H15: 38.615394 | AL15: =$AE$26*E15^2+$AF$26*E15+$AG$26 -> 63.290666
A16: 4200 | B16: 533 | C16: 45.686653 | D16: =C16*$K$3 -> 91.373307 | E16: 49.068807 | F16: =ABS(E16-E15) -> 10.709603 | G16: =E16*$J$3 -> 441.61926 | H16: 34.437971 | AL16: =$AE$26*E16^2+$AF$26*E16+$AG$26 -> 82.257817
A17: 4500 | B17: 600 | C17: 40.767212 | D17: =C17*$K$3 -> 81.534424 | E17: 57.606126 | F17: =ABS(E17-E16) -> 8.5373192 | G17: =E17*$J$3 -> 518.45513 | H17: 31.038085 | AL17: =$AE$26*E17^2+$AF$26*E17+$AG$26 -> 97.858306
A18: 4800 | B18: 818 | C18: 37.5531 | D18: =C18*$K$3 -> 75.1062 | E18: 78.858452 | F18: =ABS(E18-E17) -> 21.252326 | G18: =E18*$J$3 -> 709.72607 | H18: 27.81191 | AL18: =$AE$26*E18^2+$AF$26*E18+$AG$26 -> 138.54478
... A20: 5400 | B20: 331 | C20: -87.033635 | D20: =C20*$K$3 -> -174.06727 | E20: 57.635957 | F20: =ABS(E20-E19) -> 23.874083 | G20: =E20*$J$3 -> 518.72361 | H20: 36.023902 | AL20: =$AE$26*E20^2+$AF$26*E20+$AG$26 -> 97.913564
A21: 5700 | B21: 534 | C21: 18.13439 | D21: =C21*$K$3 -> 36.26878 | E21: 55.302086 | F21: =ABS(E21-E20) -> 2.3338713 | G21: =E21*$J$3 -> 497.71877 | H21: 38.449577 | AE21: Fuel consumption (kW) in y axis | AL21: =$AE$26*E21^2+$AF$26*E21+$AG$26 -> 93.606066
A22: 6000 | B22: 740 | C22: 52.46224 | D22: =C22*$K$3 -> 104.92448 | E22: 67.762013 | F22: =ABS(E22-E21) -> 12.459927 | G22: =E22*$J$3 -> 609.85812 | H22: 34.830477 | AE22: Power output (kW) in x axis | AL22: =$AE$26*E22^2+$AF$26*E22+$AG$26 -> 116.97165
A23: 6300 | B23: 702 | C23: 10.850295 | D23: =C23*$K$3 -> 21.70059 | E23: 75.587186 | F23: =ABS(E23-E22) -> 7.825173 | G23: =E23*$J$3 -> 680.28467 | H23: 32.245681 | AL23: =$AE$26*E23^2+$AF$26*E23+$AG$26 -> 132.11009
A24: 6600 | B24: 706 | C24: -2.5921268 | D24: =C24*$K$3 -> -5.1842537 | E24: 79.018491 | F24: =ABS(E24-E23) -> 3.4313048 | G24: =E24*$J$3 -> 711.16642 | H24: 31.965721 | AL24: =$AE$26*E24^2+$AF$26*E24+$AG$26 -> 138.86118
A25: 6900 | B25: 746 | C25: 3.6389054 | D25: =C25*$K$3 -> 7.2778109 | E25: 82.077928 | F25: =ABS(E25-E24) -> 3.0594377 | G25: =E25*$J$3 -> 738.70136 | H25: 31.90763 | AE25: k1 | AF25: k2 | AG25: k3 | AL25: =$AE$26*E25^2+$AF$26*E25+$AG$26 -> 144.93871
A26: 7200 | B26: 751 | C26: -6.329606 | D26: =C26*$K$3 -> -12.659212 | E26: 84.848666 | F26: =ABS(E26-E25) -> 2.770738 | G26: =E26*$J$3 -> 763.638 | H26: 32.043853 | AE26: 0.00292448 | AF26: 1.51536 | AG26: 0.8595 | AL26: =$AE$26*E26^2+$AF$26*E26+$AG$26 -> 150.48997
A27: 7500 | B27: 719 | C27: -27.097408 | D27: =C27*$K$3 -> -54.194815 | E27: 85.908253 | F27: =ABS(E27-E26) -> 1.0595866 | G27: =E27*$J$3 -> 773.17428 | H27: 33.407719 | AL27: =$AE$26*E27^2+$AF$26*E27+$AG$26 -> 152.62476
A28: 7800 | B28: 704 | C28: -32.358031 | D28: =C28*$K$3 -> -64.716062 | E28: 85.410569 | F28: =ABS(E28-E27) -> 0.49768384 | G28: =E28*$J$3 -> 768.69512 | H28: 35.734524 | AL28: =$AE$26*E28^2+$AF$26*E28+$AG$26 -> 151.62124
A29: 8100 | B29: 699 | C29: -30.255994 | D29: =C29*$K$3 -> -60.511988 | E29: 84.38792 | F29: =ABS(E29-E28) -> 1.0226492 | G29: =E29*$J$3 -> 759.49128 | H29: 38.159576 | AL29: =$AE$26*E29^2+$AF$26*E29+$AG$26 -> 149.56374
A30: 8400 | B30: 729 | C30: -13.526743 | D30: =C30*$K$3 -> -27.053485 | E30: 84.003534 | F30: =ABS(E30-E29) -> 0.38438549 | G30: =E30*$J$3 -> 756.03181 | H30: 39.811969 | AL30: =$AE$26*E30^2+$AF$26*E30+$AG$26 -> 148.79196
A31: 8700 | B31: 728 | C31: -14.655551 | D31: =C31*$K$3 -> -29.311102 | E31: 84.143385 | F31: =ABS(E31-E30) -> 0.13985068 | G31: =E31*$J$3 -> 757.29047 | H31: 40.911039 | AL31: =$AE$26*E31^2+$AF$26*E31+$AG$26 -> 149.07266
A32: 9000 | B32: 724 | C32: -15.914665 | D32: =C32*$K$3 -> -31.829331 | E32: 83.978765 | F32: =ABS(E32-E31) -> 0.16461969 | G32: =E32*$J$3 -> 755.80889 | H32: 42.102622 | AL32: =$AE$26*E32^2+$AF$26*E32+$AG$26 -> 148.74226
A33: 9300 | B33: 735 | C33: -9.9974718 | D33: =C33*$K$3 -> -19.994944 | E33: 83.886003 | F33: =ABS(E33-E32) -> 0.09276232 | G33: =E33*$J$3 -> 754.97403 | H33: 43.09234 | AE33: BATTERY DEGRADATION | AL33: =$AE$26*E33^2+$AF$26*E33+$AG$26 -> 148.55615
A34: 9600 | B34: 735 | C34: -10.17627 | D34: =C34*$K$3 -> -20.352539 | E34: 83.925777 | F34: =ABS(E34-E33) -> 0.039774173 | G34: =E34*$J$3 -> 755.332 | H34: 43.876949 | AL34: =$AE$26*E34^2+$AF$26*E34+$AG$26 -> 148.63595
A35: 9900 | B35: 697 | C35: -25.021821 | D35: =C35*$K$3 -> -50.043643 | E35: 83.002768 | F35: =ABS(E35-E34) -> 0.92300886 | G35: =E35*$J$3 -> 747.02492 | H35: 45.285503 | AL35: =$AE$26*E35^2+$AF$26*E35+$AG$26 -> 146.78666
A36: 10200 | B36: 434 | C36: -86.2468 | D36: =C36*$K$3 -> -172.4936 | E36: 70.099664 | F36: =ABS(E36-E35) -> 12.903105 | G36: =E36*$J$3 -> 630.89697 | H36: 50.653144 | AL36: =$AE$26*E36^2+$AF$26*E36+$AG$26 -> 121.45651
A37: 10500 | B37: 440 | C37: -49.326334 | D37: =C37*$K$3 -> -98.652669 | E37: 59.849165 | F37: =ABS(E37-E36) -> 10.250499 | G37: =E37*$J$3 -> 538.64248 | H37: 55.854063 | AL37: =$AE$26*E37^2+$AF$26*E37+$AG$26 -> 102.02779
A38: 10800 | B38: 330 | C38: -64.936392 | D38: =C38*$K$3 -> -129.87278 | E38: 51.297716 | F38: =ABS(E38-E37) -> 8.5514485 | G38: =E38*$J$3 -> 461.67945 | H38: 60.362663 | AL38: =$AE$26*E38^2+$AF$26*E38+$AG$26 -> 86.289647
A39: 11100 | B39: 305 | C39: -39.117809 | D39: =C39*$K$3 -> -78.235619 | E39: 42.581226 | F39: =ABS(E39-E38) -> 8.7164905 | G39: =E39*$J$3 -> 383.23103 | H39: 64.305418 | AL39: =$AE$26*E39^2+$AF$26*E39+$AG$26 -> 70.687939
A40: 11400 | B40: 252 | C40: -31.421228 | D40: =C40*$K$3 -> -62.842455 | E40: 34.982202 | F40: =ABS(E40-E39) -> 7.5990235 | G40: =E40*$J$3 -> 314.83982 | H40: 66.997868 | AL40: =$AE$26*E40^2+$AF$26*E40+$AG$26 -> 57.448976
A41: 11700 | B41: 464 | C41: 74.712722 | D41: =C41*$K$3 -> 149.42544 | E41: 34.952074 | F41: =ABS(E41-E40) -> 0.030128188 | G41: =E41*$J$3 -> 314.56867 | H41: 64.896746 | AL41: =$AE$26*E41^2+$AF$26*E41+$AG$26 -> 57.397159
A42: 12000 | B42: 602 | C42: 84.885046 | D42: =C42*$K$3 -> 169.77009 | E42: 47.366261 | F42: =ABS(E42-E41) -> 12.414187 | G42: =E42*$J$3 -> 426.29635 | H42: 58.344433 | AL42: =$AE$26*E42^2+$AF$26*E42+$AG$26 -> 79.197692
A43: 12300 | B43: 526 | C43: 24.6779 | D43: =C43*$K$3 -> 49.3558 | E43: 52.959843 | F43: =ABS(E43-E42) -> 5.5935818 | G43: =E43*$J$3 -> 476.63859 | H43: 54.183762 | AL43: =$AE$26*E43^2+$AF$26*E43+$AG$26 -> 89.315148
A44: 12600 | B44: 935 | C44: 81.090514 | D44: =C44*$K$3 -> 162.18103 | E44: 77.511927 | F44: =ABS(E44-E43) -> 24.552084 | G44: =E44*$J$3 -> 697.60735 | H44: 48.327093 | AL44: =$AE$26*E44^2+$AF$26*E44+$AG$26 -> 135.88854
A45: 12900 | B45: 932 | C45: 55.880478 | D45: =C45*$K$3 -> 111.76096 | E45: 91.13483 | F45: =ABS(E45-E44) -> 13.622903 | G45: =E45*$J$3 -> 820.21347 | H45: 42.745591 | AL45: =$AE$26*E45^2+$AF$26*E45+$AG$26 -> 163.25101
... A84: 24600 | B84: 163 | C84: -87.358687 | D84: =C84*$K$3 -> -174.71737 | E84: 37.762189 | F84: =ABS(E84-E83) -> 23.269997 | G84: =E84*$J$3 -> 339.85971 | H84: 43.066686 | AL84: =$AE$26*E84^2+$AF$26*E84+$AG$26 -> 62.25307
A85: 24900 | B85: 510 | C85: 69.571981 | D85: =C85*$K$3 -> 139.14396 | E85: 39.988806 | F85: =ABS(E85-E84) -> 2.2266168 | G85: =E85*$J$3 -> 359.89926 | H85: 42.80779 | W85: REFERENCE | AL85: =$AE$26*E85^2+$AF$26*E85+$AG$26 -> 66.133487
A86: 25200 | B86: 862 | C86: 58.693175 | D86: =C86*$K$3 -> 117.38635 | E86: 76.050018 | F86: =ABS(E86-E85) -> 36.061212 | G86: =E86*$J$3 -> 684.45017 | H86: 37.767767 | W86: PBES-Overview-NMC-LTO_2019-05-21-1.pdf (spbes.com) AND | AL86: =$AE$26*E86^2+$AF$26*E86+$AG$26 -> 133.01669
A87: 25500 | B87: 865 | C87: 36.323089 | D87: =C87*$K$3 -> 72.646177 | E87: 88.036707 | F87: =ABS(E87-E86) -> 11.986689 | G87: =E87*$J$3 -> 792.33037 | H87: 33.857792 | W87: Techno-Economic Feasibility Study of BatteryPowered Ferries (RESEARCH PAPER) | AL87: =$AE$26*E87^2+$AF$26*E87+$AG$26 -> 156.93288
A88: 25800 | B88: 348 | C88: -87.149365 | D88: =C88*$K$3 -> -174.29873 | E88: 63.355258 | F88: =ABS(E88-E87) -> 24.681449 | G88: =E88*$J$3 -> 570.19733 | H88: 38.360719 | AL88: =$AE$26*E88^2+$AF$26*E88+$AG$26 -> 108.60406
A89: 26100 | B89: 211 | C89: -87.435959 | D89: =C89*$K$3 -> -174.87192 | E89: 43.100599 | F89: =ABS(E89-E88) -> 20.254659 | G89: =E89*$J$3 -> 387.9054 | H89: 45.019039 | AL89: =$AE$26*E89^2+$AF$26*E89+$AG$26 -> 71.605119
A90: 26400 | B90: 211 | C90: -51.227892 | D90: =C90*$K$3 -> -102.45578 | E90: 34.828036 | F90: =ABS(E90-E89) -> 8.2725636 | G90: =E90*$J$3 -> 313.45232 | H90: 50.238433 | AL90: =$AE$26*E90^2+$AF$26*E90+$AG$26 -> 57.183883
A91: 26700 | B91: 211 | C91: -27.288036 | D91: =C91*$K$3 -> -54.576072 | E91: 29.5082 | F91: =ABS(E91-E90) -> 5.3198356 | G91: =E91*$J$3 -> 265.5738 | H91: 53.183344 | AL91: =$AE$26*E91^2+$AF$26*E91+$AG$26 -> 48.12149
A92: 27000 | B92: 211 | C92: -12.203044 | D92: =C92*$K$3 -> -24.406089 | E92: 26.156045 | F92: =ABS(E92-E91) -> 3.3521554 | G92: =E92*$J$3 -> 235.4044 | H92: 54.656741 | AL92: =$AE$26*E92^2+$AF$26*E92+$AG$26 -> 42.496074
A93: 27300 | B93: 210 | C93: -3.4683129 | D93: =C93*$K$3 -> -6.9366257 | E93: 24.103915 | F93: =ABS(E93-E92) -> 2.0521294 | G93: =E93*$J$3 -> 216.93524 | H93: 55.231905 | AL93: =$AE$26*E93^2+$AF$26*E93+$AG$26 -> 39.084728
A94: 27600 | B94: 210 | C94: 1.937532 | D94: =C94*$K$3 -> 3.875064 | E94: 22.902632 | F94: =ABS(E94-E93) -> 1.2012834 | G94: =E94*$J$3 -> 206.12369 | H94: 55.27064 | AL94: =$AE$26*E94^2+$AF$26*E94+$AG$26 -> 37.099212
A95: 27900 | B95: 211 | C95: 5.1797718 | D95: =C95*$K$3 -> 10.359544 | E95: 22.293252 | F95: =ABS(E95-E94) -> 0.60937995 | G95: =E95*$J$3 -> 200.63927 | H95: 54.981179 | AD95: AT 44% DoD -> MAX Number of cycles = 60,000 | AL95: =$AE$26*E95^2+$AF$26*E95+$AG$26 -> 36.095237
A96: 28200 | B96: 210 | C96: 5.9268324 | D96: =C96*$K$3 -> 11.853665 | E96: 22.016132 | F96: =ABS(E96-E95) -> 0.27711997 | G96: =E96*$J$3 -> 198.14519 | H96: 54.54595 | AD96: MAX CYCLES | AE96: =60000 -> 60000 | AL96: =$AE$26*E96^2+$AF$26*E96+$AG$26 -> 35.639391
A97: 28500 | B97: 210 | C97: 6.3761415 | D97: =C97*$K$3 -> 12.752283 | E97: 21.916286 | F97: =ABS(E97-E96) -> 0.099846234 | G97: =E97*$J$3 -> 197.24657 | H97: 54.065191 | AL97: =$AE$26*E97^2+$AF$26*E97+$AG$26 -> 35.47526
A98: 28800 | B98: 209 | C98: 5.8931425 | D98: =C98*$K$3 -> 11.786285 | E98: 21.912509 | F98: =ABS(E98-E97) -> 0.0037772015 | G98: =E98*$J$3 -> 197.21258 | H98: 53.589317 | AL98: =$AE$26*E98^2+$AF$26*E98+$AG$26 -> 35.469052
A99: 29100 | B99: 226 | C99: 11.987905 | D99: =C99*$K$3 -> 23.97581 | E99: 22.446984 | F99: =ABS(E99-E98) -> 0.53447539 | G99: =E99*$J$3 -> 202.02286 | H99: 52.868766 | AD99: EC (@44.1% DoD) | AE99: Max cycles at 44.1% DoD | AL99: =$AE$26*E99^2+$AF$26*E99+$AG$26 -> 36.348311
A100: 29400 | B100: 247 | C100: 16.154006 | D100: =C100*$K$3 -> 32.308011 | E100: 23.854493 | F100: =ABS(E100-E99) -> 1.4075091 | G100: =E100*$J$3 -> 214.69044 | H100: 51.754602 | AD100: 10.5 | AE100: =60000 -> 60000 | AL100: =$AE$26*E100^2+$AF$26*E100+$AG$26 -> 38.671782
A101: 29700 | B101: 249 | C101: 10.48794 | D101: =C101*$K$3 -> 20.97588 | E101: 25.335839 | F101: =ABS(E101-E100) -> 1.4813463 | G101: =E101*$J$3 -> 228.02255 | H101: 50.737126 | AL101: =$AE$26*E101^2+$AF$26*E101+$AG$26 -> 41.129655
A102: 30000 | B102: 248 | C102: 5.6780269 | D102: =C102*$K$3 -> 11.356054 | E102: 26.293588 | F102: =ABS(E102-E101) -> 0.95774893 | G102: =E102*$J$3 -> 236.64229 | H102: 50.125483 | AD102: if we performed this profile over the lifetime all the time….batteries would be replaced after: | AL102: =$AE$26*E102^2+$AF$26*E102+$AG$26 -> 42.725599
A103: 30300 | B103: 248 | C103: 3.0855637 | D103: =C103*$K$3 -> 6.1711275 | E103: 26.869682 | F103: =ABS(E103-E102) -> 0.57609397 | G103: =E103*$J$3 -> 241.82714 | H103: 49.794035 | AD103: =AE100/AD100 -> 5714.2857 | AE103: trips | AL103: =$AE$26*E103^2+$AF$26*E103+$AG$26 -> 43.688157
A104: 30600 | B104: 246 | C104: 0.73594016 | D104: =C104*$K$3 -> 1.4718803 | E104: 27.169596 | F104: =ABS(E104-E103) -> 0.29991412 | G104: =E104*$J$3 -> 244.52637 | H104: 49.65422 | AL104: =$AE$26*E104^2+$AF$26*E104+$AG$26 -> 44.190033
A105: 30900 | B105: 247 | C105: 0.51608811 | D105: =C105*$K$3 -> 1.0321762 | E105: 27.329558 | F105: =ABS(E105-E104) -> 0.15996173 | G105: =E105*$J$3 -> 245.96602 | H105: 49.606322 | AD105: If we did 1 trip per day all year | AL105: =$AE$26*E105^2+$AF$26*E105+$AG$26 -> 44.457927
A106: 31200 | B106: 247 | C106: -0.0076543361 | D106: =C106*$K$3 -> -0.015308672 | E106: 27.445945 | F106: =ABS(E106-E105) -> 0.11638651 | G106: =E106*$J$3 -> 247.0135 | H106: 49.588532 | AD106: =AD103/365 -> 15.655577 | AE106: years | AL106: =$AE$26*E106^2+$AF$26*E106+$AG$26 -> 44.652939
A107: 31500 | B107: 245 | C107: -1.0446297 | D107: =C107*$K$3 -> -2.0892594 | E107: 27.454163 | F107: =ABS(E107-E106) -> 0.0082186885 | G107: =E107*$J$3 -> 247.08747 | H107: 49.633447 | AL107: =$AE$26*E107^2+$AF$26*E107+$AG$26 -> 44.666712
A108: 31800 | B108: 249 | C108: 0.68125327 | D108: =C108*$K$3 -> 1.3625065 | E108: 27.515071 | F108: =ABS(E108-E107) -> 0.060907699 | G108: =E108*$J$3 -> 247.63564 | H108: 49.640999 | AL108: =$AE$26*E108^2+$AF$26*E108+$AG$26 -> 44.768801
A109: 32100 | B109: 246 | C109: -1.0165996 | D109: =C109*$K$3 -> -2.0331992 | E109: 27.559045 | F109: =ABS(E109-E108) -> 0.043974005 | G109: =E109*$J$3 -> 248.03141 | H109: 49.660527 | X109: PRAXIS BATTERIES | AL109: =$AE$26*E109^2+$AF$26*E109+$AG$26 -> 44.84252
A110: 32400 | B110: 246 | C110: -0.77953496 | D110: =C110*$K$3 -> -1.5590699 | E110: 27.506362 | F110: =ABS(E110-E109) -> 0.052683434 | G110: =E110*$J$3 -> 247.55725 | H110: 49.729528 | W110: 513.01 GreenBattery Rev1.12 A4.cdr (praxis-automation.eu) | AL110: =$AE$26*E110^2+$AF$26*E110+$AG$26 -> 44.754201
A111: 32700 | B111: 248 | C111: 0.14252144 | D111: =C111*$K$3 -> 0.28504288 | E111: 27.52368 | F111: =ABS(E111-E110) -> 0.017318458 | G111: =E111*$J$3 -> 247.71312 | H111: 49.750801 | AL111: =$AE$26*E111^2+$AF$26*E111+$AG$26 -> 44.783232
A112: 33000 | B112: 249 | C112: 0.27163568 | D112: =C112*$K$3 -> 0.54327136 | E112: 27.606099 | F112: =ABS(E112-E111) -> 0.082419058 | G112: =E112*$J$3 -> 248.45489 | H112: 49.734186 | AL112: =$AE$26*E112^2+$AF$26*E112+$AG$26 -> 44.921415
A113: 33300 | B113: 248 | C113: -0.41938473 | D113: =C113*$K$3 -> -0.83876945 | E113: 27.648549 | F113: =ABS(E113-E112) -> 0.042450273 | G113: =E113*$J$3 -> 248.83694 | H113: 49.742573 | AL113: =$AE$26*E113^2+$AF$26*E113+$AG$26 -> 44.992602
A114: 33600 | B114: 248 | C114: -0.40519497 | D114: =C114*$K$3 -> -0.81038994 | E114: 27.645395 | F114: =ABS(E114-E113) -> 0.0031543069 | G114: =E114*$J$3 -> 248.80856 | H114: 49.774614 | AL114: =$AE$26*E114^2+$AF$26*E114+$AG$26 -> 44.987312
A115: 33900 | B115: 249 | C115: -0.0010763821 | D115: =C115*$K$3 -> -0.0021527643 | E115: 27.666701 | F115: =ABS(E115-E114) -> 0.021305779 | G115: =E115*$J$3 -> 249.00031 | H115: 49.788885 | AL115: =$AE$26*E115^2+$AF$26*E115+$AG$26 -> 45.023044
A116: 34200 | B116: 249 | C116: -0.15089377 | D116: =C116*$K$3 -> -0.30178754 | E116: 27.699994 | F116: =ABS(E116-E115) -> 0.033293314 | G116: =E116*$J$3 -> 249.29995 | H116: 49.795372 | AL116: =$AE$26*E116^2+$AF$26*E116+$AG$26 -> 45.078887
A117: 34500 | B117: 248 | C117: -0.59933865 | D117: =C117*$K$3 -> -1.1986773 | E117: 27.688539 | F117: =ABS(E117-E116) -> 0.01145565 | G117: =E117*$J$3 -> 249.19685 | H117: 49.826282 | AL117: =$AE$26*E117^2+$AF$26*E117+$AG$26 -> 45.059671
A118: 34800 | B118: 249 | C118: -0.066996586 | D118: =C118*$K$3 -> -0.13399317 | E118: 27.68135 | F118: =ABS(E118-E117) -> 0.0071889611 | G118: =E118*$J$3 -> 249.13215 | H118: 49.850187 | AL118: =$AE$26*E118^2+$AF$26*E118+$AG$26 -> 45.047613
A119: 35100 | B119: 248 | C119: -0.51589982 | D119: =C119*$K$3 -> -1.0317996 | E119: 27.669997 | F119: =ABS(E119-E118) -> 0.011352721 | G119: =E119*$J$3 -> 249.02997 | H119: 49.874585 | AL119: =$AE$26*E119^2+$AF$26*E119+$AG$26 -> 45.028572
A120: 35400 | B120: 248 | C120: -0.36223773 | D120: =C120*$K$3 -> -0.72447547 | E120: 27.635849 | F120: =ABS(E120-E119) -> 0.034147681 | G120: =E120*$J$3 -> 248.72264 | H120: 49.908177 | AL120: =$AE$26*E120^2+$AF$26*E120+$AG$26 -> 44.971303
A121: 35700 | B121: 248 | C121: -0.25700436 | D121: =C121*$K$3 -> -0.51400871 | E121: 27.612464 | F121: =ABS(E121-E120) -> 0.023384838 | G121: =E121*$J$3 -> 248.51218 | H121: 49.931877 | W121: DoD(%) | X121: Cycles (1C) | AL121: =$AE$26*E121^2+$AF$26*E121+$AG$26 -> 44.932088
A122: 36000 | B122: 248 | C122: -0.18445753 | D122: =C122*$K$3 -> -0.36891507 | E122: 27.596343 | F122: =ABS(E122-E121) -> 0.01612127 | G122: =E122*$J$3 -> 248.36709 | H122: 49.948782 | W122: 5 | X122: 180000 | AL122: =$AE$26*E122^2+$AF$26*E122+$AG$26 -> 44.905056
A123: 36300 | B123: 249 | C123: 0.23970802 | D123: =C123*$K$3 -> 0.47941603 | E123: 27.613194 | F123: =ABS(E123-E122) -> 0.016850972 | G123: =E123*$J$3 -> 248.51875 | H123: 49.945012 | W123: 10 | X123: 130000 | AL123: =$AE$26*E123^2+$AF$26*E123+$AG$26 -> 44.933312
A124: 36600 | B124: 249 | C124: 0.087642989 | D124: =C124*$K$3 -> 0.17528598 | E124: 27.646987 | F124: =ABS(E124-E123) -> 0.033792781 | G124: =E124*$J$3 -> 248.82288 | H124: 49.93285 | W124: 20 | X124: 80000 | AL124: =$AE$26*E124^2+$AF$26*E124+$AG$26 -> 44.989981
A125: 36900 | B125: 251 | C125: 0.74607823 | D125: =C125*$K$3 -> 1.4921565 | E125: 27.722887 | F125: =ABS(E125-E124) -> 0.075900018 | G125: =E125*$J$3 -> 249.50598 | H125: 49.897883 | W125: 50 | X125: 24000 | AL125: =$AE$26*E125^2+$AF$26*E125+$AG$26 -> 45.117288
A126: 37200 | B126: 243 | C126: -2.66843 | D126: =C126*$K$3 -> -5.3368601 | E126: 27.59279 | F126: =ABS(E126-E125) -> 0.13009689 | G126: =E126*$J$3 -> 248.33511 | H126: 49.985696 | W126: 80 | X126: 6200 | AD126: EC (@44.1% DoD) | AE126: Max cycles at 44.1% DoD | AL126: =$AE$26*E126^2+$AF$26*E126+$AG$26 -> 44.899098
A127: 37500 | B127: 201 | C127: -17.117831 | D127: =C127*$K$3 -> -34.235662 | E127: 26.137151 | F127: =ABS(E127-E126) -> 1.4556387 | G127: =E127*$J$3 -> 235.23436 | H127: 50.809002 | W127: 90 | X127: 5000 | AD127: 10.5 | AE127: =X132 -> 35013.333 | AL127: =$AE$26*E127^2+$AF$26*E127+$AG$26 -> 42.464554
A128: 37800 | B128: 187 | C128: -13.668386 | D128: =C128*$K$3 -> -27.336772 | E128: 23.815055 | F128: =ABS(E128-E127) -> 2.3220963 | G128: =E128*$J$3 -> 214.33549 | H128: 51.990534 | AL128: =$AE$26*E128^2+$AF$26*E128+$AG$26 -> 38.606521
A129: 38100 | B129: 186 | C129: -6.116902 | D129: =C129*$K$3 -> -12.233804 | E129: 22.02585 | F129: =ABS(E129-E128) -> 1.7892053 | G129: =E129*$J$3 -> 198.23265 | H129: 52.729867 | AL129: =$AE$26*E129^2+$AF$26*E129+$AG$26 -> 35.655368
A130: 38400 | B130: 190 | C130: 0.25265054 | D130: =C130*$K$3 -> 0.50530108 | E130: 21.054847 | F130: =ABS(E130-E129) -> 0.97100306 | G130: =E130*$J$3 -> 189.49362 | H130: 52.933198 | W130: x | X130: y | AL130: =$AE$26*E130^2+$AF$26*E130+$AG$26 -> 34.061614
A131: 38700 | B131: 207 | C131: 8.5622103 | D131: =C131*$K$3 -> 17.124421 | E131: 21.097156 | F131: =ABS(E131-E130) -> 0.04230939 | G131: =E131*$J$3 -> 189.8744 | H131: 52.557515 | W131: 20 | X131: 80000 | AL131: =$AE$26*E131^2+$AF$26*E131+$AG$26 -> 34.130943
A132: 39000 | B132: 207 | C132: 6.3196852 | D132: =C132*$K$3 -> 12.63937 | E132: 21.595502 | F132: =ABS(E132-E131) -> 0.4983456 | G132: =E132*$J$3 -> 194.35951 | H132: 51.986403 | W132: 44.1 | X132: =X131+((W132-W131)*(X133-X131))/(W133-W131) -> 35013.333 | AL132: =$AE$26*E132^2+$AF$26*E132+$AG$26 -> 34.948337
A133: 39300 | B133: 205 | C133: 3.9941027 | D133: =C133*$K$3 -> 7.9882053 | E133: 21.890074 | F133: =ABS(E133-E132) -> 0.29457232 | G133: =E133*$J$3 -> 197.01067 | H133: 51.593723 | W133: 50 | X133: 24000 | AL133: =$AE$26*E133^2+$AF$26*E133+$AG$26 -> 35.432181
A134: 39600 | B134: 228 | C134: 11.788917 | D134: =C134*$K$3 -> 23.577835 | E134: 22.713417 | F134: =ABS(E134-E133) -> 0.82334294 | G134: =E134*$J$3 -> 204.42075 | H134: 50.94813 | AL134: =$AE$26*E134^2+$AF$26*E134+$AG$26 -> 36.787241
A135: 39900 | B135: 268 | C135: 21.746521 | D135: =C135*$K$3 -> 43.493042 | E135: 24.945009 | F135: =ABS(E135-E134) -> 2.231592 | G135: =E135*$J$3 -> 224.50508 | H135: 49.599486 | AL135: =$AE$26*E135^2+$AF$26*E135+$AG$26 -> 40.479936
A136: 40200 | B136: 303 | C136: 24.219087 | D136: =C136*$K$3 -> 48.438174 | E136: 28.284387 | F136: =ABS(E136-E135) -> 3.3393779 | G136: =E136*$J$3 -> 254.55948 | H136: 47.791979 | AL136: =$AE$26*E136^2+$AF$26*E136+$AG$26 -> 46.060132
A137: 40500 | B137: 326 | C137: 19.880109 | D137: =C137*$K$3 -> 39.760218 | E137: 31.804114 | F137: =ABS(E137-E136) -> 3.5197267 | G137: =E137*$J$3 -> 286.23702 | H137: 46.083503 | AL137: =$AE$26*E137^2+$AF$26*E137+$AG$26 -> 52.012298
A138: 40800 | B138: 326 | C138: 7.860349 | D138: =C138*$K$3 -> 15.720698 | E138: 34.475157 | F138: =ABS(E138-E137) -> 2.6710435 | G138: =E138*$J$3 -> 310.27641 | H138: 45.045272 | AL138: =$AE$26*E138^2+$AF$26*E138+$AG$26 -> 56.577625
A139: 41100 | B139: 326 | C139: 0.75465186 | D139: =C139*$K$3 -> 1.5093037 | E139: 36.054171 | F139: =ABS(E139-E138) -> 1.5790138 | G139: =E139*$J$3 -> 324.48754 | H139: 44.735991 | AL139: =$AE$26*E139^2+$AF$26*E139+$AG$26 -> 59.296089
...

Sheet Finland_ports_600LPF_125Ah
A1: Time (sec) | B1: Load Profile (kW) | C1: Battery power (kW) | D1: Total Batt Power (kW) | E1: FC power (kW) | F1: Abs(Pfc(t)-Pfc(t-1) | G1: TotalFC power(kw) | H1: Battery SoC (%) | AK1: Sampling_dt(sec) | AL1: Sampling_dt(hrs) | AM1: Fuel consumption (f(pfc)) for 1 FC (kW) | AN1: Addit_Ploss(kW) | AO1: Fctotal(kw) | AQ1: FC_total*hrs(kwh) | AR1: Ke-m ( kg/kwh) | AS1: Fuel consumption (kg) | AU1: H2 in $/kg | AV1: Fuel cost | AW1: H2 price in $/kwh | AY1: Fuel cost ($)
A2: 0 | B2: 0 | C2: 12.350136 | D2: =$K$3*C2 -> 24.700273 | E2: 0 | F2: 0 | G2: =$J$3*E2 -> 0 | H2: 50 | J2: Nfc | K2: Nbat | AK2: 300 | AL2: =AK2/3600 -> 0.083333333 | AM2: =$AF$26*E2^2+$AG$26*E2+$AH$26 -> 0.8595 | AO2: =J3*AM103+AN2 -> 95615.187 | AQ2: =AO2*AL2 -> 7967.9323 | AR2: 0.03 | AS2: =AQ2*AR2 -> 239.03797 | AU2: 4 | AV2: =AU2*AS2 -> 956.15187 | AW2: =AU2/33.35 -> 0.11994003 | AY2: =AQ2*AW2 -> 955.67403
A3: 300 | B3: 0 | C3: -0.075000176 | D3: =$K$3*C3 -> -0.15000035 | E3: 0.016667063 | F3: =ABS(E3-E2) -> 0.016667063 | G3: =$J$3*E3 -> 0.15000356 | H3: 50.542869 | J3: 9 | K3: 2 | AM3: =$AF$26*E3^2+$AG$26*E3+$AH$26 -> 0.88475741
A4: 600 | B4: 24 | C4: 11.999908 | D4: =$K$3*C4 -> 23.999816 | E4: 2.981693e-05 | F4: =ABS(E4-E3) -> 0.016637246 | G4: =$J$3*E4 -> 0.00026835237 | H4: 50.078835 | AG4: Fuel consumption | AM4: =$AF$26*E4^2+$AG$26*E4+$AH$26 -> 0.85954518 | AR4: *Source: Cost-effective control of Roll-on/Roll-off Emission-Free Ships
A5: 900 | B5: 85 | C5: 29.276072 | D5: =$K$3*C5 -> 58.552144 | E5: 2.9386053 | F5: =ABS(E5-E4) -> 2.9385754 | G5: =$J$3*E5 -> 26.447447 | H5: 48.21991 | AM5: =$AF$26*E5^2+$AG$26*E5+$AH$26 -> 5.3377989 | AR5: CHECK END OF LIFE INCREASE IN kg | AS5: =AS2+25.29%*AS2 -> 299.49067
A6: 1200 | B6: 116 | C6: 25.761904 | D6: =$K$3*C6 -> 51.523809 | E6: 7.1639838 | F6: =ABS(E6-E5) -> 4.2253785 | G6: =$J$3*E6 -> 64.475854 | H6: 46.062143 | K6: DC BUS VOLTAGE | AM6: =$AF$26*E6^2+$AG$26*E6+$AH$26 -> 11.865607 | AR6: 25.29% increase in kg due to FC degrad
A7: 1500 | B7: 108 | C7: 7.5599843 | D7: =$K$3*C7 -> 15.119969 | E7: 10.31997 | F7: =ABS(E7-E6) -> 3.1559862 | G7: =$J$3*E7 -> 92.87973 | H7: 44.829347 | AM7: =$AF$26*E7^2+$AG$26*E7+$AH$26 -> 16.809432
A8: 1800 | B8: 105 | C8: -0.95221036 | D8: =$K$3*C8 -> -1.9044207 | E8: 11.878231 | F8: =ABS(E8-E7) -> 1.5582608 | G8: =$J$3*E8 -> 106.90408 | H8: 44.605025 | AM8: =$AF$26*E8^2+$AG$26*E8+$AH$26 -> 19.271918
A9: 2100 | B9: 117 | C9: 0.0091042133 | D9: =$K$3*C9 -> 0.018208427 | E9: 12.997927 | F9: =ABS(E9-E8) -> 1.119696 | G9: =$J$3*E9 -> 116.98134 | H9: 44.638001 | AM9: =$AF$26*E9^2+$AG$26*E9+$AH$26 -> 21.050118
A10: 2400 | B10: 219 | C10: 33.772294 | D10: =$K$3*C10 -> 67.544588 | E10: 16.828229 | F10: =ABS(E10-E9) -> 3.8303022 | G10: =$J$3*E10 -> 151.45406 | H10: 43.179598 | AM10: =$AF$26*E10^2+$AG$26*E10+$AH$26 -> 27.188507
A11: 2700 | B11: 283 | C11: 36.355104 | D11: =$K$3*C11 -> 72.710208 | E11: 23.365304 | F11: =ABS(E11-E10) -> 6.5370749 | G11: =$J$3*E11 -> 210.28774 | H11: 40.411896 | AM11: =$AF$26*E11^2+$AG$26*E11+$AH$26 -> 37.86293
A12: 3000 | B12: 221 | C12: -10.865427 | D12: =$K$3*C12 -> -21.730855 | E12: 26.969969 | F12: =ABS(E12-E11) -> 3.6046655 | G12: =$J$3*E12 -> 242.72973 | H12: 39.594992 | AM12: =$AF$26*E12^2+$AG$26*E12+$AH$26 -> 43.855919
A13: 3300 | B13: 209 | C13: -17.641434 | D13: =$K$3*C13 -> -35.282869 | E13: 27.142357 | F13: =ABS(E13-E12) -> 0.17238754 | G13: =$J$3*E13 -> 244.28121 | H13: 40.730939 | AM13: =$AF$26*E13^2+$AG$26*E13+$AH$26 -> 44.144429
A14: 3600 | B14: 134 | C14: -43.968403 | D14: =$K$3*C14 -> -87.936806 | E14: 24.659534 | F14: =ABS(E14-E13) -> 2.4828228 | G14: =$J$3*E14 -> 221.93581 | H14: 43.220176 | AM14: =$AF$26*E14^2+$AG$26*E14+$AH$26 -> 40.005927
A15: 3900 | B15: 152 | C15: -21.292454 | D15: =$K$3*C15 -> -42.584909 | E15: 21.620402 | F15: =ABS(E15-E14) -> 3.0391325 | G15: =$J$3*E15 -> 194.58362 | H15: 45.662993 | AM15: =$AF$26*E15^2+$AG$26*E15+$AH$26 -> 34.989216
A16: 4200 | B16: 227 | C16: 13.60631 | D16: =$K$3*C16 -> 27.212621 | E16: 22.198406 | F16: =ABS(E16-E15) -> 0.57800385 | G16: =$J$3*E16 -> 199.78565 | H16: 45.825347 | AM16: =$AF$26*E16^2+$AG$26*E16+$AH$26 -> 35.93917
A17: 4500 | B17: 226 | C17: 3.7630417 | D17: =$K$3*C17 -> 7.5260833 | E17: 24.274724 | F17: =ABS(E17-E16) -> 2.076318 | G17: =$J$3*E17 -> 218.47251 | H17: 45.18557 | AM17: =$AF$26*E17^2+$AG$26*E17+$AH$26 -> 39.367731
A18: 4800 | B18: 211 | C18: -7.0602508 | D18: =$K$3*C18 -> -14.120502 | E18: 25.013237 | F18: =ABS(E18-E17) -> 0.73851385 | G18: =$J$3*E18 -> 225.11914 | H18: 45.355631 | AM18: =$AF$26*E18^2+$AG$26*E18+$AH$26 -> 40.593296
... A20: 5400 | B20: 226 | C20: 1.3943771 | D20: =$K$3*C20 -> 2.7887543 | E20: 24.801061 | F20: =ABS(E20-E19) -> 0.15864867 | G20: =$J$3*E20 -> 223.20955 | H20: 46.468697 | AM20: =$AF$26*E20^2+$AG$26*E20+$AH$26 -> 40.240861
A21: 5700 | B21: 229 | C21: -0.67352585 | D21: =$K$3*C21 -> -1.3470517 | E21: 25.59394 | F21: =ABS(E21-E20) -> 0.79287967 | G21: =$J$3*E21 -> 230.34546 | H21: 46.448602 | AF21: Fuel consumption (kW) in y axis | AM21: =$AF$26*E21^2+$AG$26*E21+$AH$26 -> 41.559213
A22: 6000 | B22: 221 | C22: -5.8787648 | D22: =$K$3*C22 -> -11.75753 | E22: 25.861778 | F22: =ABS(E22-E21) -> 0.26783771 | G22: =$J$3*E22 -> 232.756 | H22: 46.723653 | AF22: Power output (kW) in x axis | AM22: =$AF$26*E22^2+$AG$26*E22+$AH$26 -> 42.005388
A23: 6300 | B23: 207 | C23: -10.667456 | D23: =$K$3*C23 -> -21.334912 | E23: 25.370387 | F23: =ABS(E23-E22) -> 0.49139071 | G23: =$J$3*E23 -> 228.33349 | H23: 47.38548 | AM23: =$AF$26*E23^2+$AG$26*E23+$AH$26 -> 41.187131
A24: 6600 | B24: 220 | C24: -2.6422705 | D24: =$K$3*C24 -> -5.284541 | E24: 25.031437 | F24: =ABS(E24-E23) -> 0.33895 | G24: =$J$3*E24 -> 225.28294 | H24: 47.872401 | AM24: =$AF$26*E24^2+$AG$26*E24+$AH$26 -> 40.623538
A25: 6900 | B25: 220 | C25: -2.9140526 | D25: =$K$3*C25 -> -5.8281052 | E25: 25.091845 | F25: =ABS(E25-E24) -> 0.060407417 | G25: =$J$3*E25 -> 225.8266 | H25: 48.089713 | AF25: k1 | AG25: k2 | AH25: k3 | AM25: =$AF$26*E25^2+$AG$26*E25+$AH$26 -> 40.723932
A26: 7200 | B26: 215 | C26: -4.7665969 | D26: =$K$3*C26 -> -9.5331938 | E26: 24.947972 | F26: =ABS(E26-E25) -> 0.14387264 | G26: =$J$3*E26 -> 224.53175 | H26: 48.395699 | AF26: 0.00292448 | AG26: 1.51536 | AH26: 0.8595 | AM26: =$AF$26*E26^2+$AG$26*E26+$AH$26 -> 40.484859
A27: 7500 | B27: 174 | C27: -18.945865 | D27: =$K$3*C27 -> -37.89173 | E27: 23.54341 | F27: =ABS(E27-E26) -> 1.4045622 | G27: =$J$3*E27 -> 211.89069 | H27: 49.370929 | AM27: =$AF$26*E27^2+$AG$26*E27+$AH$26 -> 38.157258
A28: 7800 | B28: 120 | C28: -30.496477 | D28: =$K$3*C28 -> -60.992953 | E28: 20.110246 | F28: =ABS(E28-E27) -> 3.4331639 | G28: =$J$3*E28 -> 180.99221 | H28: 51.330724 | AM28: =$AF$26*E28^2+$AG$26*E28+$AH$26 -> 32.516486
A29: 8100 | B29: 198 | C29: 13.978826 | D29: =$K$3*C29 -> 27.957651 | E29: 18.893452 | F29: =ABS(E29-E28) -> 1.2167941 | G29: =$J$3*E29 -> 170.04107 | H29: 51.797126 | AM29: =$AF$26*E29^2+$AG$26*E29+$AH$26 -> 30.533811
A30: 8400 | B30: 366 | C30: 70.870628 | D30: =$K$3*C30 -> 141.74126 | E30: 24.917255 | F30: =ABS(E30-E29) -> 6.023803 | G30: =$J$3*E30 -> 224.25529 | H30: 48.233346 | AM30: =$AF$26*E30^2+$AG$26*E30+$AH$26 -> 40.433832
A31: 8700 | B31: 667 | C31: 68.490711 | D31: =$K$3*C31 -> 136.98142 | E31: 55.022321 | F31: =ABS(E31-E30) -> 30.105066 | G31: =$J$3*E31 -> 495.20089 | H31: 42.39004 | AM31: =$AF$26*E31^2+$AG$26*E31+$AH$26 -> 93.091858
A32: 9000 | B32: 864 | C32: 57.944805 | D32: =$K$3*C32 -> 115.88961 | E32: 79.652226 | F32: =ABS(E32-E31) -> 24.629905 | G32: =$J$3*E32 -> 716.87003 | H32: 37.418592 | AF32: BATTERY DEGRADATION | AM32: =$AF$26*E32^2+$AG$26*E32+$AH$26 -> 140.11559
A33: 9300 | B33: 847 | C33: 26.563231 | D33: =$K$3*C33 -> 53.126462 | E33: 88.20565 | F33: =ABS(E33-E32) -> 8.5534242 | G33: =$J$3*E33 -> 793.85085 | H33: 33.947226 | AM33: =$AF$26*E33^2+$AG$26*E33+$AH$26 -> 157.27596
A34: 9600 | B34: 836 | C34: 3.1795292 | D34: =$K$3*C34 -> 6.3590584 | E34: 92.179501 | F34: =ABS(E34-E33) -> 3.9738502 | G34: =$J$3*E34 -> 829.6155 | H34: 32.849093 | AE34: DoD = maxSoC - minSoC = | AG34: 40.6059 | AM34: =$AF$26*E34^2+$AG$26*E34+$AH$26 -> 165.39411
A35: 9900 | B35: 787 | C35: -27.325184 | D35: =$K$3*C35 -> -54.650368 | E35: 93.513948 | F35: =ABS(E35-E34) -> 1.3344478 | G35: =$J$3*E35 -> 841.62554 | H35: 33.87432 | AM35: =$AF$26*E35^2+$AG$26*E35+$AH$26 -> 168.14096
A36: 10200 | B36: 837 | C36: -5.9672112 | D36: =$K$3*C36 -> -11.934422 | E36: 94.32277 | F36: =ABS(E36-E35) -> 0.80882197 | G36: =$J$3*E36 -> 848.90493 | H36: 35.113299 | AM36: =$AF$26*E36^2+$AG$26*E36+$AH$26 -> 169.81092
A37: 10500 | B37: 843 | C37: -9.4919618 | D37: =$K$3*C37 -> -18.983924 | E37: 95.772795 | F37: =ABS(E37-E36) -> 1.4500249 | G37: =$J$3*E37 -> 861.95516 | H37: 35.726143 | AM37: =$AF$26*E37^2+$AG$26*E37+$AH$26 -> 172.81435
A38: 10800 | B38: 840 | C38: -15.043842 | D38: =$K$3*C38 -> -30.087684 | E38: 96.673177 | F38: =ABS(E38-E37) -> 0.90038202 | G38: =$J$3*E38 -> 870.0586 | H38: 36.696879 | AM38: =$AF$26*E38^2+$AG$26*E38+$AH$26 -> 174.68549
A39: 11100 | B39: 857 | C39: -9.9178047 | D39: =$K$3*C39 -> -19.835609 | E39: 97.422786 | F39: =ABS(E39-E38) -> 0.74960881 | G39: =$J$3*E39 -> 876.80507 | H39: 37.655322 | AM39: =$AF$26*E39^2+$AG$26*E39+$AH$26 -> 176.24692
A40: 11400 | B40: 867 | C40: -8.941699 | D40: =$K$3*C40 -> -17.883398 | E40: 98.316938 | F40: =ABS(E40-E39) -> 0.89415231 | G40: =$J$3*E40 -> 884.85245 | H40: 38.387015 | AM40: =$AF$26*E40^2+$AG$26*E40+$AH$26 -> 178.11372
A41: 11700 | B41: 852 | C41: -18.130676 | D41: =$K$3*C41 -> -36.261351 | E41: 98.692352 | F41: =ABS(E41-E40) -> 0.37541332 | G41: =$J$3*E41 -> 888.23117 | H41: 39.464028 | AM41: =$AF$26*E41^2+$AG$26*E41+$AH$26 -> 178.8989
A42: 12000 | B42: 849 | C42: -18.59191 | D42: =$K$3*C42 -> -37.183819 | E42: 98.461477 | F42: =ABS(E42-E41) -> 0.23087517 | G42: =$J$3*E42 -> 886.15329 | H42: 40.891593 | AM42: =$AF$26*E42^2+$AG$26*E42+$AH$26 -> 178.41593
A43: 12300 | B43: 839 | C43: -20.985691 | D43: =$K$3*C43 -> -41.971381 | E43: 97.8824 | F43: =ABS(E43-E42) -> 0.57907655 | G43: =$J$3*E43 -> 880.9416 | H43: 42.433619 | AM43: =$AF$26*E43^2+$AG$26*E43+$AH$26 -> 177.20591
A44: 12600 | B44: 839 | C44: -17.621066 | D44: =$K$3*C44 -> -35.242132 | E44: 97.134724 | F44: =ABS(E44-E43) -> 0.74767573 | G44: =$J$3*E44 -> 874.21252 | H44: 43.922454 | AM44: =$AF$26*E44^2+$AG$26*E44+$AH$26 -> 175.6465
A45: 12900 | B45: 845 | C45: -12.184231 | D45: =$K$3*C45 -> -24.368463 | E45: 96.593226 | F45: =ABS(E45-E44) -> 0.54149855 | G45: =$J$3*E45 -> 869.33903 | H45: 45.064709 | AM45: =$AF$26*E45^2+$AG$26*E45+$AH$26 -> 174.51914
A46: 13200 | B46: 839 | C46: -12.952569 | D46: =$K$3*C46 -> -25.905137 | E46: 96.097399 | F46: =ABS(E46-E45) -> 0.49582678 | G46: =$J$3*E46 -> 864.87659 | H46: 46.042233 | AM46: =$AF$26*E46^2+$AG$26*E46+$AH$26 -> 173.48838
... A78: 22800 | B78: 859 | C78: -1.1556205 | D78: =$K$3*C78 -> -2.3112409 | E78: 95.698066 | F78: =ABS(E78-E77) -> 0.14977568 | G78: =$J$3*E78 -> 861.28259 | H78: 49.583103 | AM78: =$AF$26*E78^2+$AG$26*E78+$AH$26 -> 172.65926
A79: 23100 | B79: 862 | C79: 0.25397733 | D79: =$K$3*C79 -> 0.50795467 | E79: 95.718158 | F79: =ABS(E79-E78) -> 0.020092333 | G79: =$J$3*E79 -> 861.46342 | H79: 49.61435 | AG79: EC (@40.6 % DoD) | AH79: Max cycles at 40.6% DoD | AM79: =$AF$26*E79^2+$AG$26*E79+$AH$26 -> 172.70095
A80: 23400 | B80: 864 | C80: 0.76765314 | D80: =$K$3*C80 -> 1.5353063 | E80: 95.826226 | F80: =ABS(E80-E79) -> 0.10806747 | G80: =$J$3*E80 -> 862.43603 | H80: 49.573273 | AG80: 1.32 | AH80: 71000 | AM80: =$AF$26*E80^2+$AG$26*E80+$AH$26 -> 172.92525
A81: 23700 | B81: 857 | C81: -2.5899453 | D81: =$K$3*C81 -> -5.1798906 | E81: 95.794625 | F81: =ABS(E81-E80) -> 0.031600428 | G81: =$J$3*E81 -> 862.15163 | H81: 49.653007 | AM81: =$AF$26*E81^2+$AG$26*E81+$AH$26 -> 172.85966
A82: 24000 | B82: 685 | C82: -71.802668 | D82: =$K$3*C82 -> -143.60534 | E82: 92.065075 | F82: =ABS(E82-E81) -> 3.7295502 | G82: =$J$3*E82 -> 828.58567 | H82: 52.700019 | AM82: =$AF$26*E82^2+$AG$26*E82+$AH$26 -> 165.15906
A83: 24300 | B83: 485 | C83: -69.212272 | D83: =$K$3*C83 -> -138.42454 | E83: 71.552134 | F83: =ABS(E83-E82) -> 20.512941 | G83: =$J$3*E83 -> 643.96921 | H83: 58.389152 | AM83: =$AF$26*E83^2+$AG$26*E83+$AH$26 -> 124.25923
A84: 24600 | B84: 481 | C84: -38.599752 | D84: =$K$3*C84 -> -77.199503 | E84: 62.020989 | F84: =ABS(E84-E83) -> 9.5311451 | G84: =$J$3*E84 -> 558.1889 | H84: 62.54078 | AM84: =$AF$26*E84^2+$AG$26*E84+$AH$26 -> 106.09294
A85: 24900 | B85: 496 | C85: -8.1381445 | D85: =$K$3*C85 -> -16.276289 | E85: 56.918599 | F85: =ABS(E85-E84) -> 5.1023901 | G85: =$J$3*E85 -> 512.26739 | H85: 64.246112 | AM85: =$AF$26*E85^2+$AG$26*E85+$AH$26 -> 96.586184
A86: 25200 | B86: 475 | C86: -3.2765917 | D86: =$K$3*C86 -> -6.5531835 | E86: 53.505134 | F86: =ABS(E86-E85) -> 3.4134652 | G86: =$J$3*E86 -> 481.5462 | H86: 64.673106 | AM86: =$AF$26*E86^2+$AG$26*E86+$AH$26 -> 90.311239
A87: 25500 | B87: 477 | C87: 8.7130676 | D87: =$K$3*C87 -> 17.426135 | E87: 51.063018 | F87: =ABS(E87-E86) -> 2.4421153 | G87: =$J$3*E87 -> 459.56716 | H87: 64.421148 | AM87: =$AF$26*E87^2+$AG$26*E87+$AH$26 -> 85.863738
A88: 25800 | B88: 434 | C88: -1.9099903 | D88: =$K$3*C88 -> -3.8199806 | E88: 48.646085 | F88: =ABS(E88-E87) -> 2.4169329 | G88: =$J$3*E88 -> 437.81477 | H88: 64.194868 | AM88: =$AF$26*E88^2+$AG$26*E88+$AH$26 -> 81.496443
A89: 26100 | B89: 377 | C89: -13.164462 | D89: =$K$3*C89 -> -26.328924 | E89: 44.813863 | F89: =ABS(E89-E88) -> 3.8322225 | G89: =$J$3*E89 -> 403.32477 | H89: 64.819802 | AM89: =$AF$26*E89^2+$AG$26*E89+$AH$26 -> 74.641817
A90: 26400 | B90: 234 | C90: -49.42534 | D90: =$K$3*C90 -> -98.850679 | E90: 37.157214 | F90: =ABS(E90-E89) -> 7.6566487 | G90: =$J$3*E90 -> 334.41493 | H90: 67.434305 | AM90: =$AF$26*E90^2+$AG$26*E90+$AH$26 -> 61.203764
A91: 26700 | B91: 139 | C91: -41.742447 | D91: =$K$3*C91 -> -83.484894 | E91: 24.78811 | F91: =ABS(E91-E90) -> 12.369104 | G91: =$J$3*E91 -> 223.09299 | H91: 70.898712 | AM91: =$AF$26*E91^2+$AG$26*E91+$AH$26 -> 40.219358
A92: 27000 | B92: 110 | C92: -17.549578 | D92: =$K$3*C92 -> -35.099156 | E92: 16.122064 | F92: =ABS(E92-E91) -> 8.666046 | G92: =$J$3*E92 -> 145.09857 | H92: 73.09811 | AM92: =$AF$26*E92^2+$AG$26*E92+$AH$26 -> 26.050364
... A102: 30000 | B102: 0 | C102: -0.0075097218 | D102: =$K$3*C102 -> -0.015019444 | E102: 0.0016687671 | F102: =ABS(E102-E101) -> 0.27685233 | G102: =$J$3*E102 -> 0.015018904 | H102: 62.937393 | AM102: =$AF$26*E102^2+$AG$26*E102+$AH$26 -> 0.86202879
E103: SUM(ABS(Pfc(t)-Pfc(t-1) | F103: =SUM(F2:F102) -> 242.28018 | AL103: SUM | AM103: =SUM(AM2:AM102) -> 10623.91
A106: TRANSIENT DEGRADATION
A107: Coeff | B107: 0.4185 | C107: Microvolt/DkW
A108: sum(Abs(Pfc(t)-Pfc(t-1))) | B108: =F103 -> 242.28018 | C108: DkW | D108: FROM: Integrated design and control optimization of fuel cell hybrid mining truck with minimized lifecycle cost
A109: TotalTransient Degrad | B109: =B108*B107 -> 101.39425 | C109: microvolt | D109: WHERE THEY GIVE 0.4185 microvolt for load changing degradation which is also for a same size of FC… | AE109: PRAXIS BATTERIES
AD110: 513.01 GreenBattery Rev1.12 A4.cdr (praxis-automation.eu)
A111: START/STOP CYCLE
A112: Cycles | B112: 1 | C112: Cycles | D112: Always 1 start/stop cycle start from 0 and end to 0 at end of voyage
A113: MicroVolt/cycle | B113: 23.91 | C113: Microvolt/cycle
A114: Total start/stop Degrad | B114: =B113*B112 -> 23.91 | C114: microvolt
A116: Low Power operation (<10% rated power) | C116: Power <15 kW
A117: Coeff | B117: 10.17 | C117: Microvolt/hr
A118: Hours of low power oper | B118: =(35+45)/60 -> 1.3333333 | C118: hrs | D118: Add minutes in intervals and convert to hours dividing by 60 | E118: REF
A119: Total LPO degrad | B119: =B118*B117 -> 13.56 | C119: microvolt | E119: Synthesis of degradation mechanisms and of their impacts on degradation
E120: rates on proton-exchange membrane fuel cells and lithium-ion
A121: High Power operation (>90% rated power) | C121: Power > 135 kW | E121: nickel–manganese–cobalt batteries in hybrid transport application | AD121: DoD(%) | AE121: Cycles (1C)
A122: Coeff | B122: 11.74 | C122: Microvolt/hr | AD122: 5 | AE122: 180000
A123: Hours of high power oper | B123: 0 | C123: hrs | E123: and Fletcher study | M123: An energy management strategy to concurrently optimise fuel con_x0002_sumption & PEM fuel cell lifetime in a hybrid vehicle | AD123: 10 | AE123: 130000
A124: Total HPO degrad | B124: =B123*B122 -> 0 | C124: microvolt | AD124: 20 | AE124: 80000
AD125: 50 | AE125: 24000
AD126: 80 | AE126: 6200 | AK126: EC (@40.6% DoD) | AL126: Max cycles at 40.6% DoD
AD127: 90 | AE127: 5000 | AK127: 1.32 | AL127: =AE134 -> 41546.667
A131: Colors
A132: Transient | B132: No color | AD132: x | AE132: y
A133: LPO | B133: orange | AD133: 20 | AE133: 80000
A134: HPO | B134: Red | AD134: 40.6 | AE134: =AE133+((AD134-AD133)*(AE135-AE133))/(AD135-AD133) -> 41546.667
A135: Constant | B135: - | AD135: 50 | AE135: 24000
A139: TOTAL DEGRAD | B139: =B129+B124+B119+B114+B109 -> 138.86425 | C139: microvolt

Sheet Finland_SSweden_600LPF_125Ah
A1: Time (sec) | B1: Load Profile (kW) | C1: Battery power (kW) | D1: Total Batt Power (kW) | E1: FC power (kW) | F1: Abs(Pfc(t)-Pfc(t-1) | G1: TotalFC power(kw) | H1: Battery SoC (%) | AK1: Sampling_dt(sec) | AL1: Sampling_dt(hrs) | AM1: Fuel consumption (f(pfc)) for 1 FC (kW) | AN1: Addit_Ploss(kW) | AO1: Fctotal(kw) | AQ1: FC_total*hrs(kwh) | AR1: Ke-m ( kg/kwh) | AS1: Fuel consumption (kg) | AU1: H2 in $/kg | AV1: Fuel cost | AW1: H2 price in $/kwh | AY1: Fuel cost ($)
A2: 0 | B2: 0 | C2: 12.350136 | D2: =$K$3*C2 -> 24.700273 | E2: 0 | F2: 0 | G2: =$J$3*E2 -> 0 | H2: 50 | J2: Nfc | K2: Nbat | AK2: 300 | AL2: =AK2/3600 -> 0.083333333 | AM2: =$AF$28*E2^2+$AG$28*E2+$AH$28 -> 0.8595 | AO2: =J3*AM864+AN2 -> 896545.62 | AQ2: =AO2*AL2 -> 74712.135 | AR2: 0.03 | AS2: =AQ2*AR2 -> 2241.364 | AU2: 4 | AV2: =AU2*AS2 -> 8965.4562 | AW2: =AU2/33.35 -> 0.11994003 | AY2: =AQ2*AW2 -> 8960.9757
A3: 300 | B3: 0 | C3: -0.075000176 | D3: =$K$3*C3 -> -0.15000035 | E3: 0.016667063 | F3: =ABS(E3-E2) -> 0.016667063 | G3: =$J$3*E3 -> 0.15000356 | H3: 50.542869 | J3: 9 | K3: 2 | AM3: =$AF$28*E3^2+$AG$28*E3+$AH$28 -> 0.88475741
A4: 600 | B4: 19 | C4: 9.4998992 | D4: =$K$3*C4 -> 18.999798 | E4: 2.9708356e-05 | F4: =ABS(E4-E3) -> 0.016637354 | G4: =$J$3*E4 -> 0.00026737521 | H4: 50.175835 | AM4: =$AF$28*E4^2+$AG$28*E4+$AH$28 -> 0.85954502 | AR4: *Source: Cost-effective control of Roll-on/Roll-off Emission-Free Ships
A5: 900 | B5: 50 | C5: 19.278393 | D5: =$K$3*C5 -> 38.556786 | E5: 1.2714488 | F5: =ABS(E5-E4) -> 1.2714191 | G5: =$J$3*E5 -> 11.443039 | H5: 48.913984 | AM5: =$AF$28*E5^2+$AG$28*E5+$AH$28 -> 2.7909303 | AR5: CHECK END OF LIFE INCREASE IN kg | AS5: =AS2+25.29%*AS2 -> 2808.205
A6: 1200 | B6: 110 | C6: 30.7094 | D6: =$K$3*C6 -> 61.418799 | E6: 5.3978812 | F6: =ABS(E6-E5) -> 4.1264324 | G6: =$J$3*E6 -> 48.580931 | H6: 46.961022 | K6: DC BUS VOLTAGE | AG6: Fuel consumption | AM6: =$AF$28*E6^2+$AG$28*E6+$AH$28 -> 9.1244442 | AR6: 25.29% increase in kg due to FC degrad
A7: 1500 | B7: 124 | C7: 18.936018 | D7: =$K$3*C7 -> 37.872037 | E7: 9.5697314 | F7: =ABS(E7-E6) -> 4.1718502 | G7: =$J$3*E7 -> 86.127582 | H7: 45.059608 | AM7: =$AF$28*E7^2+$AG$28*E7+$AH$28 -> 15.628911
A8: 1800 | B8: 118 | C8: 4.0007855 | D8: =$K$3*C8 -> 8.001571 | E8: 12.222006 | F8: =ABS(E8-E7) -> 2.6522745 | G8: =$J$3*E8 -> 109.99805 | H8: 44.221846 | AM8: =$AF$28*E8^2+$AG$28*E8+$AH$28 -> 19.81709
A9: 2100 | B9: 112 | C9: -4.3442259 | D9: =$K$3*C9 -> -8.6884518 | E9: 13.409782 | F9: =ABS(E9-E8) -> 1.1877762 | G9: =$J$3*E9 -> 120.68804 | H9: 44.268078 | AM9: =$AF$28*E9^2+$AG$28*E9+$AH$28 -> 21.706034
A10: 2400 | B10: 112 | C10: -6.4206418 | D10: =$K$3*C10 -> -12.841284 | E10: 13.871203 | F10: =ABS(E10-E9) -> 0.46142079 | G10: =$J$3*E10 -> 124.84083 | H10: 44.695548 | AM10: =$AF$28*E10^2+$AG$28*E10+$AH$28 -> 22.442066
A11: 2700 | B11: 112 | C11: -7.1872123 | D11: =$K$3*C11 -> -14.374425 | E11: 14.041551 | F11: =ABS(E11-E10) -> 0.17034784 | G11: =$J$3*E11 -> 126.37396 | H11: 45.228388 | AM11: =$AF$28*E11^2+$AG$28*E11+$AH$28 -> 22.71411
A12: 3000 | B12: 112 | C12: -7.1977536 | D12: =$K$3*C12 -> -14.395507 | E12: 14.043893 | F12: =ABS(E12-E11) -> 0.0023425354 | G12: =$J$3*E12 -> 126.39504 | H12: 45.788375 | AM12: =$AF$28*E12^2+$AG$28*E12+$AH$28 -> 22.717852
A13: 3300 | B13: 111 | C13: -7.1656627 | D13: =$K$3*C13 -> -14.331325 | E13: 13.925652 | F13: =ABS(E13-E12) -> 0.11824105 | G13: =$J$3*E13 -> 125.33087 | H13: 46.347261 | AM13: =$AF$28*E13^2+$AG$28*E13+$AH$28 -> 22.529002
A14: 3600 | B14: 124 | C14: -1.5700237 | D14: =$K$3*C14 -> -3.1400473 | E14: 14.126614 | F14: =ABS(E14-E13) -> 0.20096187 | G14: =$J$3*E14 -> 127.13953 | H14: 46.66532 | AM14: =$AF$28*E14^2+$AG$28*E14+$AH$28 -> 22.850019
A15: 3900 | B15: 235 | C15: 37.776748 | D15: =$K$3*C15 -> 75.553497 | E15: 17.716109 | F15: =ABS(E15-E14) -> 3.5894952 | G15: =$J$3*E15 -> 159.44498 | H15: 45.089904 | AM15: =$AF$28*E15^2+$AG$28*E15+$AH$28 -> 28.623662
A16: 4200 | B16: 428 | C16: 64.188244 | D16: =$K$3*C16 -> 128.37649 | E16: 32.040253 | F16: =ABS(E16-E15) -> 14.324143 | G16: =$J$3*E16 -> 288.36227 | H16: 40.366277 | AM16: =$AF$28*E16^2+$AG$28*E16+$AH$28 -> 52.414223
A17: 4500 | B17: 742 | C17: 54.307327 | D17: =$K$3*C17 -> 108.61465 | E17: 65.601597 | F17: =ABS(E17-E16) -> 33.561344 | G17: =$J$3*E17 -> 590.41437 | H17: 35.702684 | AM17: =$AF$28*E17^2+$AG$28*E17+$AH$28 -> 112.85524
A18: 4800 | B18: 926 | C18: 45.930223 | D18: =$K$3*C18 -> 91.860447 | E18: 89.004652 | F18: =ABS(E18-E17) -> 23.403056 | G18: =$J$3*E18 -> 801.04187 | H18: 31.758282 | AM18: =$AF$28*E18^2+$AG$28*E18+$AH$28 -> 158.90082
A19: 5100 | B19: 916 | C19: 20.637062 | D19: =$K$3*C19 -> 41.274124 | E19: 97.188501 | F19: =ABS(E19-E18) -> 8.1838491 | G19: =$J$3*E19 -> 874.69651 | H19: 28.972678 | S19: WE SHOULD SAY THAT THE AS ANDREA SAID..FOR EACH PROFILE | AM19: =$AF$28*E19^2+$AG$28*E19+$AH$28 -> 175.75855
A20: 5400 | B20: 905 | C20: -2.3926231 | D20: =$K$3*C20 -> -4.7852461 | E20: 101.08366 | F20: =ABS(E20-E19) -> 3.8951571 | G20: =$J$3*E20 -> 909.75293 | H20: 28.319208 | S20: WE GET 1 DESIGN…....Pbatmax from the profiles based on the operation of FC it covers the differnece… | AM20: =$AF$28*E20^2+$AG$28*E20+$AH$28 -> 183.91969
A21: 5700 | B21: 738 | C21: -81.496515 | D21: =$K$3*C21 -> -162.99303 | E21: 100.10755 | F21: =ABS(E21-E20) -> 0.97610911 | G21: =$J$3*E21 -> 900.96794 | H21: 31.776453 | S21: Pbat max = Ebatmax/Crate ….assume C-rate = 1… | AM21: =$AF$28*E21^2+$AG$28*E21+$AH$28 -> 181.86621
A22: 6000 | B22: 695 | C22: -80.13257 | D22: =$K$3*C22 -> -160.26514 | E22: 95.026471 | F22: =ABS(E22-E21) -> 5.0810782 | G22: =$J$3*E22 -> 855.23824 | H22: 38.003005 | S22: we should say this as a way to size the batteries. | AM22: =$AF$28*E22^2+$AG$28*E22+$AH$28 -> 171.26696
A23: 6300 | B23: 687 | C23: -60.888276 | D23: =$K$3*C23 -> -121.77655 | E23: 89.861339 | F23: =ABS(E23-E22) -> 5.1651317 | G23: =$J$3*E23 -> 808.75205 | H23: 43.38354 | AF23: Fuel consumption (kW) in y axis | AM23: =$AF$28*E23^2+$AG$28*E23+$AH$28 -> 160.64713
A24: 6600 | B24: 663 | C24: -51.504457 | D24: =$K$3*C24 -> -103.00891 | E24: 85.109789 | F24: =ABS(E24-E23) -> 4.7515499 | G24: =$J$3*E24 -> 765.9881 | H24: 47.689404 | AF24: Power output (kW) in x axis | AM24: =$AF$28*E24^2+$AG$28*E24+$AH$28 -> 151.01546
A25: 6900 | B25: 655 | C25: -36.244655 | D25: =$K$3*C25 -> -72.48931 | E25: 80.83006 | F25: =ABS(E25-E24) -> 4.2797298 | G25: =$J$3*E25 -> 727.47054 | H25: 51.031212 | AM25: =$AF$28*E25^2+$AG$28*E25+$AH$28 -> 142.45322
A26: 7200 | B26: 677 | C26: -12.654784 | D26: =$K$3*C26 -> -25.309568 | E26: 78.032389 | F26: =ABS(E26-E25) -> 2.7976708 | G26: =$J$3*E26 -> 702.2915 | H26: 52.85283 | AM26: =$AF$28*E26^2+$AG$28*E26+$AH$28 -> 136.91398
A27: 7500 | B27: 662 | C27: -11.838963 | D27: =$K$3*C27 -> -23.677926 | E27: 76.18467 | F27: =ABS(E27-E26) -> 1.8477188 | G27: =$J$3*E27 -> 685.66203 | H27: 53.799889 | AF27: k1 | AG27: k2 | AH27: k3 | AM27: =$AF$28*E27^2+$AG$28*E27+$AH$28 -> 133.28069
A28: 7800 | B28: 651 | C28: -9.12053 | D28: =$K$3*C28 -> -18.24106 | E28: 74.358437 | F28: =ABS(E28-E27) -> 1.8262327 | G28: =$J$3*E28 -> 669.22593 | H28: 54.604404 | AF28: 0.00292448 | AG28: 1.51536 | AH28: 0.8595 | AM28: =$AF$28*E28^2+$AG$28*E28+$AH$28 -> 129.70927
A29: 8100 | B29: 650 | C29: -3.0004208 | D29: =$K$3*C29 -> -6.0008415 | E29: 72.887348 | F29: =ABS(E29-E28) -> 1.4710894 | G29: =$J$3*E29 -> 655.98613 | H29: 55.055876 | AM29: =$AF$28*E29^2+$AG$28*E29+$AH$28 -> 126.84656
A30: 8400 | B30: 647 | C30: 0.16050925 | D30: =$K$3*C30 -> 0.32101851 | E30: 71.851647 | F30: =ABS(E30-E29) -> 1.0357008 | G30: =$J$3*E30 -> 646.66482 | H30: 55.156372 | AM30: =$AF$28*E30^2+$AG$28*E30+$AH$28 -> 124.83871
A31: 8700 | B31: 649 | C31: 4.0735405 | D31: =$K$3*C31 -> 8.147081 | E31: 71.204324 | F31: =ABS(E31-E30) -> 0.64732291 | G31: =$J$3*E31 -> 640.83892 | H31: 54.97957 | AM31: =$AF$28*E31^2+$AG$28*E31+$AH$28 -> 123.58696
A32: 9000 | B32: 653 | C32: 7.0638713 | D32: =$K$3*C32 -> 14.127743 | E32: 70.984256 | F32: =ABS(E32-E31) -> 0.22006825 | G32: =$J$3*E32 -> 638.8583 | H32: 54.537029 | AM32: =$AF$28*E32^2+$AG$28*E32+$AH$28 -> 123.16197
A33: 9300 | B33: 651 | C33: 6.1987068 | D33: =$K$3*C33 -> 12.397414 | E33: 70.954314 | F33: =ABS(E33-E32) -> 0.029942006 | G33: =$J$3*E33 -> 638.58883 | H33: 54.023921 | AM33: =$AF$28*E33^2+$AG$28*E33+$AH$28 -> 123.10417
A34: 9600 | B34: 650 | C34: 5.7620129 | D34: =$K$3*C34 -> 11.524026 | E34: 70.940243 | F34: =ABS(E34-E33) -> 0.014070421 | G34: =$J$3*E34 -> 638.46219 | H34: 53.560113 | AF34: BATTERY DEGRADATION | AM34: =$AF$28*E34^2+$AG$28*E34+$AH$28 -> 123.07701
A35: 9900 | B35: 650 | C35: 5.6089445 | D35: =$K$3*C35 -> 11.217889 | E35: 70.974254 | F35: =ABS(E35-E34) -> 0.034010286 | G35: =$J$3*E35 -> 638.76828 | H35: 53.11832 | AM35: =$AF$28*E35^2+$AG$28*E35+$AH$28 -> 123.14266
A36: 10200 | B36: 647 | C36: 4.0672287 | D36: =$K$3*C36 -> 8.1344574 | E36: 70.983533 | F36: =ABS(E36-E35) -> 0.0092795206 | G36: =$J$3*E36 -> 638.8518 | H36: 52.746876 | AE36: DoD | AF36: 35.6 | AM36: =$AF$28*E36^2+$AG$28*E36+$AH$28 -> 123.16057
A37: 10500 | B37: 647 | C37: 4.1044455 | D37: =$K$3*C37 -> 8.208891 | E37: 70.975253 | F37: =ABS(E37-E36) -> 0.0082798408 | G37: =$J$3*E37 -> 638.77728 | H37: 52.428969 | AM37: =$AF$28*E37^2+$AG$28*E37+$AH$28 -> 123.14459
A38: 10800 | B38: 650 | C38: 5.1065724 | D38: =$K$3*C38 -> 10.213145 | E38: 71.085877 | F38: =ABS(E38-E37) -> 0.11062326 | G38: =$J$3*E38 -> 639.77289 | H38: 52.067506 | AM38: =$AF$28*E38^2+$AG$28*E38+$AH$28 -> 123.35818
A39: 11100 | B39: 650 | C39: 4.2967102 | D39: =$K$3*C39 -> 8.5934204 | E39: 71.265847 | F39: =ABS(E39-E38) -> 0.17997034 | G39: =$J$3*E39 -> 641.39262 | H39: 51.704271 | AM39: =$AF$28*E39^2+$AG$28*E39+$AH$28 -> 123.70582
A40: 11400 | B40: 647 | C40: 2.4159221 | D40: =$K$3*C40 -> 4.8318443 | E40: 71.350472 | F40: =ABS(E40-E39) -> 0.08462505 | G40: =$J$3*E40 -> 642.15425 | H40: 51.449145 | AM40: =$AF$28*E40^2+$AG$28*E40+$AH$28 -> 123.86936
A41: 11700 | B41: 648 | C41: 2.7176135 | D41: =$K$3*C41 -> 5.435227 | E41: 71.394525 | F41: =ABS(E41-E40) -> 0.044053214 | G41: =$J$3*E41 -> 642.55073 | H41: 51.248561 | AM41: =$AF$28*E41^2+$AG$28*E41+$AH$28 -> 123.9545
A42: 12000 | B42: 648 | C42: 2.379158 | D42: =$K$3*C42 -> 4.758316 | E42: 71.469737 | F42: =ABS(E42-E41) -> 0.075211898 | G42: =$J$3*E42 -> 643.22763 | H42: 51.051412 | AM42: =$AF$28*E42^2+$AG$28*E42+$AH$28 -> 124.0999
A43: 12300 | B43: 645 | C43: 0.87885399 | D43: =$K$3*C43 -> 1.757708 | E43: 71.469815 | F43: =ABS(E43-E42) -> 7.7303477e-05 | G43: =$J$3*E43 -> 643.22833 | H43: 50.929462 | AM43: =$AF$28*E43^2+$AG$28*E43+$AH$28 -> 124.10005
A44: 12600 | B44: 645 | C44: 1.0948662 | D44: =$K$3*C44 -> 2.1897323 | E44: 71.421804 | F44: =ABS(E44-E43) -> 0.048010273 | G44: =$J$3*E44 -> 642.79624 | H44: 50.852047 | AM44: =$AF$28*E44^2+$AG$28*E44+$AH$28 -> 124.00723
A45: 12900 | B45: 648 | C45: 2.35293 | D45: =$K$3*C45 -> 4.70586 | E45: 71.475555 | F45: =ABS(E45-E44) -> 0.053751182 | G45: =$J$3*E45 -> 643.28 | H45: 50.713993 | AM45: =$AF$28*E45^2+$AG$28*E45+$AH$28 -> 124.11115
A46: 13200 | B46: 645 | C46: 0.65456604 | D46: =$K$3*C46 -> 1.3091321 | E46: 71.519654 | F46: =ABS(E46-E45) -> 0.044098441 | G46: =$J$3*E46 -> 643.67688 | H46: 50.602393 | AM46: =$AF$28*E46^2+$AG$28*E46+$AH$28 -> 124.19642
A47: 13500 | B47: 646 | C47: 1.1525078 | D47: =$K$3*C47 -> 2.3050156 | E47: 71.520098 | F47: =ABS(E47-E46) -> 0.0004441328 | G47: =$J$3*E47 -> 643.68088 | H47: 50.530564 | AM47: =$AF$28*E47^2+$AG$28*E47+$AH$28 -> 124.19727
A48: 13800 | B48: 647 | C48: 1.4025907 | D48: =$K$3*C48 -> 2.8051814 | E48: 71.575632 | F48: =ABS(E48-E47) -> 0.055534365 | G48: =$J$3*E48 -> 644.18069 | H48: 50.430413 | AM48: =$AF$28*E48^2+$AG$28*E48+$AH$28 -> 124.30467
... A82: 24000 | B82: 646 | C82: 0.090216354 | D82: =$K$3*C82 -> 0.18043271 | E82: 71.756151 | F82: =ABS(E82-E81) -> 0.030027051 | G82: =$J$3*E82 -> 645.80536 | H82: 50.0475 | AM82: =$AF$28*E82^2+$AG$28*E82+$AH$28 -> 124.65389
A83: 24300 | B83: 643 | C83: -1.0960024 | D83: =$K$3*C83 -> -2.1920047 | E83: 71.686438 | F83: =ABS(E83-E82) -> 0.06971252 | G83: =$J$3*E83 -> 645.17794 | H83: 50.090333 | AF83: EC at 35.6% DoD | AG83: Max Cycles at 35.6 % DoD | AM83: =$AF$28*E83^2+$AG$28*E83+$AH$28 -> 124.519
A84: 24600 | B84: 643 | C84: -0.59243233 | D84: =$K$3*C84 -> -1.1848647 | E84: 71.574529 | F84: =ABS(E84-E83) -> 0.11190879 | G84: =$J$3*E84 -> 644.17076 | H84: 50.154389 | AF84: 3.46 | AG84: 90000 | AM84: =$AF$28*E84^2+$AG$28*E84+$AH$28 -> 124.30254
A85: 24900 | B85: 644 | C85: 0.13815 | D85: =$K$3*C85 -> 0.27629999 | E85: 71.523288 | F85: =ABS(E85-E84) -> 0.051241066 | G85: =$J$3*E85 -> 643.70959 | H85: 50.169744 | AM85: =$AF$28*E85^2+$AG$28*E85+$AH$28 -> 124.20344
A86: 25200 | B86: 644 | C86: 0.18680963 | D86: =$K$3*C86 -> 0.37361926 | E86: 71.512479 | F86: =ABS(E86-E85) -> 0.010809316 | G86: =$J$3*E86 -> 643.61231 | H86: 50.156953 | AM86: =$AF$28*E86^2+$AG$28*E86+$AH$28 -> 124.18254
A87: 25500 | B87: 645 | C87: 0.60040362 | D87: =$K$3*C87 -> 1.2008072 | E87: 71.531676 | F87: =ABS(E87-E86) -> 0.01919711 | G87: =$J$3*E87 -> 643.78509 | H87: 50.125038 | AM87: =$AF$28*E87^2+$AG$28*E87+$AH$28 -> 124.21966
A88: 25800 | B88: 647 | C88: 1.2180486 | D88: =$K$3*C88 -> 2.4360971 | E88: 71.616636 | F88: =ABS(E88-E87) -> 0.084960308 | G88: =$J$3*E88 -> 644.54973 | H88: 50.052371 | AM88: =$AF$28*E88^2+$AG$28*E88+$AH$28 -> 124.38398
A89: 26100 | B89: 645 | C89: -0.032956055 | D89: =$K$3*C89 -> -0.06591211 | E89: 71.672426 | F89: =ABS(E89-E88) -> 0.055789151 | G89: =$J$3*E89 -> 645.05183 | H89: 50.010229 | AM89: =$AF$28*E89^2+$AG$28*E89+$AH$28 -> 124.4919
A90: 26400 | B90: 642 | C90: -1.1919423 | D90: =$K$3*C90 -> -2.3838845 | E90: 71.596652 | F90: =ABS(E90-E89) -> 0.075774037 | G90: =$J$3*E90 -> 644.36986 | H90: 50.061505 | AM90: =$AF$28*E90^2+$AG$28*E90+$AH$28 -> 124.34532
A91: 26700 | B91: 642 | C91: -0.66680055 | D91: =$K$3*C91 -> -1.3336011 | E91: 71.479949 | F91: =ABS(E91-E90) -> 0.11670225 | G91: =$J$3*E91 -> 643.31954 | H91: 50.132112 | AM91: =$AF$28*E91^2+$AG$28*E91+$AH$28 -> 124.11964
A92: 27000 | B92: 644 | C92: 0.47326361 | D92: =$K$3*C92 -> 0.94652722 | E92: 71.448819 | F92: =ABS(E92-E91) -> 0.031130166 | G92: =$J$3*E92 -> 643.03937 | H92: 50.136035 | AM92: =$AF$28*E92^2+$AG$28*E92+$AH$28 -> 124.05946
A93: 27300 | B93: 646 | C93: 1.1496152 | D93: =$K$3*C93 -> 2.2992303 | E93: 71.520738 | F93: =ABS(E93-E92) -> 0.071918441 | G93: =$J$3*E93 -> 643.68664 | H93: 50.070786 | Z93: PRAXIS BATTERIES | AM93: =$AF$28*E93^2+$AG$28*E93+$AH$28 -> 124.19851
A94: 27600 | B94: 644 | C94: -0.062109949 | D94: =$K$3*C94 -> -0.1242199 | E94: 71.567798 | F94: =ABS(E94-E93) -> 0.047060813 | G94: =$J$3*E94 -> 644.11019 | H94: 50.032316 | Y94: 513.01 GreenBattery Rev1.12 A4.cdr (praxis-automation.eu) | AM94: =$AF$28*E94^2+$AG$28*E94+$AH$28 -> 124.28952
A95: 27900 | B95: 643 | C95: -0.40966324 | D95: =$K$3*C95 -> -0.81932648 | E95: 71.53392 | F95: =ABS(E95-E94) -> 0.03387883 | G95: =$J$3*E95 -> 643.80528 | H95: 50.05176 | AM95: =$AF$28*E95^2+$AG$28*E95+$AH$28 -> 124.224
A96: 28200 | B96: 646 | C96: 0.96825648 | D96: =$K$3*C96 -> 1.936513 | E96: 71.561034 | F96: =ABS(E96-E95) -> 0.027114521 | G96: =$J$3*E96 -> 644.04931 | H96: 50.025692 | AM96: =$AF$28*E96^2+$AG$28*E96+$AH$28 -> 124.27644
A97: 28500 | B97: 647 | C97: 0.98139947 | D97: =$K$3*C97 -> 1.9627989 | E97: 71.669226 | F97: =ABS(E97-E96) -> 0.10819167 | G97: =$J$3*E97 -> 645.02303 | H97: 49.949825 | AM97: =$AF$28*E97^2+$AG$28*E97+$AH$28 -> 124.4857
A98: 28800 | B98: 646 | C98: 0.15655662 | D98: =$K$3*C98 -> 0.31311323 | E98: 71.741416 | F98: =ABS(E98-E97) -> 0.072190252 | G98: =$J$3*E98 -> 645.67274 | H98: 49.908174 | AM98: =$AF$28*E98^2+$AG$28*E98+$AH$28 -> 124.62538
A99: 29100 | B99: 648 | C99: 0.82165077 | D99: =$K$3*C99 -> 1.6433015 | E99: 71.815826 | F99: =ABS(E99-E98) -> 0.07440979 | G99: =$J$3*E99 -> 646.34243 | H99: 49.868043 | AM99: =$AF$28*E99^2+$AG$28*E99+$AH$28 -> 124.76937
A100: 29400 | B100: 647 | C100: 0.011733754 | D100: =$K$3*C100 -> 0.023467508 | E100: 71.884703 | F100: =ABS(E100-E99) -> 0.068876777 | G100: =$J$3*E100 -> 646.96232 | H100: 49.838184 | AM100: =$AF$28*E100^2+$AG$28*E100+$AH$28 -> 124.90269
A101: 29700 | B101: 646 | C101: -0.48614119 | D101: =$K$3*C101 -> -0.97228239 | E101: 71.88423 | F101: =ABS(E101-E100) -> 0.00047230226 | G101: =$J$3*E101 -> 646.95807 | H101: 49.8582 | AM101: =$AF$28*E101^2+$AG$28*E101+$AH$28 -> 124.90178
A102: 30000 | B102: 657 | C102: 3.9477837 | D102: =$K$3*C102 -> 7.8955675 | E102: 72.121084 | F102: =ABS(E102-E101) -> 0.23685388 | G102: =$J$3*E102 -> 649.08976 | H102: 49.709561 | AM102: =$AF$28*E102^2+$AG$28*E102+$AH$28 -> 125.36044
A103: 30300 | B103: 655 | C103: 1.373634 | D103: =$K$3*C103 -> 2.747268 | E103: 72.470921 | F103: =ABS(E103-E102) -> 0.3498368 | G103: =$J$3*E103 -> 652.23829 | H103: 49.510616 | AM103: =$AF$28*E103^2+$AG$28*E103+$AH$28 -> 126.0385
A104: 30600 | B104: 651 | C104: -1.0606578 | D104: =$K$3*C104 -> -2.1213157 | E104: 72.567431 | F104: =ABS(E104-E103) -> 0.096510496 | G104: =$J$3*E104 -> 653.10688 | H104: 49.506088 | AM104: =$AF$28*E104^2+$AG$28*E104+$AH$28 -> 126.22569
A105: 30900 | B105: 652 | C105: -0.54024366 | D105: =$K$3*C105 -> -1.0804873 | E105: 72.562878 | F105: =ABS(E105-E104) -> 0.0045530457 | G105: =$J$3*E105 -> 653.06591 | H105: 49.56671 | Y105: DoD(%) | Z105: Cycles (1C) | AM105: =$AF$28*E105^2+$AG$28*E105+$AH$28 -> 126.21686
A106: 31200 | B106: 645 | C106: -3.340949 | D106: =$K$3*C106 -> -6.681898 | E106: 72.407514 | F106: =ABS(E106-E105) -> 0.15536451 | G106: =$J$3*E106 -> 651.66763 | H106: 49.726333 | Y106: 5 | Z106: 180000 | AM106: =$AF$28*E106^2+$AG$28*E106+$AH$28 -> 125.91555
A107: 31500 | B107: 644 | C107: -2.5424768 | D107: =$K$3*C107 -> -5.0849536 | E107: 72.118959 | F107: =ABS(E107-E106) -> 0.2885549 | G107: =$J$3*E107 -> 649.07063 | H107: 49.952483 | Y107: 10 | Z107: 130000 | AM107: =$AF$28*E107^2+$AG$28*E107+$AH$28 -> 125.35633
A108: 31800 | B108: 647 | C108: -0.35564576 | D108: =$K$3*C108 -> -0.71129152 | E108: 71.966325 | F108: =ABS(E108-E107) -> 0.15263418 | G108: =$J$3*E108 -> 647.69692 | H108: 50.058254 | Y108: 20 | Z108: 80000 | AM108: =$AF$28*E108^2+$AG$28*E108+$AH$28 -> 125.06072
A109: 32100 | B109: 644 | C109: -1.3534561 | D109: =$K$3*C109 -> -2.7069123 | E109: 71.854753 | F109: =ABS(E109-E108) -> 0.11157205 | G109: =$J$3*E109 -> 646.69277 | H109: 50.127821 | Y109: 50 | Z109: 24000 | AM109: =$AF$28*E109^2+$AG$28*E109+$AH$28 -> 124.84472
A110: 32400 | B110: 644 | C110: -0.72193566 | D110: =$K$3*C110 -> -1.4438713 | E110: 71.714412 | F110: =ABS(E110-E109) -> 0.14034075 | G110: =$J$3*E110 -> 645.42971 | H110: 50.206515 | Y110: 80 | Z110: 6200 | AF110: EC (@35.6% DoD) | AG110: Max cycles at 35.6% DoD | AM110: =$AF$28*E110^2+$AG$28*E110+$AH$28 -> 124.57313
A111: 32700 | B111: 644 | C111: -0.2992122 | D111: =$K$3*C111 -> -0.5984244 | E111: 71.620478 | F111: =ABS(E111-E110) -> 0.093933667 | G111: =$J$3*E111 -> 644.58431 | H111: 50.244878 | Y111: 90 | Z111: 5000 | AF111: 3.46 | AG111: =Z117 -> 50880 | AM111: =$AF$28*E111^2+$AG$28*E111+$AH$28 -> 124.39141
A112: 33000 | B112: 646 | C112: 0.76032953 | D112: =$K$3*C112 -> 1.5206591 | E112: 71.607241 | F112: =ABS(E112-E111) -> 0.013237256 | G112: =$J$3*E112 -> 644.46517 | H112: 50.223605 | AM112: =$AF$28*E112^2+$AG$28*E112+$AH$28 -> 124.3658
A113: 33300 | B113: 644 | C113: -0.19765132 | D113: =$K$3*C113 -> -0.39530264 | E113: 71.597917 | F113: =ABS(E113-E112) -> 0.0093238875 | G113: =$J$3*E113 -> 644.38125 | H113: 50.204742 | AM113: =$AF$28*E113^2+$AG$28*E113+$AH$28 -> 124.34777
A114: 33600 | B114: 644 | C114: 0.0097540969 | D114: =$K$3*C114 -> 0.019508194 | E114: 71.551823 | F114: =ABS(E114-E113) -> 0.046094447 | G114: =$J$3*E114 -> 643.9664 | H114: 50.211398 | AM114: =$AF$28*E114^2+$AG$28*E114+$AH$28 -> 124.25862
A115: 33900 | B115: 643 | C115: -0.25618363 | D115: =$K$3*C115 -> -0.51236725 | E115: 71.499815 | F115: =ABS(E115-E114) -> 0.052007937 | G115: =$J$3*E115 -> 643.49833 | H115: 50.221816 | Y115: x | Z115: y | AM115: =$AF$28*E115^2+$AG$28*E115+$AH$28 -> 124.15805
A116: 34200 | B116: 642 | C116: -0.40690547 | D116: =$K$3*C116 -> -0.81381094 | E116: 71.422201 | F116: =ABS(E116-E115) -> 0.077613534 | G116: =$J$3*E116 -> 642.79981 | H116: 50.248073 | Y116: 20 | Z116: 80000 | AM116: =$AF$28*E116^2+$AG$28*E116+$AH$28 -> 124.008
A117: 34500 | B117: 643 | C117: 0.30590504 | D117: =$K$3*C117 -> 0.61181007 | E117: 71.374906 | F117: =ABS(E117-E116) -> 0.047295327 | G117: =$J$3*E117 -> 642.37415 | H117: 50.24975 | Y117: 35.6 | Z117: =Z116+((Y117-Y116)*(Z118-Z116))/(Y118-Y116) -> 50880 | AM117: =$AF$28*E117^2+$AG$28*E117+$AH$28 -> 123.91658
A118: 34800 | B118: 646 | C118: 1.5137141 | D118: =$K$3*C118 -> 3.0274281 | E118: 71.439828 | F118: =ABS(E118-E117) -> 0.0649217 | G118: =$J$3*E118 -> 642.95845 | H118: 50.17517 | Y118: 50 | Z118: 24000 | AM118: =$AF$28*E118^2+$AG$28*E118+$AH$28 -> 124.04208
A119: 35100 | B119: 646 | C119: 1.0032792 | D119: =$K$3*C119 -> 2.0065585 | E119: 71.553262 | F119: =ABS(E119-E118) -> 0.11343423 | G119: =$J$3*E119 -> 643.97936 | H119: 50.078891 | AM119: =$AF$28*E119^2+$AG$28*E119+$AH$28 -> 124.26141
A120: 35400 | B120: 646 | C120: 0.64199534 | D120: =$K$3*C120 -> 1.2839907 | E120: 71.633543 | F120: =ABS(E120-E119) -> 0.080281178 | G120: =$J$3*E120 -> 644.70189 | H120: 50.016053 | AM120: =$AF$28*E120^2+$AG$28*E120+$AH$28 -> 124.41668
A121: 35700 | B121: 641 | C121: -1.5748148 | D121: =$K$3*C121 -> -3.1496296 | E121: 71.570631 | F121: =ABS(E121-E120) -> 0.062911763 | G121: =$J$3*E121 -> 644.13568 | H121: 50.059302 | AM121: =$AF$28*E121^2+$AG$28*E121+$AH$28 -> 124.295
A122: 36000 | B122: 649 | C122: 2.24796 | D122: =$K$3*C122 -> 4.4959199 | E122: 71.60997 | F122: =ABS(E122-E121) -> 0.039338713 | G122: =$J$3*E122 -> 644.48973 | H122: 50.021058 | AM122: =$AF$28*E122^2+$AG$28*E122+$AH$28 -> 124.37108
A123: 36300 | B123: 651 | C123: 2.1286836 | D123: =$K$3*C123 -> 4.2573672 | E123: 71.858706 | F123: =ABS(E123-E122) -> 0.24873569 | G123: =$J$3*E123 -> 646.72835 | H123: 49.851175 | AM123: =$AF$28*E123^2+$AG$28*E123+$AH$28 -> 124.85237
A124: 36600 | B124: 646 | C124: -0.79719933 | D124: =$K$3*C124 -> -1.5943987 | E124: 71.953364 | F124: =ABS(E124-E123) -> 0.094658781 | G124: =$J$3*E124 -> 647.58028 | H124: 49.808601 | AM124: =$AF$28*E124^2+$AG$28*E124+$AH$28 -> 125.03562
A125: 36900 | B125: 644 | C125: -1.3765 | D125: =$K$3*C125 -> -2.7529999 | E125: 71.85987 | F125: =ABS(E125-E124) -> 0.093494397 | G125: =$J$3*E125 -> 646.73883 | H125: 49.894938 | AM125: =$AF$28*E125^2+$AG$28*E125+$AH$28 -> 124.85462
A126: 37200 | B126: 645 | C126: -0.486594 | D126: =$K$3*C126 -> -0.97318799 | E126: 71.773219 | F126: =ABS(E126-E125) -> 0.086651291 | G126: =$J$3*E126 -> 645.95897 | H126: 49.964567 | AM126: =$AF$28*E126^2+$AG$28*E126+$AH$28 -> 124.68692
A127: 37500 | B127: 643 | C127: -1.0955949 | D127: =$K$3*C127 -> -2.1911897 | E127: 71.686344 | F127: =ABS(E127-E126) -> 0.086874366 | G127: =$J$3*E127 -> 645.1771 | H127: 50.027989 | AM127: =$AF$28*E127^2+$AG$28*E127+$AH$28 -> 124.51882
A128: 37800 | B128: 644 | C128: -0.23784435 | D128: =$K$3*C128 -> -0.4756887 | E128: 71.606838 | F128: =ABS(E128-E127) -> 0.079505958 | G128: =$J$3*E128 -> 644.46155 | H128: 50.077128 | AM128: =$AF$28*E128^2+$AG$28*E128+$AH$28 -> 124.36502
A129: 38100 | B129: 643 | C129: -0.48569279 | D129: =$K$3*C129 -> -0.97138557 | E129: 71.550814 | F129: =ABS(E129-E128) -> 0.056024201 | G129: =$J$3*E129 -> 643.95733 | H129: 50.106035 | AM129: =$AF$28*E129^2+$AG$28*E129+$AH$28 -> 124.25667
A130: 38400 | B130: 643 | C130: -0.2215355 | D130: =$K$3*C130 -> -0.44307099 | E130: 71.492112 | F130: =ABS(E130-E129) -> 0.058701955 | G130: =$J$3*E130 -> 643.42901 | H130: 50.132698 | AM130: =$AF$28*E130^2+$AG$28*E130+$AH$28 -> 124.14316
... A863: 258300 | B863: 0 | C863: -2.149201 | D863: =$K$3*C863 -> -4.2984021 | E863: 0.64143016 | F863: =ABS(E863-E862) -> 1.7170824 | G863: =$J$3*E863 -> 5.7728715 | H863: 58.797651 | AM863: =$AF$28*E863^2+$AG$28*E863+$AH$28 -> 1.8327008
E864: SUM(ABS(Pfc(t)-Pfc(t-1) | F864: =SUM(F2:F863) -> 435.38498 | AL864: sum | AM864: =SUM(AM2:AM863) -> 99616.18
A867: TRANSIENT DEGRADATION
...

Sheet sSweden_Nether_600LPF_125Ah
A1: Time (sec) | B1: Load Profile (kW) | C1: Battery power (kW) | D1: Total Batt Power (kW) | E1: FC power (kW) | F1: Abs(Pfc(t)-Pfc(t-1) | G1: TotalFC power(kw) | H1: Battery SoC (%) | AK1: Sampling_dt(sec) | AL1: Sampling_dt(hrs) | AM1: Fuel consumption (f(pfc)) for 1 FC (kW) | AN1: Addit_Ploss(kW) | AO1: Fctotal(kw) | AQ1: FC_total*hrs(kwh) | AR1: Ke-m ( kg/kwh) | AS1: Fuel consumption (kg) | AU1: H2 in $/kg | AV1: Fuel cost | AW1: H2 price in $/kwh | AY1: Fuel cost ($)
A2: 0 | B2: 0 | C2: 12.350136 | D2: =$K$3*C2 -> 24.700273 | E2: 0 | F2: 0 | G2: =$J$3*E2 -> 0 | H2: 50 | J2: Nfc | K2: Nbat | AK2: 300 | AL2: =AK2/3600 -> 0.083333333 | AM2: =$AF$26*E2^2+$AG$26*E2+$AH$26 -> 0.8595 | AO2: =J3*AM1195+AN2 -> 1391281.8 | AQ2: =AO2*AL2 -> 115940.15 | AR2: 0.03 | AS2: =AQ2*AR2 -> 3478.2045 | AU2: 4 | AV2: =AU2*AS2 -> 13912.818 | AW2: =AU2/33.35 -> 0.11994003 | AY2: =AQ2*AW2 -> 13905.865
A3: 300 | B3: 0 | C3: -0.075000176 | D3: =$K$3*C3 -> -0.15000035 | E3: 0.016667063 | F3: =ABS(E3-E2) -> 0.016667063 | G3: =$J$3*E3 -> 0.15000356 | H3: 50.542869 | J3: 9 | K3: 2 | AM3: =$AF$26*E3^2+$AG$26*E3+$AH$26 -> 0.88475741
A4: 600 | B4: 28 | C4: 13.999915 | D4: =$K$3*C4 -> 27.99983 | E4: 2.9905002e-05 | F4: =ABS(E4-E3) -> 0.016637158 | G4: =$J$3*E4 -> 0.00026914502 | H4: 50.001184 | AG4: Fuel consumption | AM4: =$AF$26*E4^2+$AG$26*E4+$AH$26 -> 0.85954532 | AR4: *Source: Cost-effective control of Roll-on/Roll-off Emission-Free Ships
A5: 900 | B5: 112 | C5: 38.878586 | D5: =$K$3*C5 -> 77.757171 | E5: 3.80473 | F5: =ABS(E5-E4) -> 3.8047001 | G5: =$J$3*E5 -> 34.24257 | H5: 47.693339 | AM5: =$AF$26*E5^2+$AG$26*E5+$AH$26 -> 6.6673703 | AR5: CHECK END OF LIFE INCREASE IN kg | AS5: =AS2+25.29%*AS2 -> 4357.8425
A6: 1200 | B6: 197 | C6: 49.912231 | D6: =$K$3*C6 -> 99.824462 | E6: 10.797176 | F6: =ABS(E6-E5) -> 6.9924463 | G6: =$J$3*E6 -> 97.174587 | H6: 44.148804 | K6: DC BUS VOLTAGE | AM6: =$AF$26*E6^2+$AG$26*E6+$AH$26 -> 17.562042 | AR6: 25.29% increase in kg due to FC degrad
A7: 1500 | B7: 298 | C7: 58.80827 | D7: =$K$3*C7 -> 117.61654 | E7: 20.04236 | F7: =ABS(E7-E6) -> 9.2451837 | G7: =$J$3*E7 -> 180.38124 | H7: 39.815618 | AM7: =$AF$26*E7^2+$AG$26*E7+$AH$26 -> 32.405643
A8: 1800 | B8: 340 | C8: 39.040023 | D8: =$K$3*C8 -> 78.080045 | E8: 29.101907 | F8: =ABS(E8-E7) -> 9.0595467 | G8: =$J$3*E8 -> 261.91716 | H8: 36.028233 | AM8: =$AF$26*E8^2+$AG$26*E8+$AH$26 -> 47.436169
A9: 2100 | B9: 456 | C9: 47.239644 | D9: =$K$3*C9 -> 94.479289 | E9: 39.64277 | F9: =ABS(E9-E8) -> 10.540863 | G9: =$J$3*E9 -> 356.78493 | H9: 32.375565 | AM9: =$AF$26*E9^2+$AG$26*E9+$AH$26 -> 65.528531
A10: 2400 | B10: 289 | C10: -48.697124 | D10: =$K$3*C10 -> -97.394249 | E10: 42.932498 | F10: =ABS(E10-E9) -> 3.2897284 | G10: =$J$3*E10 -> 386.39248 | H10: 32.700149 | AM10: =$AF$26*E10^2+$AG$26*E10+$AH$26 -> 71.30809
A11: 2700 | B11: 189 | C11: -76.440396 | D11: =$K$3*C11 -> -152.88079 | E11: 37.986453 | F11: =ABS(E11-E10) -> 4.9460451 | G11: =$J$3*E11 -> 341.87808 | H11: 37.641983 | AM11: =$AF$26*E11^2+$AG$26*E11+$AH$26 -> 62.64259
A12: 3000 | B12: 141 | C12: -68.00046 | D12: =$K$3*C12 -> -136.00092 | E12: 30.777617 | F12: =ABS(E12-E11) -> 7.2088362 | G12: =$J$3*E12 -> 276.99855 | H12: 43.181674 | AM12: =$AF$26*E12^2+$AG$26*E12+$AH$26 -> 50.268917
A13: 3300 | B13: 134 | C13: -43.627507 | D13: =$K$3*C13 -> -87.255015 | E13: 24.583705 | F13: =ABS(E13-E12) -> 6.193912 | G13: =$J$3*E13 -> 221.25334 | H13: 47.399514 | AM13: =$AF$26*E13^2+$AG$26*E13+$AH$26 -> 39.880097
A14: 3600 | B14: 280 | C14: 29.562073 | D14: =$K$3*C14 -> 59.124147 | E14: 24.541464 | F14: =ABS(E14-E13) -> 0.04224098 | G14: =$J$3*E14 -> 220.87317 | H14: 47.657985 | AM14: =$AF$26*E14^2+$AG$26*E14+$AH$26 -> 39.810018
A15: 3900 | B15: 531 | C15: 69.176027 | D15: =$K$3*C15 -> 138.35205 | E15: 41.285964 | F15: =ABS(E15-E14) -> 16.7445 | G15: =$J$3*E15 -> 371.57368 | H15: 42.717225 | AM15: =$AF$26*E15^2+$AG$26*E15+$AH$26 -> 68.407465
A16: 4200 | B16: 824 | C16: 58.532268 | D16: =$K$3*C16 -> 117.06454 | E16: 73.413278 | F16: =ABS(E16-E15) -> 32.127314 | G16: =$J$3*E16 -> 660.7195 | H16: 37.693597 | AM16: =$AF$26*E16^2+$AG$26*E16+$AH$26 -> 127.86856
A17: 4500 | B17: 835 | C17: 37.299542 | D17: =$K$3*C17 -> 74.599084 | E17: 84.4866 | F17: =ABS(E17-E16) -> 11.073322 | G17: =$J$3*E17 -> 760.3794 | H17: 33.787434 | AM17: =$AF$26*E17^2+$AG$26*E17+$AH$26 -> 149.76201
A18: 4800 | B18: 740 | C18: -24.359877 | D18: =$K$3*C18 -> -48.719753 | E18: 87.6334 | F18: =ABS(E18-E17) -> 3.1467998 | G18: =$J$3*E18 -> 788.7006 | H18: 33.456865 | AM18: =$AF$26*E18^2+$AG$26*E18+$AH$26 -> 156.11452
... A20: 5400 | B20: 877 | C20: 18.076981 | D20: =$K$3*C20 -> 36.153962 | E20: 93.424116 | F20: =ABS(E20-E19) -> 3.8923539 | G20: =$J$3*E20 -> 840.81704 | H20: 32.829302 | AM20: =$AF$26*E20^2+$AG$26*E20+$AH$26 -> 167.95572
A21: 5700 | B21: 874 | C21: 0.95957424 | D21: =$K$3*C21 -> 1.9191485 | E21: 96.894619 | F21: =ABS(E21-E20) -> 3.4705037 | G21: =$J$3*E21 -> 872.05157 | H21: 32.131934 | AF21: Fuel consumption (kW) in y axis | AM21: =$AF$26*E21^2+$AG$26*E21+$AH$26 -> 175.14641
A22: 6000 | B22: 869 | C22: -11.012384 | D22: =$K$3*C22 -> -22.024769 | E22: 98.999326 | F22: =ABS(E22-E21) -> 2.1047063 | G22: =$J$3*E22 -> 890.99393 | H22: 32.556931 | AF22: Power output (kW) in x axis | AM22: =$AF$26*E22^2+$AG$26*E22+$AH$26 -> 179.54156
A23: 6300 | B23: 898 | C23: -4.5424795 | D23: =$K$3*C23 -> -9.0849591 | E23: 100.78346 | F23: =ABS(E23-E22) -> 1.7841314 | G23: =$J$3*E23 -> 907.05111 | H23: 33.148221 | AM23: =$AF$26*E23^2+$AG$26*E23+$AH$26 -> 183.28756
A24: 6600 | B24: 849 | C24: -31.935035 | D24: =$K$3*C24 -> -63.870071 | E24: 101.42657 | F24: =ABS(E24-E23) -> 0.64311382 | G24: =$J$3*E24 -> 912.83914 | H24: 34.638758 | AM24: =$AF$26*E24^2+$AG$26*E24+$AH$26 -> 184.64242
A25: 6900 | B25: 581 | C25: -87.266427 | D25: =$K$3*C25 -> -174.53285 | E25: 87.912996 | F25: =ABS(E25-E24) -> 13.513575 | G25: =$J$3*E25 -> 791.21697 | H25: 40.377071 | AF25: k1 | AG25: k2 | AH25: k3 | AM25: =$AF$26*E25^2+$AG$26*E25+$AH$26 -> 156.68175
A26: 7200 | B26: 528 | C26: -81.107017 | D26: =$K$3*C26 -> -162.21403 | E26: 76.688683 | F26: =ABS(E26-E25) -> 11.224314 | G26: =$J$3*E26 -> 690.19814 | H26: 46.865849 | AF26: 0.00292448 | AG26: 1.51536 | AH26: 0.8595 | AM26: =$AF$26*E26^2+$AG$26*E26+$AH$26 -> 134.26978
A27: 7500 | B27: 656 | C27: 0.036647668 | D27: =$K$3*C27 -> 0.073295335 | E27: 72.878671 | F27: =ABS(E27-E26) -> 3.8100117 | G27: =$J$3*E27 -> 655.90804 | H27: 49.744226 | AM27: =$AF$26*E27^2+$AG$26*E27+$AH$26 -> 126.82972
A28: 7800 | B28: 832 | C28: 69.168901 | D28: =$K$3*C28 -> 138.3378 | E28: 77.071024 | F28: =ABS(E28-E27) -> 4.1923529 | G28: =$J$3*E28 -> 693.63921 | H28: 46.806138 | AM28: =$AF$26*E28^2+$AG$26*E28+$AH$26 -> 135.02109
A29: 8100 | B29: 733 | C29: 0.56675394 | D29: =$K$3*C29 -> 1.1335079 | E29: 81.316771 | F29: =ABS(E29-E28) -> 4.2457471 | G29: =$J$3*E29 -> 731.85094 | H29: 44.279059 | AM29: =$AF$26*E29^2+$AG$26*E29+$AH$26 -> 143.42156
A30: 8400 | B30: 732 | C30: -3.4319386 | D30: =$K$3*C30 -> -6.8638772 | E30: 82.093828 | F30: =ABS(E30-E29) -> 0.77705682 | G30: =$J$3*E30 -> 738.84445 | H30: 44.402888 | AM30: =$AF$26*E30^2+$AG$26*E30+$AH$26 -> 144.97043
A31: 8700 | B31: 734 | C31: -4.5920265 | D31: =$K$3*C31 -> -9.184053 | E31: 82.573804 | F31: =ABS(E31-E30) -> 0.47997666 | G31: =$J$3*E31 -> 743.16424 | H31: 44.718512 | AM31: =$AF$26*E31^2+$AG$26*E31+$AH$26 -> 145.92891
A32: 9000 | B32: 734 | C32: -5.9114019 | D32: =$K$3*C32 -> -11.822804 | E32: 82.866987 | F32: =ABS(E32-E31) -> 0.29318305 | G32: =$J$3*E32 -> 745.80289 | H32: 45.13085 | AM32: =$AF$26*E32^2+$AG$26*E32+$AH$26 -> 146.51504
A33: 9300 | B33: 736 | C33: -5.6792231 | D33: =$K$3*C33 -> -11.358446 | E33: 83.037595 | F33: =ABS(E33-E32) -> 0.17060775 | G33: =$J$3*E33 -> 747.33836 | H33: 45.580784 | AM33: =$AF$26*E33^2+$AG$26*E33+$AH$26 -> 146.85635
A34: 9600 | B34: 741 | C34: -4.074663 | D34: =$K$3*C34 -> -8.1493259 | E34: 83.236557 | F34: =ABS(E34-E33) -> 0.19896199 | G34: =$J$3*E34 -> 749.12901 | H34: 45.955296 | AM34: =$AF$26*E34^2+$AG$26*E34+$AH$26 -> 147.2546
A35: 9900 | B35: 749 | C35: -1.6705552 | D35: =$K$3*C35 -> -3.3411104 | E35: 83.591165 | F35: =ABS(E35-E34) -> 0.35460787 | G35: =$J$3*E35 -> 752.32049 | H35: 46.171688 | AF35: BATTERY DEGRADATION | AM35: =$AF$26*E35^2+$AG$26*E35+$AH$26 -> 147.96496
A36: 10200 | B36: 744 | C36: -5.2588815 | D36: =$K$3*C36 -> -10.517763 | E36: 83.833051 | F36: =ABS(E36-E35) -> 0.24188569 | G36: =$J$3*E36 -> 754.49746 | H36: 46.45158 | AM36: =$AF$26*E36^2+$AG$26*E36+$AH$26 -> 148.44994
A37: 10500 | B37: 746 | C37: -4.5046318 | D37: =$K$3*C37 -> -9.0092637 | E37: 83.88763 | F37: =ABS(E37-E36) -> 0.054579436 | G37: =$J$3*E37 -> 754.98867 | H37: 46.828873 | AM37: =$AF$26*E37^2+$AG$26*E37+$AH$26 -> 148.55942
A38: 10800 | B38: 736 | C38: -8.6175559 | D38: =$K$3*C38 -> -17.235112 | E38: 83.690562 | F38: =ABS(E38-E37) -> 0.19706844 | G38: =$J$3*E38 -> 753.21506 | H38: 47.35061 | AM38: =$AF$26*E38^2+$AG$26*E38+$AH$26 -> 148.16421
A39: 11100 | B39: 733 | C39: -8.0424634 | D39: =$K$3*C39 -> -16.084927 | E39: 83.229432 | F39: =ABS(E39-E38) -> 0.46112998 | G39: =$J$3*E39 -> 749.06489 | H39: 47.995886 | AM39: =$AF$26*E39^2+$AG$26*E39+$AH$26 -> 147.24033
A40: 11400 | B40: 766 | C40: 7.0689045 | D40: =$K$3*C40 -> 14.137809 | E40: 83.537855 | F40: =ABS(E40-E39) -> 0.30842375 | G40: =$J$3*E40 -> 751.8407 | H40: 47.989111 | AM40: =$AF$26*E40^2+$AG$26*E40+$AH$26 -> 147.85812
A41: 11700 | B41: 716 | C41: -16.810255 | D41: =$K$3*C41 -> -33.62051 | E41: 83.28912 | F41: =ABS(E41-E40) -> 0.24873502 | G41: =$J$3*E41 -> 749.60208 | H41: 48.436448 | AM41: =$AF$26*E41^2+$AG$26*E41+$AH$26 -> 147.35985
A42: 12000 | B42: 731 | C42: -5.2419317 | D42: =$K$3*C42 -> -10.483863 | E42: 82.384853 | F42: =ABS(E42-E41) -> 0.90426775 | G42: =$J$3*E42 -> 741.46367 | H42: 49.258318 | AM42: =$AF$26*E42^2+$AG$26*E42+$AH$26 -> 145.55143
A43: 12300 | B43: 732 | C43: -3.2434496 | D43: =$K$3*C43 -> -6.4868992 | E43: 82.051934 | F43: =ABS(E43-E42) -> 0.332919 | G43: =$J$3*E43 -> 738.4674 | H43: 49.581981 | AM43: =$AF$26*E43^2+$AG$26*E43+$AH$26 -> 144.88684
A44: 12600 | B44: 731 | C44: -2.6269266 | D44: =$K$3*C44 -> -5.2538533 | E44: 81.803841 | F44: =ABS(E44-E43) -> 0.24809265 | G44: =$J$3*E44 -> 736.23457 | H44: 49.808224 | AM44: =$AF$26*E44^2+$AG$26*E44+$AH$26 -> 144.392
A45: 12900 | B45: 730 | C45: -2.1156541 | D45: =$K$3*C45 -> -4.2313081 | E45: 81.579128 | F45: =ABS(E45-E44) -> 0.22471299 | G45: =$J$3*E45 -> 734.21215 | H45: 49.990977 | AM45: =$AF$26*E45^2+$AG$26*E45+$AH$26 -> 143.94411
A46: 13200 | B46: 732 | C46: -0.49967508 | D46: =$K$3*C46 -> -0.99935016 | E46: 81.442241 | F46: =ABS(E46-E45) -> 0.13688691 | G46: =$J$3*E46 -> 732.98017 | H46: 50.087814 | AM46: =$AF$26*E46^2+$AG$26*E46+$AH$26 -> 143.67142
A47: 13500 | B47: 732 | C47: -0.2527734 | D47: =$K$3*C47 -> -0.50554679 | E47: 81.387385 | F47: =ABS(E47-E46) -> 0.054855787 | G47: =$J$3*E47 -> 732.48647 | H47: 50.116318 | AM47: =$AF$26*E47^2+$AG$26*E47+$AH$26 -> 143.56217
... A84: 24600 | B84: 717 | C84: 0.60155666 | D84: =$K$3*C84 -> 1.2031133 | E84: 79.530978 | F84: =ABS(E84-E83) -> 0.11154658 | G84: =$J$3*E84 -> 715.7788 | H84: 49.682702 | AM84: =$AF$26*E84^2+$AG$26*E84+$AH$26 -> 139.87541
A85: 24900 | B85: 715 | C85: -0.61888342 | D85: =$K$3*C85 -> -1.2377668 | E85: 79.579973 | F85: =ABS(E85-E84) -> 0.04899484 | G85: =$J$3*E85 -> 716.21975 | H85: 49.687041 | AB85: EC at 40.6% DoD | AD85: Max cycles at 40.6% DoD | AM85: =$AF$26*E85^2+$AG$26*E85+$AH$26 -> 139.97246
A86: 25200 | B86: 779 | C86: 24.86548 | D86: =$K$3*C86 -> 49.730959 | E86: 81.027546 | F86: =ABS(E86-E85) -> 1.4475734 | G86: =$J$3*E86 -> 729.24791 | H86: 48.664213 | AB86: 8.08 | AD86: 71000 | AM86: =$AF$26*E86^2+$AG$26*E86+$AH$26 -> 142.84597
A87: 25500 | B87: 1007 | C87: 71.624143 | D87: =$K$3*C87 -> 143.24829 | E87: 91.481284 | F87: =ABS(E87-E86) -> 10.453738 | G87: =$J$3*E87 -> 823.33156 | H87: 43.851749 | AM87: =$AF$26*E87^2+$AG$26*E87+$AH$26 -> 163.96104
A88: 25800 | B88: 1157 | C88: 60.56777 | D88: =$K$3*C88 -> 121.13554 | E88: 110.55469 | F88: =ABS(E88-E87) -> 19.073407 | G88: =$J$3*E88 -> 994.99222 | H88: 38.655121 | AM88: =$AF$26*E88^2+$AG$26*E88+$AH$26 -> 204.13365
A89: 26100 | B89: 1019 | C89: -10.87424 | D89: =$K$3*C89 -> -21.748481 | E89: 115.63424 | F89: =ABS(E89-E88) -> 5.0795451 | G89: =$J$3*E89 -> 1040.7081 | H89: 36.37979 | AM89: =$AF$26*E89^2+$AG$26*E89+$AH$26 -> 215.19103
A90: 26400 | B90: 930 | C90: -51.3814 | D90: =$K$3*C90 -> -102.7628 | E90: 114.74676 | F90: =ABS(E90-E89) -> 0.88747423 | G90: =$J$3*E90 -> 1032.7209 | H90: 38.881313 | AM90: =$AF$26*E90^2+$AG$26*E90+$AH$26 -> 213.24825
A91: 26700 | B91: 745 | C91: -87.459308 | D91: =$K$3*C91 -> -174.91862 | E91: 105.35095 | F91: =ABS(E91-E90) -> 9.3958073 | G91: =$J$3*E91 -> 948.15859 | H91: 44.914603 | AM91: =$AF$26*E91^2+$AG$26*E91+$AH$26 -> 192.96241
A92: 27000 | B92: 731 | C92: -69.866917 | D92: =$K$3*C92 -> -139.73383 | E92: 96.744935 | F92: =ABS(E92-E91) -> 8.6060201 | G92: =$J$3*E92 -> 870.70441 | H92: 51.071297 | AM92: =$AF$26*E92^2+$AG$26*E92+$AH$26 -> 174.83482
A93: 27300 | B93: 728 | C93: -45.332956 | D93: =$K$3*C93 -> -90.665912 | E93: 90.960064 | F93: =ABS(E93-E92) -> 5.7848709 | G93: =$J$3*E93 -> 818.64057 | H93: 55.435184 | AM93: =$AF$26*E93^2+$AG$26*E93+$AH$26 -> 162.89311
A94: 27600 | B94: 728 | C94: -25.352628 | D94: =$K$3*C94 -> -50.705256 | E94: 86.520325 | F94: =ABS(E94-E93) -> 4.4397385 | G94: =$J$3*E94 -> 778.68293 | H94: 58.106302 | AM94: =$AF$26*E94^2+$AG$26*E94+$AH$26 -> 153.86092
A95: 27900 | B95: 726 | C95: -11.771924 | D95: =$K$3*C95 -> -23.543848 | E95: 83.280406 | F95: =ABS(E95-E94) -> 3.2399188 | G95: =$J$3*E95 -> 749.52366 | H95: 59.503639 | AM95: =$AF$26*E95^2+$AG$26*E95+$AH$26 -> 147.3424
A96: 28200 | B96: 727 | C96: -1.2090355 | D96: =$K$3*C96 -> -2.4180711 | E96: 81.044346 | F96: =ABS(E96-E95) -> 2.2360609 | G96: =$J$3*E96 -> 729.39911 | H96: 59.976204 | AM96: =$AF$26*E96^2+$AG$26*E96+$AH$26 -> 142.87939
A97: 28500 | B97: 729 | C97: 5.9900413 | D97: =$K$3*C97 -> 11.980083 | E97: 79.666856 | F97: =ABS(E97-E96) -> 1.3774893 | G97: =$J$3*E97 -> 717.00171 | H97: 59.769439 | W97: PRAXIS BATTERIES | AM97: =$AF$26*E97^2+$AG$26*E97+$AH$26 -> 140.14458
A98: 28800 | B98: 728 | C98: 9.0682982 | D98: =$K$3*C98 -> 18.136596 | E98: 78.871748 | F98: =ABS(E98-E97) -> 0.79510853 | G98: =$J$3*E98 -> 709.84573 | H98: 59.175245 | V98: 513.01 GreenBattery Rev1.12 A4.cdr (praxis-automation.eu) | AM98: =$AF$26*E98^2+$AG$26*E98+$AH$26 -> 138.57106
A99: 29100 | B99: 654 | C99: -18.343718 | D99: =$K$3*C99 -> -36.687437 | E99: 76.741457 | F99: =ABS(E99-E98) -> 2.1302912 | G99: =$J$3*E99 -> 690.67311 | H99: 59.617 | AM99: =$AF$26*E99^2+$AG$26*E99+$AH$26 -> 134.37343
A100: 29400 | B100: 644 | C100: -9.0785094 | D100: =$K$3*C100 -> -18.157019 | E100: 73.571355 | F100: =ABS(E100-E99) -> 3.1701016 | G100: =$J$3*E100 -> 662.14219 | H100: 60.651108 | AM100: =$AF$26*E100^2+$AG$26*E100+$AH$26 -> 128.17605
A101: 29700 | B101: 645 | C101: 1.5783783 | D101: =$K$3*C101 -> 3.1567566 | E101: 71.314354 | F101: =ABS(E101-E100) -> 2.2570008 | G101: =$J$3*E101 -> 641.82919 | H101: 60.909233 | AM101: =$AF$26*E101^2+$AG$26*E101+$AH$26 -> 123.79956
A102: 30000 | B102: 644 | C102: 7.3229138 | D102: =$K$3*C102 -> 14.645828 | E102: 69.926758 | F102: =ABS(E102-E101) -> 1.3875966 | G102: =$J$3*E102 -> 629.34082 | H102: 60.545663 | AM102: =$AF$26*E102^2+$AG$26*E102+$AH$26 -> 121.12369
A103: 30300 | B103: 644 | C103: 10.889997 | D103: =$K$3*C103 -> 21.779995 | E103: 69.134109 | F103: =ABS(E103-E102) -> 0.79264904 | G103: =$J$3*E103 -> 622.20698 | H103: 59.826462 | AM103: =$AF$26*E103^2+$AG$26*E103+$AH$26 -> 119.60019
A104: 30600 | B104: 645 | C104: 12.928927 | D104: =$K$3*C104 -> 25.857853 | E104: 68.792138 | F104: =ABS(E104-E103) -> 0.34197069 | G104: =$J$3*E104 -> 619.12924 | H104: 58.893496 | AM104: =$AF$26*E104^2+$AG$26*E104+$AH$26 -> 118.94404
A105: 30900 | B105: 644 | C105: 12.756266 | D105: =$K$3*C105 -> 25.512532 | E105: 68.719406 | F105: =ABS(E105-E104) -> 0.072732072 | G105: =$J$3*E105 -> 618.47465 | H105: 57.89466 | AM105: =$AF$26*E105^2+$AG$26*E105+$AH$26 -> 118.80458
A106: 31200 | B106: 643 | C106: 12.028695 | D106: =$K$3*C106 -> 24.05739 | E106: 68.769975 | F106: =ABS(E106-E105) -> 0.050569038 | G106: =$J$3*E106 -> 618.92977 | H106: 56.932525 | AM106: =$AF$26*E106^2+$AG$26*E106+$AH$26 -> 118.90154
A107: 31500 | B107: 645 | C107: 12.173255 | D107: =$K$3*C107 -> 24.34651 | E107: 68.960054 | F107: =ABS(E107-E106) -> 0.19007918 | G107: =$J$3*E107 -> 620.64049 | H107: 55.990127 | AM107: =$AF$26*E107^2+$AG$26*E107+$AH$26 -> 119.26614
A108: 31800 | B108: 647 | C108: 11.669117 | D108: =$K$3*C108 -> 23.338234 | E108: 69.294291 | F108: =ABS(E108-E107) -> 0.33423701 | G108: =$J$3*E108 -> 623.64862 | H108: 55.063657 | AM108: =$AF$26*E108^2+$AG$26*E108+$AH$26 -> 119.90777
A109: 32100 | B109: 646 | C109: 9.6221882 | D109: =$K$3*C109 -> 19.244376 | E109: 69.638046 | F109: =ABS(E109-E108) -> 0.34375514 | G109: =$J$3*E109 -> 626.74242 | H109: 54.241491 | V109: DoD(%) | W109: Cycles (1C) | AM109: =$AF$26*E109^2+$AG$26*E109+$AH$26 -> 120.56835
A110: 32400 | B110: 646 | C110: 8.3007659 | D110: =$K$3*C110 -> 16.601532 | E110: 69.931678 | F110: =ABS(E110-E109) -> 0.2936319 | G110: =$J$3*E110 -> 629.3851 | H110: 53.548218 | V110: 5 | W110: 180000 | AM110: =$AF$26*E110^2+$AG$26*E110+$AH$26 -> 121.13316
A111: 32700 | B111: 646 | C111: 7.0935643 | D111: =$K$3*C111 -> 14.187129 | E111: 70.199932 | F111: =ABS(E111-E110) -> 0.26825392 | G111: =$J$3*E111 -> 631.79939 | H111: 52.953041 | V111: 10 | W111: 130000 | AM111: =$AF$26*E111^2+$AG$26*E111+$AH$26 -> 121.6496
A112: 33000 | B112: 646 | C112: 6.0140834 | D112: =$K$3*C112 -> 12.028167 | E112: 70.439805 | F112: =ABS(E112-E111) -> 0.23987284 | G112: =$J$3*E112 -> 633.95824 | H112: 52.446484 | V112: 20 | W112: 80000 | AM112: =$AF$26*E112^2+$AG$26*E112+$AH$26 -> 122.11175
A113: 33300 | B113: 646 | C113: 5.064444 | D113: =$K$3*C113 -> 10.128888 | E113: 70.650825 | F113: =ABS(E113-E112) -> 0.21102052 | G113: =$J$3*E113 -> 635.85743 | H113: 52.0185 | V113: 50 | W113: 24000 | AC113: at the REQUIRED DoD (%) | AM113: =$AF$26*E113^2+$AG$26*E113+$AH$26 -> 122.51859
A114: 33600 | B114: 647 | C114: 4.6320445 | D114: =$K$3*C114 -> 9.264089 | E114: 70.858012 | F114: =ABS(E114-E113) -> 0.20718626 | G114: =$J$3*E114 -> 637.7221 | H114: 51.642655 | V114: 80 | W114: 6200 | AC114: EC | AD114: MAX CYCLES | AM114: =$AF$26*E114^2+$AG$26*E114+$AH$26 -> 122.91829
A115: 33900 | B115: 647 | C115: 3.752227 | D115: =$K$3*C115 -> 7.504454 | E115: 71.05352 | F115: =ABS(E115-E114) -> 0.19550851 | G115: =$J$3*E115 -> 639.48168 | H115: 51.319292 | V115: 90 | W115: 5000 | AC115: 8.08 | AD115: =W121 -> 41546.667 | AM115: =$AF$26*E115^2+$AG$26*E115+$AH$26 -> 123.2957
A116: 34200 | B116: 647 | C116: 3.0331165 | D116: =$K$3*C116 -> 6.0662331 | E116: 71.213314 | F116: =ABS(E116-E115) -> 0.15979427 | G116: =$J$3*E116 -> 640.91983 | H116: 51.057643 | AM116: =$AF$26*E116^2+$AG$26*E116+$AH$26 -> 123.60433
A117: 34500 | B117: 646 | C117: 2.0541746 | D117: =$K$3*C117 -> 4.1083492 | E117: 71.319744 | F117: =ABS(E117-E116) -> 0.10642947 | G117: =$J$3*E117 -> 641.87769 | H117: 50.862885 | AM117: =$AF$26*E117^2+$AG$26*E117+$AH$26 -> 123.80997
A118: 34800 | B118: 648 | C118: 2.5334818 | D118: =$K$3*C118 -> 5.0669636 | E118: 71.435438 | F118: =ABS(E118-E117) -> 0.11569379 | G118: =$J$3*E118 -> 642.91894 | H118: 50.682949 | AM118: =$AF$26*E118^2+$AG$26*E118+$AH$26 -> 124.03359
A119: 35100 | B119: 650 | C119: 2.7058218 | D119: =$K$3*C119 -> 5.4116435 | E119: 71.619353 | F119: =ABS(E119-E118) -> 0.18391526 | G119: =$J$3*E119 -> 644.57418 | H119: 50.478614 | V119: x | W119: y | AM119: =$AF$26*E119^2+$AG$26*E119+$AH$26 -> 124.38923
A120: 35400 | B120: 648 | C120: 1.110533 | D120: =$K$3*C120 -> 2.2210661 | E120: 71.751646 | F120: =ABS(E120-E119) -> 0.13229285 | G120: =$J$3*E120 -> 645.76481 | H120: 50.335218 | V120: 20 | W120: 80000 | AM120: =$AF$26*E120^2+$AG$26*E120+$AH$26 -> 124.64517
A121: 35700 | B121: 648 | C121: 0.86414151 | D121: =$K$3*C121 -> 1.728283 | E121: 71.80639 | F121: =ABS(E121-E120) -> 0.054744103 | G121: =$J$3*E121 -> 646.25751 | H121: 50.259215 | V121: 40.6 | W121: =W120+((V121-V120)*(W122-W120))/(V122-V120) -> 41546.667 | AM121: =$AF$26*E121^2+$AG$26*E121+$AH$26 -> 124.75111
A122: 36000 | B122: 648 | C122: 0.67154438 | D122: =$K$3*C122 -> 1.3430888 | E122: 71.849187 | F122: =ABS(E122-E121) -> 0.042797158 | G122: =$J$3*E122 -> 646.64268 | H122: 50.200108 | V122: 50 | W122: 24000 | AM122: =$AF$26*E122^2+$AG$26*E122+$AH$26 -> 124.83394
A123: 36300 | B123: 647 | C123: 0.12809276 | D123: =$K$3*C123 -> 0.25618552 | E123: 71.858846 | F123: =ABS(E123-E122) -> 0.009658561 | G123: =$J$3*E123 -> 646.72961 | H123: 50.170728 | AM123: =$AF$26*E123^2+$AG$26*E123+$AH$26 -> 124.85264
A124: 36600 | B124: 650 | C124: 1.3602441 | D124: =$K$3*C124 -> 2.7204882 | E124: 71.918351 | F124: =ABS(E124-E123) -> 0.059505716 | G124: =$J$3*E124 -> 647.26516 | H124: 50.108973 | AM124: =$AF$26*E124^2+$AG$26*E124+$AH$26 -> 124.96783
A125: 36900 | B125: 649 | C125: 0.47957895 | D125: =$K$3*C125 -> 0.95915789 | E125: 72.002952 | F125: =ABS(E125-E124) -> 0.084601135 | G125: =$J$3*E125 -> 648.02657 | H125: 50.040194 | AM125: =$AF$26*E125^2+$AG$26*E125+$AH$26 -> 125.13164
A126: 37200 | B126: 650 | C126: 0.70177489 | D126: =$K$3*C126 -> 1.4035498 | E126: 72.064677 | F126: =ABS(E126-E125) -> 0.061724529 | G126: =$J$3*E126 -> 648.58209 | H126: 49.993562 | AM126: =$AF$26*E126^2+$AG$26*E126+$AH$26 -> 125.25118
A127: 37500 | B127: 646 | C127: -1.1608105 | D127: =$K$3*C127 -> -2.3216211 | E127: 72.034158 | F127: =ABS(E127-E126) -> 0.030518614 | G127: =$J$3*E127 -> 648.30742 | H127: 50.01726 | AM127: =$AF$26*E127^2+$AG$26*E127+$AH$26 -> 125.19207
A128: 37800 | B128: 649 | C128: 0.5024031 | D128: =$K$3*C128 -> 1.0048062 | E128: 71.997867 | F128: =ABS(E128-E127) -> 0.036291093 | G128: =$J$3*E128 -> 647.98081 | H128: 50.037631 | AM128: =$AF$26*E128^2+$AG$26*E128+$AH$26 -> 125.12179
A129: 38100 | B129: 648 | C129: -0.072227497 | D129: =$K$3*C129 -> -0.14445499 | E129: 72.014464 | F129: =ABS(E129-E128) -> 0.016597256 | G129: =$J$3*E129 -> 648.13018 | H129: 50.022705 | AM129: =$AF$26*E129^2+$AG$26*E129+$AH$26 -> 125.15394
A130: 38400 | B130: 649 | C130: 0.36428175 | D130: =$K$3*C130 -> 0.7285635 | E130: 72.028566 | F130: =ABS(E130-E129) -> 0.014101567 | G130: =$J$3*E130 -> 648.25709 | H130: 50.009978 | AM130: =$AF$26*E130^2+$AG$26*E130+$AH$26 -> 125.18124
A131: 38700 | B131: 648 | C131: -0.17118742 | D131: =$K$3*C131 -> -0.34237484 | E131: 72.036454 | F131: =ABS(E131-E130) -> 0.0078883849 | G131: =$J$3*E131 -> 648.32809 | H131: 50.004153 | AM131: =$AF$26*E131^2+$AG$26*E131+$AH$26 -> 125.19652
A132: 39000 | B132: 649 | C132: 0.29423795 | D132: =$K$3*C132 -> 0.5884759 | E132: 72.044131 | F132: =ABS(E132-E131) -> 0.0076760939 | G132: =$J$3*E132 -> 648.39717 | H132: 49.997906 | AM132: =$AF$26*E132^2+$AG$26*E132+$AH$26 -> 125.21139
A133: 39300 | B133: 647 | C133: -0.61320935 | D133: =$K$3*C133 -> -1.2264187 | E133: 72.023574 | F133: =ABS(E133-E132) -> 0.020556303 | G133: =$J$3*E133 -> 648.21217 | H133: 50.013158 | AM133: =$AF$26*E133^2+$AG$26*E133+$AH$26 -> 125.17158
A134: 39600 | B134: 646 | C134: -0.74808089 | D134: =$K$3*C134 -> -1.4961618 | E134: 71.942435 | F134: =ABS(E134-E133) -> 0.081138921 | G134: =$J$3*E134 -> 647.48192 | H134: 50.066508 | AM134: =$AF$26*E134^2+$AG$26*E134+$AH$26 -> 125.01446
... A1194: 357600 | B1194: 0 | C1194: -0.43538138 | D1194: =$K$3*C1194 -> -0.87076276 | E1194: 0.096752425 | F1194: =ABS(E1194-E1193) -> 1.4421842 | G1194: =$J$3*E1194 -> 0.87077183 | H1194: 64.058968 | AM1194: =$AF$26*E1194^2+$AG$26*E1194+$AH$26 -> 1.0061421
E1195: SUM(ABS(Pfc(t)-Pfc(t-1) | F1195: =SUM(F2:F1194) -> 1285.2923 | AL1195: SUM | AM1195: =SUM(AM2:AM1194) -> 154586.87
A1198: TRANSIENT DEGRADATION
...

Sheet Maneuv_Amsterdam_600LPF_125AH
A1: Time (sec) | B1: Load Profile (kW) | C1: Battery power (kW) | D1: Total Batt Power (kW) | E1: FC power (kW) | F1: Abs(Pfc(t)-Pfc(t-1) | G1: TotalFC power(kw) | H1: Battery SoC (%) | AK1: Sampling_dt(sec) | AL1: Sampling_dt(hrs) | AM1: Fuel consumption (f(pfc)) for 1 FC (kW) | AN1: Addit_Ploss(kW) | AO1: Fctotal(kw) | AQ1: FC_total*hrs(kwh) | AR1: Ke-m ( kg/kwh) | AS1: Fuel consumption (kg) | AU1: H2 in $/kg | AV1: Fuel cost | AW1: H2 price in $/kwh | AY1: Fuel cost ($)
A2: 0 | B2: 0 | C2: 12.350136 | D2: =$K$3*C2 -> 24.700273 | E2: 0 | F2: 0 | G2: =$J$3*E2 -> 0 | H2: 50 | J2: Nfc | K2: Nbat | AK2: 300 | AL2: =AK2/3600 -> 0.083333333 | AM2: =$AF$26*E2^2+$AG$26*E2+$AH$26 -> 0.8595 | AO2: =J3*AM70+AN2 -> 27481.733 | AQ2: =AO2*AL2 -> 2290.1444 | AR2: 0.03 | AS2: =AQ2*AR2 -> 68.704333 | AU2: 4 | AV2: =AU2*AS2 -> 274.81733 | AW2: =AU2/33.35 -> 0.11994003 | AY2: =AQ2*AW2 -> 274.67999
A3: 300 | B3: 0 | C3: -0.075000176 | D3: =$K$3*C3 -> -0.15000035 | E3: 0.016667063 | F3: =ABS(E3-E2) -> 0.016667063 | G3: =$J$3*E3 -> 0.15000356 | H3: 50.542869 | J3: 9 | K3: 2 | AM3: =$AF$26*E3^2+$AG$26*E3+$AH$26 -> 0.88475741
A4: 600 | B4: 28 | C4: 13.999915 | D4: =$K$3*C4 -> 27.99983 | E4: 2.9905002e-05 | F4: =ABS(E4-E3) -> 0.016637158 | G4: =$J$3*E4 -> 0.00026914502 | H4: 50.001184 | AG4: Fuel consumption | AM4: =$AF$26*E4^2+$AG$26*E4+$AH$26 -> 0.85954532 | AR4: *Source: Cost-effective control of Roll-on/Roll-off Emission-Free Ships
A5: 900 | B5: 86 | C5: 28.717026 | D5: =$K$3*C5 -> 57.434051 | E5: 3.1739923 | F5: =ABS(E5-E4) -> 3.1739624 | G5: =$J$3*E5 -> 28.565931 | H5: 48.10525 | AM5: =$AF$26*E5^2+$AG$26*E5+$AH$26 -> 5.6987029 | AR5: CHECK END OF LIFE INCREASE IN kg | AS5: =AS2+25.29%*AS2 -> 86.079659
A6: 1200 | B6: 110 | C6: 22.883581 | D6: =$K$3*C6 -> 45.767162 | E6: 7.1369479 | F6: =ABS(E6-E5) -> 3.9629556 | G6: =$J$3*E6 -> 64.232531 | H6: 46.08244 | K6: DC BUS VOLTAGE | AM6: =$AF$26*E6^2+$AG$26*E6+$AH$26 -> 11.823507 | AR6: 25.29% increase in kg due to FC degrad
A7: 1500 | B7: 139 | C7: 19.693398 | D7: =$K$3*C7 -> 39.386797 | E7: 11.068079 | F7: =ABS(E7-E6) -> 3.9311315 | G7: =$J$3*E7 -> 99.612715 | H7: 44.426659 | AM7: =$AF$26*E7^2+$AG$26*E7+$AH$26 -> 17.989881
A8: 1800 | B8: 146 | C8: 8.7260592 | D8: =$K$3*C8 -> 17.452118 | E8: 14.283035 | F8: =ABS(E8-E7) -> 3.2149557 | G8: =$J$3*E8 -> 128.54732 | H8: 43.358343 | AM8: =$AF$26*E8^2+$AG$26*E8+$AH$26 -> 23.100049
A9: 2100 | B9: 162 | C9: 5.6236506 | D9: =$K$3*C9 -> 11.247301 | E9: 16.750214 | F9: =ABS(E9-E8) -> 2.467179 | G9: =$J$3*E9 -> 150.75193 | H9: 42.810147 | AM9: =$AF$26*E9^2+$AG$26*E9+$AH$26 -> 27.062625
A10: 2400 | B10: 121 | C10: -17.474019 | D10: =$K$3*C10 -> -34.948037 | E10: 17.327503 | F10: =ABS(E10-E9) -> 0.57728893 | G10: =$J$3*E10 -> 155.94753 | H10: 43.361657 | AM10: =$AF$26*E10^2+$AG$26*E10+$AH$26 -> 27.994958
A11: 2700 | B11: 142 | C11: -6.1262091 | D11: =$K$3*C11 -> -12.252418 | E11: 17.139069 | F11: =ABS(E11-E10) -> 0.18843435 | G11: =$J$3*E11 -> 154.25162 | H11: 44.235544 | AM11: =$AF$26*E11^2+$AG$26*E11+$AH$26 -> 27.690418
A12: 3000 | B12: 156 | C12: -2.1780522 | D12: =$K$3*C12 -> -4.3561044 | E12: 17.817253 | F12: =ABS(E12-E11) -> 0.67818416 | G12: =$J$3*E12 -> 160.35528 | H12: 44.543655 | AM12: =$AF$26*E12^2+$AG$26*E12+$AH$26 -> 28.787442
A13: 3300 | B13: 135 | C13: -12.870187 | D13: =$K$3*C13 -> -25.740373 | E13: 17.859969 | F13: =ABS(E13-E12) -> 0.042716315 | G13: =$J$3*E13 -> 160.73972 | H13: 45.171078 | AM13: =$AF$26*E13^2+$AG$26*E13+$AH$26 -> 28.856629
A14: 3600 | B14: 164 | C14: 0.54815016 | D14: =$K$3*C14 -> 1.0963003 | E14: 18.100307 | F14: =ABS(E14-E13) -> 0.24033806 | G14: =$J$3*E14 -> 162.90277 | H14: 45.598165 | AM14: =$AF$26*E14^2+$AG$26*E14+$AH$26 -> 29.246103
A15: 3900 | B15: 281 | C15: 40.476391 | D15: =$K$3*C15 -> 80.952783 | E15: 22.22722 | F15: =ABS(E15-E14) -> 4.1269124 | G15: =$J$3*E15 -> 200.04498 | H15: 43.831393 | AM15: =$AF$26*E15^2+$AG$26*E15+$AH$26 -> 35.986577
A16: 4200 | B16: 332 | C16: 35.799983 | D16: =$K$3*C16 -> 71.599966 | E16: 28.93303 | F16: =ABS(E16-E15) -> 6.7058106 | G16: =$J$3*E16 -> 260.39727 | H16: 40.85029 | AM16: =$AF$26*E16^2+$AG$26*E16+$AH$26 -> 47.151598
A17: 4500 | B17: 466 | C17: 56.873216 | D17: =$K$3*C17 -> 113.74643 | E17: 38.498336 | F17: =ABS(E17-E16) -> 9.5653059 | G17: =$J$3*E17 -> 346.48503 | H17: 36.898841 | AM17: =$AF$26*E17^2+$AG$26*E17+$AH$26 -> 63.532775
A18: 4800 | B18: 473 | C18: 25.543141 | D18: =$K$3*C18 -> 51.086283 | E18: 46.878665 | F18: =ABS(E18-E17) -> 8.3803289 | G18: =$J$3*E18 -> 421.90799 | H18: 33.69626 | AM18: =$AF$26*E18^2+$AG$26*E18+$AH$26 -> 78.324418
... A20: 5400 | B20: 471 | C20: -10.654814 | D20: =$K$3*C20 -> -21.309628 | E20: 54.700229 | F20: =ABS(E20-E19) -> 2.8291774 | G20: =$J$3*E20 -> 492.30207 | H20: 32.960865 | AM20: =$AF$26*E20^2+$AG$26*E20+$AH$26 -> 92.500421
A21: 5700 | B21: 461 | C21: -21.071925 | D21: =$K$3*C21 -> -42.14385 | E21: 55.904003 | F21: =ABS(E21-E20) -> 1.2037733 | G21: =$J$3*E21 -> 503.13603 | H21: 34.235064 | AF21: Fuel consumption (kW) in y axis | AM21: =$AF$26*E21^2+$AG$26*E21+$AH$26 -> 94.713943
A22: 6000 | B22: 433 | C22: -33.063363 | D22: =$K$3*C22 -> -66.126725 | E22: 55.457705 | F22: =ABS(E22-E21) -> 0.44629786 | G22: =$J$3*E22 -> 499.11934 | H22: 36.382416 | AF22: Power output (kW) in x axis | AM22: =$AF$26*E22^2+$AG$26*E22+$AH$26 -> 93.892293
A23: 6300 | B23: 371 | C23: -51.512096 | D23: =$K$3*C23 -> -103.02419 | E23: 52.668678 | F23: =ABS(E23-E22) -> 2.7890268 | G23: =$J$3*E23 -> 474.0181 | H23: 39.723377 | AM23: =$AF$26*E23^2+$AG$26*E23+$AH$26 -> 88.783985
A24: 6600 | B24: 467 | C24: 1.1074656 | D24: =$K$3*C24 -> 2.2149313 | E24: 51.64181 | F24: =ABS(E24-E23) -> 1.0268684 | G24: =$J$3*E24 -> 464.77629 | H24: 41.496658 | AM24: =$AF$26*E24^2+$AG$26*E24+$AH$26 -> 86.91466
A25: 6900 | B25: 467 | C25: -5.0348359 | D25: =$K$3*C25 -> -10.069672 | E25: 53.006945 | F25: =ABS(E25-E24) -> 1.3651351 | G25: =$J$3*E25 -> 477.0625 | H25: 41.671192 | AF25: k1 | AG25: k2 | AH25: k3 | AM25: =$AF$26*E25^2+$AG$26*E25+$AH$26 -> 89.401121
A26: 7200 | B26: 468 | C26: -7.965986 | D26: =$K$3*C26 -> -15.931972 | E26: 53.769394 | F26: =ABS(E26-E25) -> 0.76244875 | G26: =$J$3*E26 -> 483.92454 | H26: 42.187806 | AF26: 0.00292448 | AG26: 1.51536 | AH26: 0.8595 | AM26: =$AF$26*E26^2+$AG$26*E26+$AH$26 -> 90.794592
A27: 7500 | B27: 467 | C27: -10.035892 | D27: =$K$3*C27 -> -20.071785 | E27: 54.118253 | F27: =ABS(E27-E26) -> 0.3488598 | G27: =$J$3*E27 -> 487.06428 | H27: 42.895633 | AM27: =$AF$26*E27^2+$AG$26*E27+$AH$26 -> 91.433311
A28: 7800 | B28: 558 | C28: 24.652654 | D28: =$K$3*C28 -> 49.305308 | E28: 56.520477 | F28: =ABS(E28-E27) -> 2.4022235 | G28: =$J$3*E28 -> 508.68429 | H28: 42.203267 | AM28: =$AF$26*E28^2+$AG$26*E28+$AH$26 -> 95.850809
A29: 8100 | B29: 451 | C29: -32.417002 | D29: =$K$3*C29 -> -64.834003 | E29: 57.314211 | F29: =ABS(E29-E28) -> 0.79373373 | G29: =$J$3*E29 -> 515.8279 | H29: 42.695644 | AM29: =$AF$26*E29^2+$AG$26*E29+$AH$26 -> 97.317841
A30: 8400 | B30: 141 | C30: -87.547079 | D30: =$K$3*C30 -> -175.09416 | E30: 35.921266 | F30: =ABS(E30-E29) -> 21.392944 | G30: =$J$3*E30 -> 323.2914 | H30: 48.515095 | AM30: =$AF$26*E30^2+$AG$26*E30+$AH$26 -> 59.066716
A31: 8700 | B31: 204 | C31: -23.541206 | D31: =$K$3*C31 -> -47.082413 | E31: 27.897752 | F31: =ABS(E31-E30) -> 8.0235141 | G31: =$J$3*E31 -> 251.07977 | H31: 52.54939 | AM31: =$AF$26*E31^2+$AG$26*E31+$AH$26 -> 45.410715
A32: 9000 | B32: 236 | C32: 1.3258596 | D32: =$K$3*C32 -> 2.6517191 | E32: 25.927377 | F32: =ABS(E32-E31) -> 1.9703752 | G32: =$J$3*E32 -> 233.34639 | H32: 53.316583 | AF32: BATTERY DEGRADATION | AM32: =$AF$26*E32^2+$AG$26*E32+$AH$26 -> 42.11473
A33: 9300 | B33: 138 | C33: -33.483933 | D33: =$K$3*C33 -> -66.967865 | E33: 22.774134 | F33: =ABS(E33-E32) -> 3.1532428 | G33: =$J$3*E33 -> 204.96721 | H33: 54.694405 | AM33: =$AF$26*E33^2+$AG$26*E33+$AH$26 -> 36.887326
A34: 9600 | B34: 120 | C34: -20.834298 | D34: =$K$3*C34 -> -41.668595 | E34: 17.963094 | F34: =ABS(E34-E33) -> 4.81104 | G34: =$J$3*E34 -> 161.66785 | H34: 56.74734 | AM34: =$AF$26*E34^2+$AG$26*E34+$AH$26 -> 29.023704
A35: 9900 | B35: 119 | C35: -6.2977762 | D35: =$K$3*C35 -> -12.595552 | E35: 14.621673 | F35: =ABS(E35-E34) -> 3.3414211 | G35: =$J$3*E35 -> 131.59506 | H35: 57.74262 | AM35: =$AF$26*E35^2+$AG$26*E35+$AH$26 -> 23.641833
A36: 10200 | B36: 120 | C36: 2.7496072 | D36: =$K$3*C36 -> 5.4992143 | E36: 12.722269 | F36: =ABS(E36-E35) -> 1.899404 | G36: =$J$3*E36 -> 114.50042 | H36: 57.844883 | AM36: =$AF$26*E36^2+$AG$26*E36+$AH$26 -> 20.611663
A37: 10500 | B37: 120 | C37: 7.1427621 | D37: =$K$3*C37 -> 14.285524 | E37: 11.746018 | F37: =ABS(E37-E36) -> 0.97625086 | G37: =$J$3*E37 -> 105.71416 | H37: 57.442685 | AM37: =$AF$26*E37^2+$AG$26*E37+$AH$26 -> 19.062434
A38: 10800 | B38: 101 | C38: 2.1231858 | D38: =$K$3*C38 -> 4.2463716 | E38: 10.750379 | F38: =ABS(E38-E37) -> 0.99563957 | G38: =$J$3*E38 -> 96.753408 | H38: 57.102168 | AM38: =$AF$26*E38^2+$AG$26*E38+$AH$26 -> 17.488178
A39: 11100 | B39: 113 | C39: 10.695265 | D39: =$K$3*C39 -> 21.390529 | E39: 10.178801 | F39: =ABS(E39-E38) -> 0.57157744 | G39: =$J$3*E39 -> 91.609211 | H39: 56.569094 | AM39: =$AF$26*E39^2+$AG$26*E39+$AH$26 -> 16.587048
A40: 11400 | B40: 131 | C40: 16.940244 | D40: =$K$3*C40 -> 33.880488 | E40: 10.791019 | F40: =ABS(E40-E39) -> 0.61221786 | G40: =$J$3*E40 -> 97.119172 | H40: 55.466901 | AM40: =$AF$26*E40^2+$AG$26*E40+$AH$26 -> 17.552323
A41: 11700 | B41: 149 | C41: 19.369979 | D41: =$K$3*C41 -> 38.739959 | E41: 12.251065 | F41: =ABS(E41-E40) -> 1.4600459 | G41: =$J$3*E41 -> 110.25958 | H41: 54.040111 | AM41: =$AF$26*E41^2+$AG$26*E41+$AH$26 -> 19.863205
A42: 12000 | B42: 187 | C42: 26.977036 | D42: =$K$3*C42 -> 53.954072 | E42: 14.782795 | F42: =ABS(E42-E41) -> 2.5317305 | G42: =$J$3*E42 -> 133.04516 | H42: 52.198314 | AM42: =$AF$26*E42^2+$AG$26*E42+$AH$26 -> 23.899847
A43: 12300 | B43: 238 | C43: 34.435119 | D43: =$K$3*C43 -> 68.870239 | E43: 18.792051 | F43: =ABS(E43-E42) -> 4.0092555 | G43: =$J$3*E43 -> 169.12846 | H43: 49.763438 | AM43: =$AF$26*E43^2+$AG$26*E43+$AH$26 -> 30.368977
A44: 12600 | B44: 295 | C44: 38.925128 | D44: =$K$3*C44 -> 77.850255 | E44: 24.127519 | F44: =ABS(E44-E43) -> 5.3354677 | G44: =$J$3*E44 -> 217.14767 | H44: 46.867239 | AM44: =$AF$26*E44^2+$AG$26*E44+$AH$26 -> 39.123825
... A69: 20100 | B69: 0 | C69: -0.0013979016 | D69: =$K$3*C69 -> -0.0027958031 | E69: 0.00031097363 | F69: =ABS(E69-E68) -> 0.14365585 | G69: =$J$3*E69 -> 0.0027987627 | H69: 62.648486 | AM69: =$AF$26*E69^2+$AG$26*E69+$AH$26 -> 0.85997124
E70: SUM(ABS(Pfc(t)-Pfc(t-1) | F70: =SUM(F2:F69) -> 210.38 | AL70: SUM | AM70: =SUM(AM2:AM69) -> 3053.5259
A73: TRANSIENT DEGRADATION
A74: Coeff | B74: 0.4185 | C74: Microvolt/DkW
A75: sum(Abs(Pfc(t)-Pfc(t-1))) | B75: =F70 -> 210.38 | C75: DkW | D75: FROM: Integrated design and control optimization of fuel cell hybrid mining truck with minimized lifecycle cost
A76: TotalTransient Degrad | B76: =B75*B74 -> 88.044032 | C76: microvolt | D76: WHERE THEY GIVE 0.4185 microvolt for load changing degradation which is also for a same size of FC…
A78: START/STOP CYCLE
A79: Cycles | B79: 1 | C79: Cycles | D79: Always 1 start/stop cycle start from 0 and end to 0 at end of voyage
A80: MicroVolt/cycle | B80: 23.91 | C80: Microvolt/cycle
A81: Total start/stop Degrad | B81: =B80*B79 -> 23.91 | C81: microvolt
AB82: EC at 30% DoD | AE82: Max cycles at 30% DoD
A83: Low Power operation (<10% rated power) | C83: Power <15 kW | AB83: 1.62 | AE83: 109000
A84: Coeff | B84: 10.17 | C84: Microvolt/hr
A85: Hours of low power oper | B85: =(30+35+30)/60 -> 1.5833333 | C85: hrs | D85: Add minutes in intervals and convert to hours dividing by 60 | E85: REF
A86: Total LPO degrad | B86: =B85*B84 -> 16.1025 | C86: microvolt | E86: Synthesis of degradation mechanisms and of their impacts on degradation
E87: rates on proton-exchange membrane fuel cells and lithium-ion
A88: High Power operation (>90% rated power) | C88: Power > 135 kW | E88: nickel–manganese–cobalt batteries in hybrid transport application
A89: Coeff | B89: 11.74 | C89: Microvolt/hr
A90: Hours of high power oper | B90: 0 | C90: hrs | E90: and Fletcher study | J90: An energy management strategy to concurrently optimise fuel con_x0002_sumption & PEM fuel cell lifetime in a hybrid vehicle
A91: Total HPO degrad | B91: =B90*B89 -> 0 | C91: microvolt | Z91: PRAXIS BATTERIES
Y92: 513.01 GreenBattery Rev1.12 A4.cdr (praxis-automation.eu)
A98: Colors
A99: Transient | B99: No color
A100: LPO | B100: orange
A101: HPO | B101: Red
A102: Constant | B102: -
Y103: DoD(%) | Z103: Cycles (1C)
Y104: 5 | Z104: 180000
Y105: 10 | Z105: 130000
A106: TOTAL DEGRAD | B106: =B96+B91+B86+B81+B76 -> 128.05653 | C106: microvolt | Y106: 20 | Z106: 80000
Y107: 50 | Z107: 24000 | AF107: at the REQUIRED DoD (%)
Y108: 80 | Z108: 6200 | AF108: EC | AG108: MAX CYCLES
Y109: 90 | Z109: 5000 | AF109: 1.62 | AG109: =Z115 -> 61333.333
Y113: x | Z113: y
Y114: 20 | Z114: 80000
Y115: 30 | Z115: =Z114+((Y115-Y114)*(Z116-Z114))/(Y116-Y114) -> 61333.333
Y116: 50 | Z116: 24000

Sheet Amsterd_Lithuania_600LPF_125Ah
A1: Time (sec) | B1: Load Profile (kW) | C1: Battery power (kW) | D1: Total Batt Power (kW) | E1: FC power (kW) | F1: Abs(Pfc(t)-Pfc(t-1) | G1: TotalFC power(kw) | H1: Battery SoC (%) | AK1: Sampling_dt(sec) | AL1: Sampling_dt(hrs) | AM1: Fuel consumption (f(pfc)) for 1 FC (kW) | AN1: Addit_Ploss(kW) | AO1: Fctotal(kw) | AQ1: FC_total*hrs(kwh) | AR1: Ke-m ( kg/kwh) | AS1: Fuel consumption (kg) | AU1: H2 in $/kg | AV1: Fuel cost | AW1: H2 price in $/kwh | AY1: Fuel cost ($) | BB1: FUEL CONSUMPTION CALCULATION ALTERNATIVE | BG1: Fuel consumption (f(pfc)) for 1 FC (kW) | BI1: Total FC (kg)
A2: 0 | B2: 0 | C2: 12.350136 | D2: =$K$3*C2 -> 24.700273 | E2: 0 | F2: 0 | G2: =$J$3*E2 -> 0 | H2: 50 | J2: Nfc | K2: Nbat | AK2: 300 | AL2: =AK2/3600 -> 0.083333333 | AM2: =$AF$26*E2^2+$AG$26*E2+$AH$26 -> 0.8595 | AO2: =J3*AM1586+AN2 -> 1938568.7 | AQ2: =AO2*AL2 -> 161547.39 | AR2: 0.03 | AS2: =AQ2*AR2 -> 4846.4218 | AU2: 4 | AV2: =AU2*AS2 -> 19385.687 | AW2: =AU2/33.35 -> 0.11994003 | AY2: =AQ2*AW2 -> 19375.999 | BG2: =$BC$5*E2^2+$BD$5*E2+$BE$5 -> 0.08 | BI2: =J3*BG1586*AL2 -> 4881.5789
A3: 300 | B3: 0 | C3: -0.075000176 | D3: =$K$3*C3 -> -0.15000035 | E3: 0.016667063 | F3: =ABS(E3-E2) -> 0.016667063 | G3: =$J$3*E3 -> 0.15000356 | H3: 50.542869 | J3: 9 | K3: 2 | AM3: =$AF$26*E3^2+$AG$26*E3+$AH$26 -> 0.88475741 | BC3: FUNCTION OF Kg now the FC | BG3: =$BC$5*E3^2+$BD$5*E3+$BE$5 -> 0.080739545
A4: 600 | B4: 18 | C4: 8.9998975 | D4: =$K$3*C4 -> 17.999795 | E4: 2.968684e-05 | F4: =ABS(E4-E3) -> 0.016637376 | G4: =$J$3*E4 -> 0.00026718156 | H4: 50.195227 | AG4: Fuel consumption | AM4: =$AF$26*E4^2+$AG$26*E4+$AH$26 -> 0.85954499 | AR4: *Source: Cost-effective control of Roll-on/Roll-off Emission-Free Ships | BC4: k1 | BD4: k2 | BE4: k3 | BG4: =$BC$5*E4^2+$BD$5*E4+$BE$5 -> 0.080001317
A5: 900 | B5: 64 | C5: 24.092738 | D5: =$K$3*C5 -> 48.185476 | E5: 1.7571587 | F5: =ABS(E5-E4) -> 1.757129 | G5: =$J$3*E5 -> 15.814428 | H5: 48.711771 | AM5: =$AF$26*E5^2+$AG$26*E5+$AH$26 -> 3.5312576 | AR5: CHECK END OF LIFE INCREASE IN kg | AS5: =AS2+25.29%*AS2 -> 6072.0819 | BC5: 9.712e-05 | BD5: 0.04437 | BE5: 0.08 | BG5: =$BC$5*E5^2+$BD$5*E5+$BE$5 -> 0.158265
A6: 1200 | B6: 112 | C6: 28.969368 | D6: =$K$3*C6 -> 57.938737 | E6: 6.0067738 | F6: =ABS(E6-E5) -> 4.2496151 | G6: =$J$3*E6 -> 54.060964 | H6: 46.651405 | K6: DC BUS VOLTAGE | AM6: =$AF$26*E6^2+$AG$26*E6+$AH$26 -> 10.067444 | AR6: 25.29% increase in kg due to FC degrad | BG6: =$BC$5*E6^2+$BD$5*E6+$BE$5 -> 0.35002477
A7: 1500 | B7: 139 | C7: 22.556263 | D7: =$K$3*C7 -> 45.112525 | E7: 10.431889 | F7: =ABS(E7-E6) -> 4.4251149 | G7: =$J$3*E7 -> 93.886998 | H7: 44.655189 | AM7: =$AF$26*E7^2+$AG$26*E7+$AH$26 -> 16.985821 | BG7: =$BC$5*E7^2+$BD$5*E7+$BE$5 -> 0.55343191
A8: 1800 | B8: 138 | C8: 7.4215484 | D8: =$K$3*C8 -> 14.843097 | E8: 13.684045 | F8: =ABS(E8-E7) -> 3.2521568 | G8: =$J$3*E8 -> 123.15641 | H8: 43.5421 | AM8: =$AF$26*E8^2+$AG$26*E8+$AH$26 -> 22.143373 | BG8: =$BC$5*E8^2+$BD$5*E8+$BE$5 -> 0.70534712
A9: 2100 | B9: 170 | C9: 10.986146 | D9: =$K$3*C9 -> 21.972292 | E9: 16.44743 | F9: =ABS(E9-E8) -> 2.7633842 | G9: =$J$3*E9 -> 148.02687 | H9: 42.808636 | AM9: =$AF$26*E9^2+$AG$26*E9+$AH$26 -> 26.574401 | BG9: =$BC$5*E9^2+$BD$5*E9+$BE$5 -> 0.83604516
A10: 2400 | B10: 183 | C10: 5.3228848 | D10: =$K$3*C10 -> 10.64577 | E10: 19.150362 | F10: =ABS(E10-E9) -> 2.7029324 | G10: =$J$3*E10 -> 172.35326 | H10: 42.193823 | AM10: =$AF$26*E10^2+$AG$26*E10+$AH$26 -> 30.951706 | BG10: =$BC$5*E10^2+$BD$5*E10+$BE$5 -> 0.965319
A11: 2700 | B11: 222 | C11: 11.62693 | D11: =$K$3*C11 -> 23.253859 | E11: 22.08274 | F11: =ABS(E11-E10) -> 2.932378 | G11: =$J$3*E11 -> 198.74466 | H11: 41.506774 | AM11: =$AF$26*E11^2+$AG$26*E11+$AH$26 -> 35.748916 | BG11: =$BC$5*E11^2+$BD$5*E11+$BE$5 -> 1.1071715
A12: 3000 | B12: 144 | C12: -29.043456 | D12: =$K$3*C12 -> -58.086913 | E12: 22.454028 | F12: =ABS(E12-E11) -> 0.37128833 | G12: =$J$3*E12 -> 202.08626 | H12: 42.340327 | AM12: =$AF$26*E12^2+$AG$26*E12+$AH$26 -> 36.359911 | BG12: =$BC$5*E12^2+$BD$5*E12+$BE$5 -> 1.1252515
A13: 3300 | B13: 145 | C13: -20.369948 | D13: =$K$3*C13 -> -40.739896 | E13: 20.637649 | F13: =ABS(E13-E12) -> 1.8163791 | G13: =$J$3*E13 -> 185.73884 | H13: 44.225671 | AM13: =$AF$26*E13^2+$AG$26*E13+$AH$26 -> 33.378541 | BG13: =$BC$5*E13^2+$BD$5*E13+$BE$5 -> 1.0370571
A14: 3600 | B14: 154 | C14: -11.474392 | D14: =$K$3*C14 -> -22.948784 | E14: 19.660867 | F14: =ABS(E14-E13) -> 0.9767821 | G14: =$J$3*E14 -> 176.94781 | H14: 45.428963 | AM14: =$AF$26*E14^2+$AG$26*E14+$AH$26 -> 31.783249 | BG14: =$BC$5*E14^2+$BD$5*E14+$BE$5 -> 0.98989439
A15: 3900 | B15: 314 | C15: 50.086181 | D15: =$K$3*C15 -> 100.17236 | E15: 23.758305 | F15: =ABS(E15-E14) -> 4.0974373 | G15: =$J$3*E15 -> 213.82474 | H15: 43.668668 | AM15: =$AF$26*E15^2+$AG$26*E15+$AH$26 -> 38.512628 | BG15: =$BC$5*E15^2+$BD$5*E15+$BE$5 -> 1.188976
A16: 4200 | B16: 397 | C16: 52.770246 | D16: =$K$3*C16 -> 105.54049 | E16: 32.38395 | F16: =ABS(E16-E15) -> 8.6256453 | G16: =$J$3*E16 -> 291.45555 | H16: 39.599721 | AM16: =$AF$26*E16^2+$AG$26*E16+$AH$26 -> 52.999804 | BG16: =$BC$5*E16^2+$BD$5*E16+$BE$5 -> 1.6187276
A17: 4500 | B17: 591 | C17: 53.033766 | D17: =$K$3*C17 -> 106.06753 | E17: 51.989841 | F17: =ABS(E17-E16) -> 19.605891 | G17: =$J$3*E17 -> 467.90857 | H17: 35.105498 | AM17: =$AF$26*E17^2+$AG$26*E17+$AH$26 -> 87.547529 | BG17: =$BC$5*E17^2+$BD$5*E17+$BE$5 -> 2.6492991
A18: 4800 | B18: 595 | C18: 23.678819 | D18: =$K$3*C18 -> 47.357637 | E18: 60.848053 | F18: =ABS(E18-E17) -> 8.8582121 | G18: =$J$3*E18 -> 547.63247 | H18: 32.060334 | AM18: =$AF$26*E18^2+$AG$26*E18+$AH$26 -> 103.89405 | BG18: =$BC$5*E18^2+$BD$5*E18+$BE$5 -> 3.1394135
... A20: 5400 | B20: 600 | C20: -9.0330137 | D20: =$K$3*C20 -> -18.066027 | E20: 68.672579 | F20: =ABS(E20-E19) -> 2.9883277 | G20: =$J$3*E20 -> 618.05321 | H20: 31.367721 | AM20: =$AF$26*E20^2+$AG$26*E20+$AH$26 -> 118.7148 | BG20: =$BC$5*E20^2+$BD$5*E20+$BE$5 -> 3.5850128
A21: 5700 | B21: 606 | C21: -14.558809 | D21: =$K$3*C21 -> -29.117618 | E21: 70.567096 | F21: =ABS(E21-E20) -> 1.8945166 | G21: =$J$3*E21 -> 635.10386 | H21: 32.308115 | S21: This profile determines the battery size | AF21: Fuel consumption (kW) in y axis | AM21: =$AF$26*E21^2+$AG$26*E21+$AH$26 -> 122.35713 | BG21: =$BC$5*E21^2+$BD$5*E21+$BE$5 -> 3.694692
A22: 6000 | B22: 540 | C22: -45.467281 | D22: =$K$3*C22 -> -90.934563 | E22: 70.102548 | F22: =ABS(E22-E21) -> 0.46454776 | G22: =$J$3*E22 -> 630.92293 | H22: 34.740482 | S22: largest SoC range…from about 25-79% | AF22: Power output (kW) in x axis | AM22: =$AF$26*E22^2+$AG$26*E22+$AH$26 -> 121.46207 | BG22: =$BC$5*E22^2+$BD$5*E22+$BE$5 -> 3.6677334
A23: 6300 | B23: 495 | C23: -53.897336 | D23: =$K$3*C23 -> -107.79467 | E23: 66.975941 | F23: =ABS(E23-E22) -> 3.1266071 | G23: =$J$3*E23 -> 602.78347 | H23: 38.61583 | S23: so we can say 20-80% we size the battery | AM23: =$AF$26*E23^2+$AG$26*E23+$AH$26 -> 115.47073 | BG23: =$BC$5*E23^2+$BD$5*E23+$BE$5 -> 3.4873811
A24: 6600 | B24: 504 | C24: -35.090623 | D24: =$K$3*C24 -> -70.181246 | E24: 63.796662 | F24: =ABS(E24-E23) -> 3.179279 | G24: =$J$3*E24 -> 574.16996 | H24: 42.000269 | AM24: =$AF$26*E24^2+$AG$26*E24+$AH$26 -> 109.43708 | BG24: =$BC$5*E24^2+$BD$5*E24+$BE$5 -> 3.3059377
A25: 6900 | B25: 503 | C25: -25.775313 | D25: =$K$3*C25 -> -51.550625 | E25: 61.615611 | F25: =ABS(E25-E24) -> 2.1810512 | G25: =$J$3*E25 -> 554.5405 | H25: 44.328994 | S25: from matlab code Pbatmax= 96.5 KW | AF25: k1 | AG25: k2 | AH25: k3 | AM25: =$AF$26*E25^2+$AG$26*E25+$AH$26 -> 105.33207 | BG25: =$BC$5*E25^2+$BD$5*E25+$BE$5 -> 3.1825991
A26: 7200 | B26: 415 | C26: -52.561791 | D26: =$K$3*C26 -> -105.12358 | E26: 57.790725 | F26: =ABS(E26-E25) -> 3.8248862 | G26: =$J$3*E26 -> 520.11652 | H26: 47.445292 | S26: Ebatmax =96.5kwh | AF26: 0.00292448 | AG26: 1.51536 | AH26: 0.8595 | AM26: =$AF$26*E26^2+$AG$26*E26+$AH$26 -> 98.200337 | BG26: =$BC$5*E26^2+$BD$5*E26+$BE$5 -> 2.9685327
A27: 7500 | B27: 415 | C27: -31.480737 | D27: =$K$3*C27 -> -62.961473 | E27: 53.105999 | F27: =ABS(E27-E26) -> 4.6847259 | G27: =$J$3*E27 -> 477.95399 | H27: 50.620863 | S27: so we say Ebatmax = 100 kwh | AM27: =$AF$26*E27^2+$AG$26*E27+$AH$26 -> 89.581962 | BG27: =$BC$5*E27^2+$BD$5*E27+$BE$5 -> 2.7102156
A28: 7800 | B28: 419 | C28: -15.68602 | D28: =$K$3*C28 -> -31.37204 | E28: 50.040611 | F28: =ABS(E28-E27) -> 3.0653875 | G28: =$J$3*E28 -> 450.3655 | H28: 52.393061 | AM28: =$AF$26*E28^2+$AG$26*E28+$AH$26 -> 84.012122 | BG28: =$BC$5*E28^2+$BD$5*E28+$BE$5 -> 2.5434965
A29: 8100 | B29: 421 | C29: -6.3458551 | D29: =$K$3*C29 -> -12.69171 | E29: 48.187308 | F29: =ABS(E29-E28) -> 1.8533033 | G29: =$J$3*E29 -> 433.68577 | H29: 53.215303 | AM29: =$AF$26*E29^2+$AG$26*E29+$AH$26 -> 80.67131 | BG29: =$BC$5*E29^2+$BD$5*E29+$BE$5 -> 2.4435851
A30: 8400 | B30: 413 | C30: -4.3899172 | D30: =$K$3*C30 -> -8.7798344 | E30: 46.863826 | F30: =ABS(E30-E29) -> 1.323482 | G30: =$J$3*E30 -> 421.77443 | H30: 53.625445 | AM30: =$AF$26*E30^2+$AG$26*E30+$AH$26 -> 78.297864 | BG30: =$BC$5*E30^2+$BD$5*E30+$BE$5 -> 2.3726447
A31: 8700 | B31: 413 | C31: 0.038690689 | D31: =$K$3*C31 -> 0.077381377 | E31: 45.879703 | F31: =ABS(E31-E30) -> 0.98412255 | G31: =$J$3*E31 -> 412.91733 | H31: 53.778844 | AM31: =$AF$26*E31^2+$AG$26*E31+$AH$26 -> 76.539643 | BG31: =$BC$5*E31^2+$BD$5*E31+$BE$5 -> 2.3201149
A32: 9000 | B32: 412 | C32: 2.2117548 | D32: =$K$3*C32 -> 4.4235095 | E32: 45.285708 | F32: =ABS(E32-E31) -> 0.59399534 | G32: =$J$3*E32 -> 407.57137 | H32: 53.683591 | AM32: =$AF$26*E32^2+$AG$26*E32+$AH$26 -> 75.481161 | BG32: =$BC$5*E32^2+$BD$5*E32+$BE$5 -> 2.2885001
A33: 9300 | B33: 411 | C33: 3.3451239 | D33: =$K$3*C33 -> 6.6902479 | E33: 44.922747 | F33: =ABS(E33-E32) -> 0.36296093 | G33: =$J$3*E33 -> 404.30472 | H33: 53.463389 | AF33: BATTERY DEGRADATION | AM33: =$AF$26*E33^2+$AG$26*E33+$AH$26 -> 74.83539 | BG33: =$BC$5*E33^2+$BD$5*E33+$BE$5 -> 2.2692156
A34: 9600 | B34: 417 | C34: 6.4801827 | D34: =$K$3*C34 -> 12.960365 | E34: 44.892722 | F34: =ABS(E34-E33) -> 0.030025294 | G34: =$J$3*E34 -> 404.0345 | H34: 53.069725 | AM34: =$AF$26*E34^2+$AG$26*E34+$AH$26 -> 74.782005 | BG34: =$BC$5*E34^2+$BD$5*E34+$BE$5 -> 2.2676215
A35: 9900 | B35: 410 | C35: 2.9902022 | D35: =$K$3*C35 -> 5.9804043 | E35: 44.89052 | F35: =ABS(E35-E34) -> 0.0022014966 | G35: =$J$3*E35 -> 404.01468 | H35: 52.713676 | AM35: =$AF$26*E35^2+$AG$26*E35+$AH$26 -> 74.778091 | BG35: =$BC$5*E35^2+$BD$5*E35+$BE$5 -> 2.2675046
A36: 10200 | B36: 410 | C36: 3.4924576 | D36: =$K$3*C36 -> 6.9849153 | E36: 44.778897 | F36: =ABS(E36-E35) -> 0.11162294 | G36: =$J$3*E36 -> 403.01008 | H36: 52.459647 | AM36: =$AF$26*E36^2+$AG$26*E36+$AH$26 -> 74.57967 | BG36: =$BC$5*E36^2+$BD$5*E36+$BE$5 -> 2.2615798
A37: 10500 | B37: 416 | C37: 5.876584 | D37: =$K$3*C37 -> 11.753168 | E37: 44.915743 | F37: =ABS(E37-E36) -> 0.13684591 | G37: =$J$3*E37 -> 404.24169 | H37: 52.086374 | AM37: =$AF$26*E37^2+$AG$26*E37+$AH$26 -> 74.822937 | BG37: =$BC$5*E37^2+$BD$5*E37+$BE$5 -> 2.2688438
A38: 10800 | B38: 427 | C38: 8.8341852 | D38: =$K$3*C38 -> 17.66837 | E38: 45.480696 | F38: =ABS(E38-E37) -> 0.56495261 | G38: =$J$3*E38 -> 409.32626 | H38: 51.502741 | AM38: =$AF$26*E38^2+$AG$26*E38+$AH$26 -> 75.828396 | BG38: =$BC$5*E38^2+$BD$5*E38+$BE$5 -> 2.2988706
A39: 11100 | B39: 401 | C39: -4.0129828 | D39: =$K$3*C39 -> -8.0259657 | E39: 45.446806 | F39: =ABS(E39-E38) -> 0.033890362 | G39: =$J$3*E39 -> 409.02125 | H39: 51.36093 | AM39: =$AF$26*E39^2+$AG$26*E39+$AH$26 -> 75.768028 | BG39: =$BC$5*E39^2+$BD$5*E39+$BE$5 -> 2.2970676
A40: 11400 | B40: 454 | C40: 18.883344 | D40: =$K$3*C40 -> 37.766688 | E40: 46.247443 | F40: =ABS(E40-E39) -> 0.80063702 | G40: =$J$3*E40 -> 416.22698 | H40: 50.698613 | AM40: =$AF$26*E40^2+$AG$26*E40+$AH$26 -> 77.195978 | BG40: =$BC$5*E40^2+$BD$5*E40+$BE$5 -> 2.3397218
A41: 11700 | B41: 429 | C41: 1.363131 | D41: =$K$3*C41 -> 2.726262 | E41: 47.363174 | F41: =ABS(E41-E40) -> 1.1157317 | G41: =$J$3*E41 -> 426.26857 | H41: 49.971737 | AM41: =$AF$26*E41^2+$AG$26*E41+$AH$26 -> 79.192159 | BG41: =$BC$5*E41^2+$BD$5*E41+$BE$5 -> 2.3993705
A42: 12000 | B42: 340 | C42: -33.20874 | D42: =$K$3*C42 -> -66.417479 | E42: 45.157085 | F42: =ABS(E42-E41) -> 2.2060894 | G42: =$J$3*E42 -> 406.41376 | H42: 51.327413 | AM42: =$AF$26*E42^2+$AG$26*E42+$AH$26 -> 75.25223 | BG42: =$BC$5*E42^2+$BD$5*E42+$BE$5 -> 2.2816633
A43: 12300 | B43: 262 | C43: -46.956091 | D43: =$K$3*C43 -> -93.912183 | E43: 39.545454 | F43: =ABS(E43-E42) -> 5.6116309 | G43: =$J$3*E43 -> 355.90909 | H43: 54.470836 | AM43: =$AF$26*E43^2+$AG$26*E43+$AH$26 -> 65.358527 | BG43: =$BC$5*E43^2+$BD$5*E43+$BE$5 -> 1.9865122
A44: 12600 | B44: 120 | C44: -67.424296 | D44: =$K$3*C44 -> -134.84859 | E44: 28.574316 | F44: =ABS(E44-E43) -> 10.971138 | G44: =$J$3*E44 -> 257.16885 | H44: 59.209317 | AM44: =$AF$26*E44^2+$AG$26*E44+$AH$26 -> 46.547689 | BG44: =$BC$5*E44^2+$BD$5*E44+$BE$5 -> 1.4271401
A45: 12900 | B45: 107 | C45: -33.528048 | D45: =$K$3*C45 -> -67.056095 | E45: 19.339447 | F45: =ABS(E45-E44) -> 9.2348696 | G45: =$J$3*E45 -> 174.05502 | H45: 62.960613 | AM45: =$AF$26*E45^2+$AG$26*E45+$AH$26 -> 31.259521 | BG45: =$BC$5*E45^2+$BD$5*E45+$BE$5 -> 0.97441551
... A87: 25500 | B87: 780 | C87: -3.474499 | D87: =$K$3*C87 -> -6.9489981 | E87: 87.436254 | F87: =ABS(E87-E86) -> 0.40787569 | G87: =$J$3*E87 -> 786.92628 | H87: 50.04639 | AM87: =$AF$26*E87^2+$AG$26*E87+$AH$26 -> 155.71484 | BG87: =$BC$5*E87^2+$BD$5*E87+$BE$5 -> 4.7020385
A88: 25800 | B88: 788 | C88: 1.078578 | D88: =$K$3*C88 -> 2.1571559 | E88: 87.313324 | F88: =ABS(E88-E87) -> 0.12292997 | G88: =$J$3*E88 -> 785.81991 | H88: 50.126479 | AC88: EC at 50.8% DoD | AF88: Max cycles at 50.8% DoD | AM88: =$AF$26*E88^2+$AG$26*E88+$AH$26 -> 155.46573 | BG88: =$BC$5*E88^2+$BD$5*E88+$BE$5 -> 4.6944978
A89: 26100 | B89: 787 | C89: 0.34216389 | D89: =$K$3*C89 -> 0.68432777 | E89: 87.365894 | F89: =ABS(E89-E88) -> 0.052570395 | G89: =$J$3*E89 -> 786.29305 | H89: 50.073335 | AC89: 7.23 | AF89: 49000 | AM89: =$AF$26*E89^2+$AG$26*E89+$AH$26 -> 155.57225 | BG89: =$BC$5*E89^2+$BD$5*E89+$BE$5 -> 4.6977222
A90: 26400 | B90: 786 | C90: -0.14696165 | D90: =$K$3*C90 -> -0.2939233 | E90: 87.363478 | F90: =ABS(E90-E89) -> 0.0024164681 | G90: =$J$3*E90 -> 786.2713 | H90: 50.067146 | AM90: =$AF$26*E90^2+$AG$26*E90+$AH$26 -> 155.56735 | BG90: =$BC$5*E90^2+$BD$5*E90+$BE$5 -> 4.697574
A91: 26700 | B91: 787 | C91: 0.34870144 | D91: =$K$3*C91 -> 0.69740289 | E91: 87.364433 | F91: =ABS(E91-E90) -> 0.00095539113 | G91: =$J$3*E91 -> 786.2799 | H91: 50.057896 | AM91: =$AF$26*E91^2+$AG$26*E91+$AH$26 -> 155.56929 | BG91: =$BC$5*E91^2+$BD$5*E91+$BE$5 -> 4.6976326
A92: 27000 | B92: 796 | C92: 3.8664087 | D92: =$K$3*C92 -> 7.7328173 | E92: 87.582672 | F92: =ABS(E92-E91) -> 0.21823845 | G92: =$J$3*E92 -> 788.24404 | H92: 49.883966 | AM92: =$AF$26*E92^2+$AG$26*E92+$AH$26 -> 156.01166 | BG92: =$BC$5*E92^2+$BD$5*E92+$BE$5 -> 4.7110239
A93: 27300 | B93: 797 | C93: 2.7447223 | D93: =$K$3*C93 -> 5.4894446 | E93: 87.943054 | F93: =ABS(E93-E92) -> 0.36038237 | G93: =$J$3*E93 -> 791.48749 | H93: 49.63005 | AM93: =$AF$26*E93^2+$AG$26*E93+$AH$26 -> 156.74276 | BG93: =$BC$5*E93^2+$BD$5*E93+$BE$5 -> 4.7331575
A94: 27600 | B94: 789 | C94: -1.7167661 | D94: =$K$3*C94 -> -3.4335322 | E94: 88.045637 | F94: =ABS(E94-E93) -> 0.10258322 | G94: =$J$3*E94 -> 792.41073 | H94: 49.602737 | AM94: =$AF$26*E94^2+$AG$26*E94+$AH$26 -> 156.95101 | BG94: =$BC$5*E94^2+$BD$5*E94+$BE$5 -> 4.7394625
A95: 27900 | B95: 791 | C95: -0.49334908 | D95: =$K$3*C95 -> -0.98669815 | E95: 87.99595 | F95: =ABS(E95-E94) -> 0.049686847 | G95: =$J$3*E95 -> 791.96355 | H95: 49.685168 | AM95: =$AF$26*E95^2+$AG$26*E95+$AH$26 -> 156.85013 | BG95: =$BC$5*E95^2+$BD$5*E95+$BE$5 -> 4.7364084
A96: 28200 | B96: 792 | C96: -0.0848927 | D96: =$K$3*C96 -> -0.1697854 | E96: 88.016296 | F96: =ABS(E96-E95) -> 0.020345946 | G96: =$J$3*E96 -> 792.14667 | H96: 49.706475 | AM96: =$AF$26*E96^2+$AG$26*E96+$AH$26 -> 156.89144 | BG96: =$BC$5*E96^2+$BD$5*E96+$BE$5 -> 4.7376589
A97: 28500 | B97: 787 | C97: -2.2311981 | D97: =$K$3*C97 -> -4.4623963 | E97: 87.937728 | F97: =ABS(E97-E96) -> 0.078568159 | G97: =$J$3*E97 -> 791.43955 | H97: 49.802544 | AM97: =$AF$26*E97^2+$AG$26*E97+$AH$26 -> 156.73195 | BG97: =$BC$5*E97^2+$BD$5*E97+$BE$5 -> 4.7328302
A98: 28800 | B98: 787 | C98: -1.5039234 | D98: =$K$3*C98 -> -3.0078469 | E98: 87.776102 | F98: =ABS(E98-E97) -> 0.16162607 | G98: =$J$3*E98 -> 789.98492 | H98: 49.945602 | AM98: =$AF$26*E98^2+$AG$26*E98+$AH$26 -> 156.40397 | BG98: =$BC$5*E98^2+$BD$5*E98+$BE$5 -> 4.7229007
A99: 29100 | B99: 788 | C99: -0.56612301 | D99: =$K$3*C99 -> -1.132246 | E99: 87.678816 | F99: =ABS(E99-E98) -> 0.097286097 | G99: =$J$3*E99 -> 789.10934 | H99: 50.023365 | AM99: =$AF$26*E99^2+$AG$26*E99+$AH$26 -> 156.20663 | BG99: =$BC$5*E99^2+$BD$5*E99+$BE$5 -> 4.7169263
A100: 29400 | B100: 789 | C100: 0.062733384 | D100: =$K$3*C100 -> 0.12546677 | E100: 87.650183 | F100: =ABS(E100-E99) -> 0.028632633 | G100: =$J$3*E100 -> 788.85165 | H100: 50.041133 | AA100: PRAXIS BATTERIES | AM100: =$AF$26*E100^2+$AG$26*E100+$AH$26 -> 156.14856 | BG100: =$BC$5*E100^2+$BD$5*E100+$BE$5 -> 4.7151683
A101: 29700 | B101: 789 | C101: 0.062636327 | D101: =$K$3*C101 -> 0.12527265 | E101: 87.650209 | F101: =ABS(E101-E100) -> 2.5780549e-05 | G101: =$J$3*E101 -> 788.85188 | H101: 50.036258 | Z101: 513.01 GreenBattery Rev1.12 A4.cdr (praxis-automation.eu) | AM101: =$AF$26*E101^2+$AG$26*E101+$AH$26 -> 156.14861 | BG101: =$BC$5*E101^2+$BD$5*E101+$BE$5 -> 4.7151699
A102: 30000 | B102: 788 | C102: -0.34222565 | D102: =$K$3*C102 -> -0.68445131 | E102: 87.629073 | F102: =ABS(E102-E101) -> 0.021136108 | G102: =$J$3*E102 -> 788.66166 | H102: 50.048274 | AM102: =$AF$26*E102^2+$AG$26*E102+$AH$26 -> 156.10575 | BG102: =$BC$5*E102^2+$BD$5*E102+$BE$5 -> 4.7138723
A103: 30300 | B103: 787 | C103: -0.58754114 | D103: =$K$3*C103 -> -1.1750823 | E103: 87.57248 | F103: =ABS(E103-E102) -> 0.056592583 | G103: =$J$3*E103 -> 788.15232 | H103: 50.085103 | AM103: =$AF$26*E103^2+$AG$26*E103+$AH$26 -> 155.99099 | BG103: =$BC$5*E103^2+$BD$5*E103+$BE$5 -> 4.7103983
A104: 30600 | B104: 788 | C104: 0.0846484 | D104: =$K$3*C104 -> 0.1692968 | E104: 87.53421 | F104: =ABS(E104-E103) -> 0.038269926 | G104: =$J$3*E104 -> 787.80789 | H104: 50.102734 | AM104: =$AF$26*E104^2+$AG$26*E104+$AH$26 -> 155.9134 | BG104: =$BC$5*E104^2+$BD$5*E104+$BE$5 -> 4.7080495
A105: 30900 | B105: 786 | C105: -0.69225718 | D105: =$K$3*C105 -> -1.3845144 | E105: 87.48465 | F105: =ABS(E105-E104) -> 0.049560539 | G105: =$J$3*E105 -> 787.36185 | H105: 50.128552 | AM105: =$AF$26*E105^2+$AG$26*E105+$AH$26 -> 155.81293 | BG105: =$BC$5*E105^2+$BD$5*E105+$BE$5 -> 4.705008
A106: 31200 | B106: 787 | C106: 0.044344618 | D106: =$K$3*C106 -> 0.088689237 | E106: 87.432063 | F106: =ABS(E106-E105) -> 0.052586916 | G106: =$J$3*E106 -> 786.88857 | H106: 50.151635 | AM106: =$AF$26*E106^2+$AG$26*E106+$AH$26 -> 155.70635 | BG106: =$BC$5*E106^2+$BD$5*E106+$BE$5 -> 4.7017814
A107: 31500 | B107: 789 | C107: 0.91804582 | D107: =$K$3*C107 -> 1.8360916 | E107: 87.460123 | F107: =ABS(E107-E106) -> 0.028060324 | G107: =$J$3*E107 -> 787.14111 | H107: 50.111738 | AM107: =$AF$26*E107^2+$AG$26*E107+$AH$26 -> 155.76322 | BG107: =$BC$5*E107^2+$BD$5*E107+$BE$5 -> 4.7035031
A108: 31800 | B108: 786 | C108: -0.5700625 | D108: =$K$3*C108 -> -1.140125 | E108: 87.457502 | F108: =ABS(E108-E107) -> 0.0026216136 | G108: =$J$3*E108 -> 787.11752 | H108: 50.102445 | AM108: =$AF$26*E108^2+$AG$26*E108+$AH$26 -> 155.75791 | BG108: =$BC$5*E108^2+$BD$5*E108+$BE$5 -> 4.7033422
A109: 32100 | B109: 784 | C109: -1.1000144 | D109: =$K$3*C109 -> -2.2000289 | E109: 87.35305 | F109: =ABS(E109-E108) -> 0.10445206 | G109: =$J$3*E109 -> 786.17745 | H109: 50.168853 | AM109: =$AF$26*E109^2+$AG$26*E109+$AH$26 -> 155.54622 | BG109: =$BC$5*E109^2+$BD$5*E109+$BE$5 -> 4.6969343
A110: 32400 | B110: 794 | C110: 3.4297088 | D110: =$K$3*C110 -> 6.8594176 | E110: 87.457498 | F110: =ABS(E110-E109) -> 0.10444871 | G110: =$J$3*E110 -> 787.11749 | H110: 50.065353 | AM110: =$AF$26*E110^2+$AG$26*E110+$AH$26 -> 155.7579 | BG110: =$BC$5*E110^2+$BD$5*E110+$BE$5 -> 4.703342
A111: 32700 | B111: 792 | C111: 1.369444 | D111: =$K$3*C111 -> 2.7388879 | E111: 87.693146 | F111: =ABS(E111-E110) -> 0.23564792 | G111: =$J$3*E111 -> 789.23832 | H111: 49.884607 | AM111: =$AF$26*E111^2+$AG$26*E111+$AH$26 -> 156.23569 | BG111: =$BC$5*E111^2+$BD$5*E111+$BE$5 -> 4.7178062
A112: 33000 | B112: 794 | C112: 1.5912678 | D112: =$K$3*C112 -> 3.1825356 | E112: 87.866045 | F112: =ABS(E112-E111) -> 0.17289883 | G112: =$J$3*E112 -> 790.79441 | H112: 49.768893 | Z112: DoD(%) | AA112: Cycles (1C) | AM112: =$AF$26*E112^2+$AG$26*E112+$AH$26 -> 156.58647 | BG112: =$BC$5*E112^2+$BD$5*E112+$BE$5 -> 4.7284257
A113: 33300 | B113: 795 | C113: 1.2624957 | D113: =$K$3*C113 -> 2.5249914 | E113: 88.050207 | F113: =ABS(E113-E112) -> 0.1841624 | G113: =$J$3*E113 -> 792.45187 | H113: 49.658888 | Z113: 5 | AA113: 180000 | AM113: =$AF$26*E113^2+$AG$26*E113+$AH$26 -> 156.96029 | BG113: =$BC$5*E113^2+$BD$5*E113+$BE$5 -> 4.7397434
A114: 33600 | B114: 794 | C114: 0.1910149 | D114: =$K$3*C114 -> 0.38202981 | E114: 88.177203 | F114: =ABS(E114-E113) -> 0.1269951 | G114: =$J$3*E114 -> 793.59482 | H114: 49.605432 | Z114: 10 | AA114: 130000 | AM114: =$AF$26*E114^2+$AG$26*E114+$AH$26 -> 157.21818 | BG114: =$BC$5*E114^2+$BD$5*E114+$BE$5 -> 4.7475518
A115: 33900 | B115: 791 | C115: -1.3125089 | D115: =$K$3*C115 -> -2.6250179 | E115: 88.177994 | F115: =ABS(E115-E114) -> 0.00079128032 | G115: =$J$3*E115 -> 793.60194 | H115: 49.653274 | Z115: 20 | AA115: 80000 | AM115: =$AF$26*E115^2+$AG$26*E115+$AH$26 -> 157.21979 | BG115: =$BC$5*E115^2+$BD$5*E115+$BE$5 -> 4.7476004
A116: 34200 | B116: 794 | C116: 0.19012804 | D116: =$K$3*C116 -> 0.38025607 | E116: 88.177383 | F116: =ABS(E116-E115) -> 0.00061119401 | G116: =$J$3*E116 -> 793.59644 | H116: 49.692639 | Z116: 50 | AA116: 24000 | AG116: at the REQUIRED DoD (%) | AM116: =$AF$26*E116^2+$AG$26*E116+$AH$26 -> 157.21854 | BG116: =$BC$5*E116^2+$BD$5*E116+$BE$5 -> 4.7475628
A117: 34500 | B117: 793 | C117: -0.45854114 | D117: =$K$3*C117 -> -0.91708228 | E117: 88.210435 | F117: =ABS(E117-E116) -> 0.033051935 | G117: =$J$3*E117 -> 793.89391 | H117: 49.7049 | Z117: 80 | AA117: 6200 | AG117: EC | AH117: MAX CYCLES | AM117: =$AF$26*E117^2+$AG$26*E117+$AH$26 -> 157.28568 | BG117: =$BC$5*E117^2+$BD$5*E117+$BE$5 -> 4.7495955
A118: 34800 | B118: 792 | C118: -0.85661367 | D118: =$K$3*C118 -> -1.7132273 | E118: 88.187786 | F118: =ABS(E118-E117) -> 0.022648878 | G118: =$J$3*E118 -> 793.69007 | H118: 49.757136 | Z118: 90 | AA118: 5000 | AG118: 7.23 | AH118: 23500 | AM118: =$AF$26*E118^2+$AG$26*E118+$AH$26 -> 157.23967 | BG118: =$BC$5*E118^2+$BD$5*E118+$BE$5 -> 4.7482026
A119: 35100 | B119: 792 | C119: -0.67295603 | D119: =$K$3*C119 -> -1.3459121 | E119: 88.146972 | F119: =ABS(E119-E118) -> 0.040814095 | G119: =$J$3*E119 -> 793.32274 | H119: 49.816054 | AM119: =$AF$26*E119^2+$AG$26*E119+$AH$26 -> 157.15678 | BG119: =$BC$5*E119^2+$BD$5*E119+$BE$5 -> 4.7456927
A120: 35400 | B120: 791 | C120: -0.92694968 | D120: =$K$3*C120 -> -1.8538994 | E120: 88.092312 | F120: =ABS(E120-E119) -> 0.054660054 | G120: =$J$3*E120 -> 792.8308 | H120: 49.87894 | AM120: =$AF$26*E120^2+$AG$26*E120+$AH$26 -> 157.04578 | BG120: =$BC$5*E120^2+$BD$5*E120+$BE$5 -> 4.7423319
A121: 35700 | B121: 788 | C121: -1.8539178 | D121: =$K$3*C121 -> -3.7078357 | E121: 87.964989 | F121: =ABS(E121-E120) -> 0.12732302 | G121: =$J$3*E121 -> 791.6849 | H121: 49.98961 | AM121: =$AF$26*E121^2+$AG$26*E121+$AH$26 -> 156.78728 | BG121: =$BC$5*E121^2+$BD$5*E121+$BE$5 -> 4.7345055
A122: 36000 | B122: 807 | C122: 6.4786959 | D122: =$K$3*C122 -> 12.957392 | E122: 88.224296 | F122: =ABS(E122-E121) -> 0.2593079 | G122: =$J$3*E122 -> 794.01867 | H122: 49.786035 | Z122: x | AA122: y | AM122: =$AF$26*E122^2+$AG$26*E122+$AH$26 -> 157.31384 | BG122: =$BC$5*E122^2+$BD$5*E122+$BE$5 -> 4.7504481
A123: 36300 | B123: 813 | C123: 6.3399471 | D123: =$K$3*C123 -> 12.679894 | E123: 88.9218 | F123: =ABS(E123-E122) -> 0.69750376 | G123: =$J$3*E123 -> 800.2962 | H123: 49.287598 | Z123: 20 | AA123: 80000 | AC123: NOT NEEDED SINCE IT IS 50% DoD | AM123: =$AF$26*E123^2+$AG$26*E123+$AH$26 -> 158.73216 | BG123: =$BC$5*E123^2+$BD$5*E123+$BE$5 -> 4.7933965
A124: 36600 | B124: 823 | C124: 7.5955624 | D124: =$K$3*C124 -> 15.191125 | E124: 89.753806 | F124: =ABS(E124-E123) -> 0.83200619 | G124: =$J$3*E124 -> 807.78426 | H124: 48.741703 | Z124: 30 | AA124: =AA123+((Z124-Z123)*(AA125-AA123))/(Z125-Z123) -> 61333.333 | AM124: =$AF$26*E124^2+$AG$26*E124+$AH$26 -> 160.4277 | BG124: =$BC$5*E124^2+$BD$5*E124+$BE$5 -> 4.8447504
A125: 36900 | B125: 757 | C125: -22.563565 | D125: =$K$3*C125 -> -45.12713 | E125: 89.122866 | F125: =ABS(E125-E124) -> 0.63094052 | G125: =$J$3*E125 -> 802.10579 | H125: 49.405654 | Z125: 50 | AA125: 24000 | AM125: =$AF$26*E125^2+$AG$26*E125+$AH$26 -> 159.14154 | BG125: =$BC$5*E125^2+$BD$5*E125+$BE$5 -> 4.8057946
A126: 37200 | B126: 759 | C126: -13.641121 | D126: =$K$3*C126 -> -27.282242 | E126: 87.362161 | F126: =ABS(E126-E125) -> 1.7607046 | G126: =$J$3*E126 -> 786.25945 | H126: 50.783316 | AM126: =$AF$26*E126^2+$AG$26*E126+$AH$26 -> 155.56469 | BG126: =$BC$5*E126^2+$BD$5*E126+$BE$5 -> 4.6974932
A127: 37500 | B127: 763 | C127: -6.4226987 | D127: =$K$3*C127 -> -12.845397 | E127: 86.202588 | F127: =ABS(E127-E126) -> 1.159573 | G127: =$J$3*E127 -> 775.82329 | H127: 51.540932 | AM127: =$AF$26*E127^2+$AG$26*E127+$AH$26 -> 153.21893 | BG127: =$BC$5*E127^2+$BD$5*E127+$BE$5 -> 4.6264965
A128: 37800 | B128: 762 | C128: -3.4886144 | D128: =$K$3*C128 -> -6.9772288 | E128: 85.439533 | F128: =ABS(E128-E127) -> 0.76305571 | G128: =$J$3*E128 -> 768.95579 | H128: 51.91723 | AM128: =$AF$26*E128^2+$AG$26*E128+$AH$26 -> 151.6796 | BG128: =$BC$5*E128^2+$BD$5*E128+$BE$5 -> 4.5799197
A129: 38100 | B129: 761 | C129: -1.4448682 | D129: =$K$3*C129 -> -2.8897363 | E129: 84.874294 | F129: =ABS(E129-E128) -> 0.56523836 | G129: =$J$3*E129 -> 763.86865 | H129: 52.102922 | AM129: =$AF$26*E129^2+$AG$26*E129+$AH$26 -> 150.54153 | BG129: =$BC$5*E129^2+$BD$5*E129+$BE$5 -> 4.5454905
A130: 38400 | B130: 766 | C130: 2.3310511 | D130: =$K$3*C130 -> 4.6621022 | E130: 84.590752 | F130: =ABS(E130-E129) -> 0.28354203 | G130: =$J$3*E130 -> 761.31677 | H130: 52.057524 | AM130: =$AF$26*E130^2+$AG$26*E130+$AH$26 -> 149.97134 | BG130: =$BC$5*E130^2+$BD$5*E130+$BE$5 -> 4.5282431
A131: 38700 | B131: 763 | C131: 1.4327864 | D131: =$K$3*C131 -> 2.8655728 | E131: 84.457074 | F131: =ABS(E131-E130) -> 0.1336778 | G131: =$J$3*E131 -> 760.11367 | H131: 51.913851 | AM131: =$AF$26*E131^2+$AG$26*E131+$AH$26 -> 149.70268 | BG131: =$BC$5*E131^2+$BD$5*E131+$BE$5 -> 4.5201171
A132: 39000 | B132: 758 | C132: -0.003777673 | D132: =$K$3*C132 -> -0.0075553461 | E132: 84.220779 | F132: =ABS(E132-E131) -> 0.23629566 | G132: =$J$3*E132 -> 757.98701 | H132: 51.862522 | AM132: =$AF$26*E132^2+$AG$26*E132+$AH$26 -> 149.22804 | BG132: =$BC$5*E132^2+$BD$5*E132+$BE$5 -> 4.5057617
A133: 39300 | B133: 761 | C133: 2.2819713 | D133: =$K$3*C133 -> 4.5639426 | E133: 84.046148 | F133: =ABS(E133-E132) -> 0.17463105 | G133: =$J$3*E133 -> 756.41533 | H133: 51.767338 | AM133: =$AF$26*E133^2+$AG$26*E133+$AH$26 -> 148.87748 | BG133: =$BC$5*E133^2+$BD$5*E133+$BE$5 -> 4.4951594
A134: 39600 | B134: 762 | C134: 2.8338936 | D134: =$K$3*C134 -> 5.6677872 | E134: 84.034618 | F134: =ABS(E134-E133) -> 0.011529183 | G134: =$J$3*E134 -> 756.31157 | H134: 51.566855 | AM134: =$AF$26*E134^2+$AG$26*E134+$AH$26 -> 148.85434 | BG134: =$BC$5*E134^2+$BD$5*E134+$BE$5 -> 4.4944597
A135: 39900 | B135: 760 | C135: 1.8571773 | D135: =$K$3*C135 -> 3.7143545 | E135: 84.029457 | F135: =ABS(E135-E134) -> 0.0051618576 | G135: =$J$3*E135 -> 756.26511 | H135: 51.387356 | AM135: =$AF$26*E135^2+$AG$26*E135+$AH$26 -> 148.84398 | BG135: =$BC$5*E135^2+$BD$5*E135+$BE$5 -> 4.4941464
A136: 40200 | B136: 757 | C136: 0.75192207 | D136: =$K$3*C136 -> 1.5038441 | E136: 83.941745 | F136: =ABS(E136-E135) -> 0.087711461 | G136: =$J$3*E136 -> 755.47571 | H136: 51.289188 | AM136: =$AF$26*E136^2+$AG$26*E136+$AH$26 -> 148.66798 | BG136: =$BC$5*E136^2+$BD$5*E136+$BE$5 -> 4.4888238
A137: 40500 | B137: 761 | C137: 2.8128731 | D137: =$K$3*C137 -> 5.6257462 | E137: 83.928174 | F137: =ABS(E137-E136) -> 0.013571492 | G137: =$J$3*E137 -> 755.35356 | H137: 51.144605 | AM137: =$AF$26*E137^2+$AG$26*E137+$AH$26 -> 148.64075 | BG137: =$BC$5*E137^2+$BD$5*E137+$BE$5 -> 4.4880004
... A1585: 474900 | B1585: 0 | C1585: -0.00012320124 | D1585: =$K$3*C1585 -> -0.00024640247 | E1585: 2.5590175e-05 | F1585: =ABS(E1585-E1584) -> 0.014565352 | G1585: =$J$3*E1585 -> 0.00023031157 | H1585: 67.556249 | AM1585: =$AF$26*E1585^2+$AG$26*E1585+$AH$26 -> 0.85953878 | BG1585: =$BC$5*E1585^2+$BD$5*E1585+$BE$5 -> 0.080001135
E1586: SUM(ABS(Pfc(t)-Pfc(t-1) | F1586: =SUM(F2:F1585) -> 1349.4938 | AL1586: SUM | AM1586: =SUM(AM2:AM1585) -> 215396.53 | BF1586: sum | BG1586: =SUM(BG2:BG1585) -> 6508.7719
A1589: TRANSIENT DEGRADATION
A1590: Coeff | B1590: 0.4185 | C1590: Microvolt/DkW
A1591: sum(Abs(Pfc(t)-Pfc(t-1))) | B1591: =F1586 -> 1349.4938 | C1591: DkW | D1591: FROM: Integrated design and control optimization of fuel cell hybrid mining truck with minimized lifecycle cost
...

Sheet Lithuanian_ports_600LPF_125Ah
A1: Time (sec) | B1: Load Profile (kW) | C1: Battery power (kW) | D1: Total Batt Power (kW) | E1: FC power (kW) | F1: Abs(Pfc(t)-Pfc(t-1) | G1: TotalFC power(kw) | H1: Battery SoC (%) | AK1: Sampling_dt(sec) | AL1: Sampling_dt(hrs) | AM1: Fuel consumption (f(pfc)) for 1 FC (kW) | AN1: Addit_Ploss(kW) | AO1: Fctotal(kw) | AQ1: FC_total*hrs(kwh) | AR1: Ke-m ( kg/kwh) | AS1: Fuel consumption (kg) | AU1: H2 in $/kg | AV1: Fuel cost | AW1: H2 price in $/kwh | AY1: Fuel cost ($)
A2: 0 | B2: 0 | C2: 12.350136 | D2: =$K$3*C2 -> 24.700273 | E2: 0 | F2: 0 | G2: =$J$3*E2 -> 0 | H2: 50 | J2: Nfc | K2: Nbat | AK2: 300 | AL2: =AK2/3600 -> 0.083333333 | AM2: =$AF$26*E2^2+$AG$26*E2+$AH$26 -> 0.8595 | AO2: =J3*AM145+AN2 -> 141788.34 | AQ2: =AO2*AL2 -> 11815.695 | AR2: 0.03 | AS2: =AQ2*AR2 -> 354.47084 | AU2: 4 | AV2: =AU2*AS2 -> 1417.8834 | AW2: =AU2/33.35 -> 0.11994003 | AY2: =AQ2*AW2 -> 1417.1748
A3: 300 | B3: 0 | C3: -0.075000176 | D3: =$K$3*C3 -> -0.15000035 | E3: 0.016667063 | F3: =ABS(E3-E2) -> 0.016667063 | G3: =$J$3*E3 -> 0.15000356 | H3: 50.542869 | J3: 9 | K3: 2 | AM3: =$AF$26*E3^2+$AG$26*E3+$AH$26 -> 0.88475741
A4: 600 | B4: 6 | C4: 2.9998777 | D4: =$K$3*C4 -> 5.9997553 | E4: 2.9433711e-05 | F4: =ABS(E4-E3) -> 0.016637629 | G4: =$J$3*E4 -> 0.00026490339 | H4: 50.427703 | AG4: Fuel consumption | AM4: =$AF$26*E4^2+$AG$26*E4+$AH$26 -> 0.8595446 | AR4: *Source: Cost-effective control of Roll-on/Roll-off Emission-Free Ships
A5: 900 | B5: 74 | C5: 33.275773 | D5: =$K$3*C5 -> 66.551545 | E5: 0.82754892 | F5: =ABS(E5-E4) -> 0.82751949 | G5: =$J$3*E5 -> 7.4479403 | H5: 48.91568 | AM5: =$AF$26*E5^2+$AG$26*E5+$AH$26 -> 2.1155373 | AR5: CHECK END OF LIFE INCREASE IN kg | AS5: =AS2+25.29%*AS2 -> 444.11651
A6: 1200 | B6: 117 | C6: 30.478194 | D6: =$K$3*C6 -> 60.956389 | E6: 6.2270304 | F6: =ABS(E6-E5) -> 5.3994815 | G6: =$J$3*E6 -> 56.043274 | H6: 46.557796 | K6: DC BUS VOLTAGE | AM6: =$AF$26*E6^2+$AG$26*E6+$AH$26 -> 10.409092 | AR6: 25.29% increase in kg due to FC degrad
A7: 1500 | B7: 127 | C7: 17.014251 | D7: =$K$3*C7 -> 34.028502 | E7: 10.330122 | F7: =ABS(E7-E6) -> 4.1030917 | G7: =$J$3*E7 -> 92.971099 | H7: 44.74838 | AM7: =$AF$26*E7^2+$AG$26*E7+$AH$26 -> 16.825429
A8: 1800 | B8: 143 | C8: 10.888535 | D8: =$K$3*C8 -> 21.777069 | E8: 13.469154 | F8: =ABS(E8-E7) -> 3.1390313 | G8: =$J$3*E8 -> 121.22238 | H8: 43.681191 | AM8: =$AF$26*E8^2+$AG$26*E8+$AH$26 -> 21.80067
A9: 2100 | B9: 159 | C9: 6.9690485 | D9: =$K$3*C9 -> 13.938097 | E9: 16.117909 | F9: =ABS(E9-E8) -> 2.6487551 | G9: =$J$3*E9 -> 145.06118 | H9: 42.998974 | AM9: =$AF$26*E9^2+$AG$26*E9+$AH$26 -> 26.043676
A10: 2400 | B10: 129 | C10: -12.56172 | D10: =$K$3*C10 -> -25.12344 | E10: 17.124766 | F10: =ABS(E10-E9) -> 1.0068573 | G10: =$J$3*E10 -> 154.12289 | H10: 43.293216 | AM10: =$AF$26*E10^2+$AG$26*E10+$AH$26 -> 27.667311
A11: 2700 | B11: 144 | C11: -5.8404789 | D11: =$K$3*C11 -> -11.680958 | E11: 17.297797 | F11: =ABS(E11-E10) -> 0.17303106 | G11: =$J$3*E11 -> 155.68017 | H11: 43.983346 | AM11: =$AF$26*E11^2+$AG$26*E11+$AH$26 -> 27.946934
A12: 3000 | B12: 179 | C12: 5.5720765 | D12: =$K$3*C12 -> 11.144153 | E12: 18.650534 | F12: =ABS(E12-E11) -> 1.3527374 | G12: =$J$3*E12 -> 167.85481 | H12: 43.948987 | AM12: =$AF$26*E12^2+$AG$26*E12+$AH$26 -> 30.139032
A13: 3300 | B13: 249 | C13: 24.507607 | D13: =$K$3*C13 -> 49.015214 | E13: 22.220333 | F13: =ABS(E13-E12) -> 3.5697987 | G13: =$J$3*E13 -> 199.983 | H13: 42.697113 | AM13: =$AF$26*E13^2+$AG$26*E13+$AH$26 -> 35.975246
A14: 3600 | B14: 293 | C14: 24.002257 | D14: =$K$3*C14 -> 48.004514 | E14: 27.221465 | F14: =ABS(E14-E13) -> 5.0011315 | G14: =$J$3*E14 -> 244.99318 | H14: 40.796953 | AM14: =$AF$26*E14^2+$AG$26*E14+$AH$26 -> 44.276882
A15: 3900 | B15: 377 | C15: 37.601629 | D15: =$K$3*C15 -> 75.203257 | E15: 33.532529 | F15: =ABS(E15-E14) -> 6.3110645 | G15: =$J$3*E15 -> 301.79276 | H15: 38.322602 | AM15: =$AF$26*E15^2+$AG$26*E15+$AH$26 -> 54.961728
A16: 4200 | B16: 378 | C16: 12.40578 | D16: =$K$3*C16 -> 24.81156 | E16: 39.242737 | F16: =ABS(E16-E15) -> 5.7102081 | G16: =$J$3*E16 -> 353.18464 | H16: 36.454005 | AM16: =$AF$26*E16^2+$AG$26*E16+$AH$26 -> 64.830051
A17: 4500 | B17: 389 | C17: 1.5802726 | D17: =$K$3*C17 -> 3.1605451 | E17: 42.870528 | F17: =ABS(E17-E16) -> 3.6277911 | G17: =$J$3*E17 -> 385.83475 | H17: 35.947512 | AM17: =$AF$26*E17^2+$AG$26*E17+$AH$26 -> 71.198634
A18: 4800 | B18: 389 | C18: -8.7234981 | D18: =$K$3*C18 -> -17.446996 | E18: 45.160217 | F18: =ABS(E18-E17) -> 2.2896884 | G18: =$J$3*E18 -> 406.44195 | H18: 36.264498 | AM18: =$AF$26*E18^2+$AG$26*E18+$AH$26 -> 75.257803
... A20: 5400 | B20: 455 | C20: 9.0534798 | D20: =$K$3*C20 -> 18.10696 | E20: 48.542867 | F20: =ABS(E20-E19) -> 2.2347557 | G20: =$J$3*E20 -> 436.88581 | H20: 37.349862 | AM20: =$AF$26*E20^2+$AG$26*E20+$AH$26 -> 81.310693
A21: 5700 | B21: 526 | C21: 23.720879 | D21: =$K$3*C21 -> 47.441758 | E21: 53.17216 | F21: =ABS(E21-E20) -> 4.6292924 | G21: =$J$3*E21 -> 478.54944 | H21: 36.013013 | AF21: Fuel consumption (kW) in y axis | AM21: =$AF$26*E21^2+$AG$26*E21+$AH$26 -> 89.702784
A22: 6000 | B22: 713 | C22: 47.525207 | D22: =$K$3*C22 -> 95.050414 | E22: 66.286962 | F22: =ABS(E22-E21) -> 13.114802 | G22: =$J$3*E22 -> 596.58266 | H22: 32.508277 | AF22: Power output (kW) in x axis | AM22: =$AF$26*E22^2+$AG$26*E22+$AH$26 -> 114.15816
A23: 6300 | B23: 737 | C23: 28.917917 | D23: =$K$3*C23 -> 57.835834 | E23: 75.460816 | F23: =ABS(E23-E22) -> 9.1738543 | G23: =$J$3*E23 -> 679.14735 | H23: 29.431862 | AM23: =$AF$26*E23^2+$AG$26*E23+$AH$26 -> 131.86277
A24: 6600 | B24: 745 | C24: 8.2100844 | D24: =$K$3*C24 -> 16.420169 | E24: 80.951197 | F24: =ABS(E24-E23) -> 5.4903805 | G24: =$J$3*E24 -> 728.56077 | H24: 28.03685 | AM24: =$AF$26*E24^2+$AG$26*E24+$AH$26 -> 142.6941
A25: 6900 | B25: 747 | C25: -7.0445425 | D25: =$K$3*C25 -> -14.089085 | E25: 84.563131 | F25: =ABS(E25-E24) -> 3.611934 | G25: =$J$3*E25 -> 761.06818 | H25: 28.039133 | AF25: k1 | AG25: k2 | AH25: k3 | AM25: =$AF$26*E25^2+$AG$26*E25+$AH$26 -> 149.91582
A26: 7200 | B26: 746 | C26: -17.406079 | D26: =$K$3*C26 -> -34.812158 | E26: 86.754444 | F26: =ABS(E26-E25) -> 2.1913131 | G26: =$J$3*E26 -> 780.79 | H26: 29.027488 | AF26: 0.00292448 | AG26: 1.51536 | AH26: 0.8595 | AM26: =$AF$26*E26^2+$AG$26*E26+$AH$26 -> 154.33433
A27: 7500 | B27: 744 | C27: -23.597887 | D27: =$K$3*C27 -> -47.195775 | E27: 87.908098 | F27: =ABS(E27-E26) -> 1.1536539 | G27: =$J$3*E27 -> 791.17288 | H27: 30.646875 | AM27: =$AF$26*E27^2+$AG$26*E27+$AH$26 -> 156.67181
A28: 7800 | B28: 745 | C28: -25.318939 | D28: =$K$3*C28 -> -50.637878 | E28: 88.401614 | F28: =ABS(E28-E27) -> 0.49351581 | G28: =$J$3*E28 -> 795.61452 | H28: 32.558664 | AM28: =$AF$26*E28^2+$AG$26*E28+$AH$26 -> 157.67413
A29: 8100 | B29: 741 | C29: -27.328212 | D29: =$K$3*C29 -> -54.656424 | E29: 88.403693 | F29: =ABS(E29-E28) -> 0.0020789506 | G29: =$J$3*E29 -> 795.63323 | H29: 34.613438 | AM29: =$AF$26*E29^2+$AG$26*E29+$AH$26 -> 157.67835
A30: 8400 | B30: 744 | C30: -24.606344 | D30: =$K$3*C30 -> -49.212688 | E30: 88.132156 | F30: =ABS(E30-E29) -> 0.27153701 | G30: =$J$3*E30 -> 793.1894 | H30: 36.625098 | AM30: =$AF$26*E30^2+$AG$26*E30+$AH$26 -> 157.12669
A31: 8700 | B31: 744 | C31: -22.971094 | D31: =$K$3*C31 -> -45.942188 | E31: 87.768805 | F31: =ABS(E31-E30) -> 0.36335046 | G31: =$J$3*E31 -> 789.91925 | H31: 38.469359 | AM31: =$AF$26*E31^2+$AG$26*E31+$AH$26 -> 156.38917
A32: 9000 | B32: 742 | C32: -21.702776 | D32: =$K$3*C32 -> -43.405552 | E32: 87.264778 | F32: =ABS(E32-E31) -> 0.50402707 | G32: =$J$3*E32 -> 785.383 | H32: 40.200916 | AM32: =$AF$26*E32^2+$AG$26*E32+$AH$26 -> 155.36738
A33: 9300 | B33: 745 | C33: -17.908121 | D33: =$K$3*C33 -> -35.816242 | E33: 86.754871 | F33: =ABS(E33-E32) -> 0.50990756 | G33: =$J$3*E33 -> 780.79384 | H33: 41.728335 | AM33: =$AF$26*E33^2+$AG$26*E33+$AH$26 -> 154.33519
A34: 9600 | B34: 746 | C34: -15.470687 | D34: =$K$3*C34 -> -30.941374 | E34: 86.324368 | F34: =ABS(E34-E33) -> 0.43050222 | G34: =$J$3*E34 -> 776.91932 | H34: 43.017603 | AM34: =$AF$26*E34^2+$AG$26*E34+$AH$26 -> 153.46492
A35: 9900 | B35: 748 | C35: -12.811278 | D35: =$K$3*C35 -> -25.622555 | E35: 85.955633 | F35: =ABS(E35-E34) -> 0.36873576 | G35: =$J$3*E35 -> 773.60069 | H35: 44.108338 | AF35: BATTERY DEGRADATION | AM35: =$AF$26*E35^2+$AG$26*E35+$AH$26 -> 152.72037
A36: 10200 | B36: 747 | C36: -11.734363 | D36: =$K$3*C36 -> -23.468725 | E36: 85.605244 | F36: =ABS(E36-E35) -> 0.35038913 | G36: =$J$3*E36 -> 770.44719 | H36: 45.058493 | AM36: =$AF$26*E36^2+$AG$26*E36+$AH$26 -> 152.0136
A37: 10500 | B37: 746 | C37: -10.515963 | D37: =$K$3*C37 -> -21.031926 | E37: 85.223403 | F37: =ABS(E37-E36) -> 0.38184078 | G37: =$J$3*E37 -> 767.01062 | H37: 45.919044 | AM37: =$AF$26*E37^2+$AG$26*E37+$AH$26 -> 151.24422
A38: 10800 | B38: 748 | C38: -8.0594736 | D38: =$K$3*C38 -> -16.118947 | E38: 84.899749 | F38: =ABS(E38-E37) -> 0.32365411 | G38: =$J$3*E38 -> 764.09774 | H38: 46.633374 | AM38: =$AF$26*E38^2+$AG$26*E38+$AH$26 -> 150.59274
A39: 11100 | B39: 746 | C39: -7.7274686 | D39: =$K$3*C39 -> -15.454937 | E39: 84.603783 | F39: =ABS(E39-E38) -> 0.29596515 | G39: =$J$3*E39 -> 761.43405 | H39: 47.245572 | AM39: =$AF$26*E39^2+$AG$26*E39+$AH$26 -> 149.99753
A40: 11400 | B40: 749 | C40: -5.1642845 | D40: =$K$3*C40 -> -10.328569 | E40: 84.367516 | F40: =ABS(E40-E39) -> 0.23626705 | G40: =$J$3*E40 -> 759.30765 | H40: 47.738912 | AM40: =$AF$26*E40^2+$AG$26*E40+$AH$26 -> 149.52275
A41: 11700 | B41: 745 | C41: -6.0965769 | D41: =$K$3*C41 -> -12.193154 | E41: 84.130292 | F41: =ABS(E41-E40) -> 0.23722481 | G41: =$J$3*E41 -> 757.17262 | H41: 48.179044 | AM41: =$AF$26*E41^2+$AG$26*E41+$AH$26 -> 149.04637
A42: 12000 | B42: 738 | C42: -7.6119067 | D42: =$K$3*C42 -> -15.223813 | E42: 83.689294 | F42: =ABS(E42-E41) -> 0.44099768 | G42: =$J$3*E42 -> 753.20365 | H42: 48.715799 | AM42: =$AF$26*E42^2+$AG$26*E42+$AH$26 -> 148.16167
A43: 12300 | B43: 740 | C43: -4.628493 | D43: =$K$3*C43 -> -9.2569859 | E43: 83.248529 | F43: =ABS(E43-E42) -> 0.44076508 | G43: =$J$3*E43 -> 749.23676 | H43: 49.182442 | AM43: =$AF$26*E43^2+$AG$26*E43+$AH$26 -> 147.27857
A44: 12600 | B44: 742 | C44: -2.5198573 | D44: =$K$3*C44 -> -5.0397145 | E44: 83.002182 | F44: =ABS(E44-E43) -> 0.24634696 | G44: =$J$3*E44 -> 747.01964 | H44: 49.453951 | AM44: =$AF$26*E44^2+$AG$26*E44+$AH$26 -> 146.78549
A45: 12900 | B45: 740 | C45: -2.6631606 | D45: =$K$3*C45 -> -5.3263212 | E45: 82.811833 | F45: =ABS(E45-E44) -> 0.190349 | G45: =$J$3*E45 -> 745.3065 | H45: 49.655742 | AM45: =$AF$26*E45^2+$AG$26*E45+$AH$26 -> 146.40474
A46: 13200 | B46: 739 | C46: -2.2327958 | D46: =$K$3*C46 -> -4.4655916 | E46: 82.605095 | F46: =ABS(E46-E45) -> 0.20673826 | G46: =$J$3*E46 -> 743.44585 | H46: 49.844703 | AM46: =$AF$26*E46^2+$AG$26*E46+$AH$26 -> 145.99144
A47: 13500 | B47: 741 | C47: -0.66050178 | D47: =$K$3*C47 -> -1.3210036 | E47: 82.477915 | F47: =ABS(E47-E46) -> 0.12717979 | G47: =$J$3*E47 -> 742.30123 | H47: 49.952501 | AM47: =$AF$26*E47^2+$AG$26*E47+$AH$26 -> 145.73732
... A86: 25200 | B86: 732 | C86: 0.058218718 | D86: =$K$3*C86 -> 0.11643744 | E86: 81.318285 | F86: =ABS(E86-E85) -> 0.0014905551 | G86: =$J$3*E86 -> 731.86456 | H86: 50.18086 | AM86: =$AF$26*E86^2+$AG$26*E86+$AH$26 -> 143.42458
A87: 25500 | B87: 735 | C87: 1.3369302 | D87: =$K$3*C87 -> 2.6738604 | E87: 81.367441 | F87: =ABS(E87-E86) -> 0.049156914 | G87: =$J$3*E87 -> 732.30697 | H87: 50.122826 | AC87: EC at 41.6% DoD | AE87: MAX cycles at 41.65% DoD | AM87: =$AF$26*E87^2+$AG$26*E87+$AH$26 -> 143.52246
A88: 25800 | B88: 730 | C88: -1.103109 | D88: =$K$3*C88 -> -2.206218 | E88: 81.354148 | F88: =ABS(E88-E87) -> 0.013293269 | G88: =$J$3*E88 -> 732.18733 | H88: 50.120969 | AC88: 1.43 | AE88: 70000 | AM88: =$AF$26*E88^2+$AG$26*E88+$AH$26 -> 143.49599
A89: 26100 | B89: 753 | C89: 8.5576473 | D89: =$K$3*C89 -> 17.115295 | E89: 81.762735 | F89: =ABS(E89-E88) -> 0.40858731 | G89: =$J$3*E89 -> 735.86462 | H89: 49.802136 | AM89: =$AF$26*E89^2+$AG$26*E89+$AH$26 -> 144.31005
A90: 26400 | B90: 841 | C90: 40.207858 | D90: =$K$3*C90 -> 80.415716 | E90: 84.506672 | F90: =ABS(E90-E89) -> 2.7439361 | G90: =$J$3*E90 -> 760.56004 | H90: 47.800884 | AM90: =$AF$26*E90^2+$AG$26*E90+$AH$26 -> 149.80235
A91: 26700 | B91: 839 | C91: 22.790737 | D91: =$K$3*C91 -> 45.581474 | E91: 88.155041 | F91: =ABS(E91-E90) -> 3.6483695 | G91: =$J$3*E91 -> 793.39537 | H91: 45.386352 | AM91: =$AF$26*E91^2+$AG$26*E91+$AH$26 -> 157.17317
A92: 27000 | B92: 836 | C92: 10.436002 | D92: =$K$3*C92 -> 20.872004 | E92: 90.567037 | F92: =ABS(E92-E91) -> 2.4119954 | G92: =$J$3*E92 -> 815.10333 | H92: 44.12468 | AM92: =$AF$26*E92^2+$AG$26*E92+$AH$26 -> 162.08888
A93: 27300 | B93: 837 | C93: 3.6997279 | D93: =$K$3*C93 -> 7.3994558 | E93: 92.174957 | F93: =ABS(E93-E92) -> 1.6079207 | G93: =$J$3*E93 -> 829.57462 | H93: 43.59289 | AM93: =$AF$26*E93^2+$AG$26*E93+$AH$26 -> 165.38478
A94: 27600 | B94: 837 | C94: -1.2056826 | D94: =$K$3*C94 -> -2.4113653 | E94: 93.264967 | F94: =ABS(E94-E93) -> 1.0900095 | G94: =$J$3*E94 -> 839.3847 | H94: 43.509528 | AA94: PRAXIS BATTERIES | AM94: =$AF$26*E94^2+$AG$26*E94+$AH$26 -> 167.62766
A95: 27900 | B95: 836 | C95: -4.7494333 | D95: =$K$3*C95 -> -9.4988667 | E95: 93.941306 | F95: =ABS(E95-E94) -> 0.67633886 | G95: =$J$3*E95 -> 845.47175 | H95: 43.750978 | Z95: 513.01 GreenBattery Rev1.12 A4.cdr (praxis-automation.eu) | AM95: =$AF$26*E95^2+$AG$26*E95+$AH$26 -> 169.02284
A96: 28200 | B96: 834 | C96: -7.2721089 | D96: =$K$3*C96 -> -14.544218 | E96: 94.279655 | F96: =ABS(E96-E95) -> 0.33834885 | G96: =$J$3*E96 -> 848.51689 | H96: 44.225212 | AM96: =$AF$26*E96^2+$AG$26*E96+$AH$26 -> 169.72181
A97: 28500 | B97: 834 | C97: -7.8074063 | D97: =$K$3*C97 -> -15.614813 | E97: 94.39859 | F97: =ABS(E97-E96) -> 0.11893579 | G97: =$J$3*E97 -> 849.58731 | H97: 44.812654 | AM97: =$AF$26*E97^2+$AG$26*E97+$AH$26 -> 169.96766
A98: 28800 | B98: 834 | C98: -7.8270395 | D98: =$K$3*C98 -> -15.654079 | E98: 94.402953 | F98: =ABS(E98-E97) -> 0.004362388 | G98: =$J$3*E98 -> 849.62657 | H98: 45.420104 | AM98: =$AF$26*E98^2+$AG$26*E98+$AH$26 -> 169.97668
A99: 29100 | B99: 834 | C99: -7.5067026 | D99: =$K$3*C99 -> -15.013405 | E99: 94.331773 | F99: =ABS(E99-E98) -> 0.07118021 | G99: =$J$3*E99 -> 848.98595 | H99: 46.014856 | AM99: =$AF$26*E99^2+$AG$26*E99+$AH$26 -> 169.82953
A100: 29400 | B100: 837 | C100: -5.75706 | D100: =$K$3*C100 -> -11.51412 | E100: 94.276287 | F100: =ABS(E100-E99) -> 0.055485156 | G100: =$J$3*E100 -> 848.48659 | H100: 46.525357 | AM100: =$AF$26*E100^2+$AG$26*E100+$AH$26 -> 169.71485
A101: 29700 | B101: 837 | C101: -5.5791541 | D101: =$K$3*C101 -> -11.158308 | E101: 94.23677 | F101: =ABS(E101-E100) -> 0.03951774 | G101: =$J$3*E101 -> 848.13093 | H101: 46.965234 | AM101: =$AF$26*E101^2+$AG$26*E101+$AH$26 -> 169.63318
A102: 30000 | B102: 833 | C102: -6.8491065 | D102: =$K$3*C102 -> -13.698213 | E102: 94.074568 | F102: =ABS(E102-E101) -> 0.16220161 | G102: =$J$3*E102 -> 846.67111 | H102: 47.451333 | AM102: =$AF$26*E102^2+$AG$26*E102+$AH$26 -> 169.29806
A103: 30300 | B103: 834 | C103: -5.3602496 | D103: =$K$3*C103 -> -10.720499 | E103: 93.854817 | F103: =ABS(E103-E102) -> 0.2197505 | G103: =$J$3*E103 -> 844.69336 | H103: 47.92144 | AM103: =$AF$26*E103^2+$AG$26*E103+$AH$26 -> 168.84428
A104: 30600 | B104: 833 | C104: -4.9634076 | D104: =$K$3*C104 -> -9.9268152 | E104: 93.655544 | F104: =ABS(E104-E103) -> 0.19927316 | G104: =$J$3*E104 -> 842.8999 | H104: 48.321281 | AM104: =$AF$26*E104^2+$AG$26*E104+$AH$26 -> 168.43304
A105: 30900 | B105: 835 | C105: -3.2721101 | D105: =$K$3*C105 -> -6.5442202 | E105: 93.501922 | F105: =ABS(E105-E104) -> 0.15362262 | G105: =$J$3*E105 -> 841.5173 | H105: 48.636549 | AM105: =$AF$26*E105^2+$AG$26*E105+$AH$26 -> 168.11616
A106: 31200 | B106: 837 | C106: -2.0217106 | D106: =$K$3*C106 -> -4.0434212 | E106: 93.446282 | F106: =ABS(E106-E105) -> 0.055639722 | G106: =$J$3*E106 -> 841.01654 | H106: 48.838792 | Z106: DoD(%) | AA106: Cycles (1C) | AM106: =$AF$26*E106^2+$AG$26*E106+$AH$26 -> 168.00142
A107: 31500 | B107: 806 | C107: -14.499045 | D107: =$K$3*C107 -> -28.998089 | E107: 92.774777 | F107: =ABS(E107-E106) -> 0.67150531 | G107: =$J$3*E107 -> 834.97299 | H107: 49.513525 | Z107: 5 | AA107: 180000 | AM107: =$AF$26*E107^2+$AG$26*E107+$AH$26 -> 166.61815
A108: 31800 | B108: 745 | C108: -34.143315 | D108: =$K$3*C108 -> -68.286631 | E108: 90.362688 | F108: =ABS(E108-E107) -> 2.4120887 | G108: =$J$3*E108 -> 813.26419 | H108: 51.448305 | Z108: 10 | AA108: 130000 | AM108: =$AF$26*E108^2+$AG$26*E108+$AH$26 -> 161.6711
A109: 32100 | B109: 705 | C109: -36.690974 | D109: =$K$3*C109 -> -73.381948 | E109: 86.484562 | F109: =ABS(E109-E108) -> 3.8781264 | G109: =$J$3*E109 -> 778.36106 | H109: 54.18965 | Z109: 20 | AA109: 80000 | AM109: =$AF$26*E109^2+$AG$26*E109+$AH$26 -> 153.78863
A110: 32400 | B110: 710 | C110: -18.251812 | D110: =$K$3*C110 -> -36.503624 | E110: 82.942594 | F110: =ABS(E110-E109) -> 3.5419673 | G110: =$J$3*E110 -> 746.48335 | H110: 56.260034 | Z110: 50 | AA110: 24000 | AG110: at the REQUIRED DoD (%) | AM110: =$AF$26*E110^2+$AG$26*E110+$AH$26 -> 146.66627
A111: 32700 | B111: 488 | C111: -64.882568 | D111: =$K$3*C111 -> -129.76514 | E111: 71.179498 | F111: =ABS(E111-E110) -> 11.763096 | G111: =$J$3*E111 -> 640.61548 | H111: 60.37622 | Z111: 80 | AA111: 6200 | AG111: EC | AH111: MAX CYCLES | AM111: =$AF$26*E111^2+$AG$26*E111+$AH$26 -> 123.539
A112: 33000 | B112: 358 | C112: -54.865676 | D112: =$K$3*C112 -> -109.73135 | E112: 52.62378 | F112: =ABS(E112-E111) -> 18.555718 | G112: =$J$3*E112 -> 473.61402 | H112: 64.922451 | Z112: 90 | AA112: 5000 | AG112: 1.43 | AH112: =AA118 -> 39680 | AM112: =$AF$26*E112^2+$AG$26*E112+$AH$26 -> 88.702124
A113: 33300 | B113: 325 | C113: -33.463894 | D113: =$K$3*C113 -> -66.927789 | E113: 43.54702 | F113: =ABS(E113-E112) -> 9.07676 | G113: =$J$3*E113 -> 391.92318 | H113: 68.277457 | AM113: =$AF$26*E113^2+$AG$26*E113+$AH$26 -> 72.39473
A114: 33600 | B114: 325 | C114: -5.6133933 | D114: =$K$3*C114 -> -11.226787 | E114: 37.358142 | F114: =ABS(E114-E113) -> 6.1888784 | G114: =$J$3*E114 -> 336.22328 | H114: 69.688751 | AM114: =$AF$26*E114^2+$AG$26*E114+$AH$26 -> 61.552028
A115: 33900 | B115: 325 | C115: 10.766761 | D115: =$K$3*C115 -> 21.533521 | E115: 33.718193 | F115: =ABS(E115-E114) -> 3.6399493 | G115: =$J$3*E115 -> 303.46373 | H115: 69.429132 | AM115: =$AF$26*E115^2+$AG$26*E115+$AH$26 -> 55.27959
A116: 34200 | B116: 323 | C116: 18.692993 | D116: =$K$3*C116 -> 37.385985 | E116: 31.734625 | F116: =ABS(E116-E115) -> 1.9835672 | G116: =$J$3*E116 -> 285.61163 | H116: 68.254094 | Z116: x | AA116: y | AM116: =$AF$26*E116^2+$AG$26*E116+$AH$26 -> 51.894086
A117: 34500 | B117: 332 | C117: 26.222512 | D117: =$K$3*C117 -> 52.445024 | E117: 31.061395 | F117: =ABS(E117-E116) -> 0.67323021 | G117: =$J$3*E117 -> 279.55256 | H117: 66.476065 | Z117: 20 | AA117: 80000 | AM117: =$AF$26*E117^2+$AG$26*E117+$AH$26 -> 50.750264
A118: 34800 | B118: 338 | C118: 27.837553 | D118: =$K$3*C118 -> 55.675107 | E118: 31.36916 | F118: =ABS(E118-E117) -> 0.3077646 | G118: =$J$3*E118 -> 282.32244 | H118: 64.361858 | Z118: 41.6 | AA118: =AA117+((Z118-Z117)*(AA119-AA117))/(Z119-Z117) -> 39680 | AM118: =$AF$26*E118^2+$AG$26*E118+$AH$26 -> 51.272829
A119: 35100 | B119: 336 | C119: 24.206188 | D119: =$K$3*C119 -> 48.412376 | E119: 31.953907 | F119: =ABS(E119-E118) -> 0.58474763 | G119: =$J$3*E119 -> 287.58517 | H119: 62.345905 | Z119: 50 | AA119: 24000 | AM119: =$AF$26*E119^2+$AG$26*E119+$AH$26 -> 52.26722
A120: 35400 | B120: 341 | C120: 23.480259 | D120: =$K$3*C120 -> 46.960519 | E120: 32.670758 | F120: =ABS(E120-E119) -> 0.71685076 | G120: =$J$3*E120 -> 294.03682 | H120: 60.488869 | AM120: =$AF$26*E120^2+$AG$26*E120+$AH$26 -> 53.488987
A121: 35700 | B121: 337 | C121: 18.415546 | D121: =$K$3*C121 -> 36.831093 | E121: 33.351806 | F121: =ABS(E121-E120) -> 0.68104757 | G121: =$J$3*E121 -> 300.16625 | H121: 58.874409 | AM121: =$AF$26*E121^2+$AG$26*E121+$AH$26 -> 54.652517
A122: 36000 | B122: 331 | C122: 13.830027 | D122: =$K$3*C122 -> 27.660054 | E122: 33.70414 | F122: =ABS(E122-E121) -> 0.35233461 | G122: =$J$3*E122 -> 303.33726 | H122: 57.635141 | AM122: =$AF$26*E122^2+$AG$26*E122+$AH$26 -> 55.255525
A123: 36300 | B123: 332 | C123: 13.139319 | D123: =$K$3*C123 -> 26.278638 | E123: 33.968728 | F123: =ABS(E123-E122) -> 0.26458725 | G123: =$J$3*E123 -> 305.71855 | H123: 56.587073 | AM123: =$AF$26*E123^2+$AG$26*E123+$AH$26 -> 55.708834
A124: 36600 | B124: 332 | C124: 11.659232 | D124: =$K$3*C124 -> 23.318464 | E124: 34.297631 | F124: =ABS(E124-E123) -> 0.32890345 | G124: =$J$3*E124 -> 308.67868 | H124: 55.626526 | AM124: =$AF$26*E124^2+$AG$26*E124+$AH$26 -> 56.272904
A125: 36900 | B125: 333 | C125: 10.570194 | D125: =$K$3*C125 -> 21.140388 | E125: 34.650742 | F125: =ABS(E125-E124) -> 0.35311127 | G125: =$J$3*E125 -> 311.85668 | H125: 54.76464 | AM125: =$AF$26*E125^2+$AG$26*E125+$AH$26 -> 56.879196
A126: 37200 | B126: 351 | C126: 15.778768 | D126: =$K$3*C126 -> 31.557535 | E126: 35.493239 | F126: =ABS(E126-E125) -> 0.84249691 | G126: =$J$3*E126 -> 319.43915 | H126: 53.717973 | AM126: =$AF$26*E126^2+$AG$26*E126+$AH$26 -> 58.328707
A127: 37500 | B127: 359 | C127: 14.091745 | D127: =$K$3*C127 -> 28.183491 | E127: 36.75701 | F127: =ABS(E127-E126) -> 1.2637711 | G127: =$J$3*E127 -> 330.81309 | H127: 52.559295 | AM127: =$AF$26*E127^2+$AG$26*E127+$AH$26 -> 60.510803
A128: 37800 | B128: 354 | C128: 7.493266 | D128: =$K$3*C128 -> 14.986532 | E128: 37.667785 | F128: =ABS(E128-E127) -> 0.91077496 | G128: =$J$3*E128 -> 339.01007 | H128: 51.742465 | AM128: =$AF$26*E128^2+$AG$26*E128+$AH$26 -> 62.089189
A129: 38100 | B129: 348 | C129: 2.993882 | D129: =$K$3*C129 -> 5.987764 | E129: 38.000976 | F129: =ABS(E129-E128) -> 0.33319087 | G129: =$J$3*E129 -> 342.00879 | H129: 51.350724 | AM129: =$AF$26*E129^2+$AG$26*E129+$AH$26 -> 62.667825
A130: 38400 | B130: 360 | C130: 7.0871803 | D130: =$K$3*C130 -> 14.174361 | E130: 38.42465 | F130: =ABS(E130-E129) -> 0.42367349 | G130: =$J$3*E130 -> 345.82185 | H130: 50.943003 | AM130: =$AF$26*E130^2+$AG$26*E130+$AH$26 -> 63.404536
A131: 38700 | B131: 330 | C131: -6.8438918 | D131: =$K$3*C131 -> -13.687784 | E131: 38.187181 | F131: =ABS(E131-E130) -> 0.23746883 | G131: =$J$3*E131 -> 343.68463 | H131: 50.984514 | AM131: =$AF$26*E131^2+$AG$26*E131+$AH$26 -> 62.991481
... A144: 42600 | B144: 0 | C144: -1.1816611 | D144: =$K$3*C144 -> -2.3633223 | E144: 0.034381676 | F144: =ABS(E144-E143) -> 1.8245689 | G144: =$J$3*E144 -> 0.30943508 | H144: 59.644968 | AM144: =$AF$26*E144^2+$AG$26*E144+$AH$26 -> 0.91160407
E145: SUM(ABS(Pfc(t)-Pfc(t-1) | F145: =SUM(F2:F144) -> 219.1629 | AL145: sum | AM145: =SUM(AM2:AM144) -> 15754.26
A148: TRANSIENT DEGRADATION
A149: Coeff | B149: 0.4185 | C149: Microvolt/DkW
A150: sum(Abs(Pfc(t)-Pfc(t-1))) | B150: =F145 -> 219.1629 | C150: DkW | D150: FROM: Integrated design and control optimization of fuel cell hybrid mining truck with minimized lifecycle cost
A151: TotalTransient Degrad | B151: =B150*B149 -> 91.719675 | C151: microvolt | D151: WHERE THEY GIVE 0.4185 microvolt for load changing degradation which is also for a same size of FC…
A153: START/STOP CYCLE
A154: Cycles | B154: 1 | C154: Cycles | D154: Always 1 start/stop cycle start from 0 and end to 0 at end of voyage
...

Sheet Lithua_Sweden_600LPF_125Ah
A1: Time (sec) | B1: Load Profile (kW) | C1: Battery power (kW) | D1: Total Batt Power (kW) | E1: FC power (kW) | F1: Abs(Pfc(t)-Pfc(t-1) | G1: TotalFC power(kw) | H1: Battery SoC (%) | AK1: Sampling_dt(sec) | AL1: Sampling_dt(hrs) | AM1: Fuel consumption (f(pfc)) for 1 FC (kW) | AN1: Addit_Ploss(kW) | AO1: Fctotal(kw) | AQ1: FC_total*hrs(kwh) | AR1: Ke-m ( kg/kwh) | AS1: Fuel consumption (kg) | AU1: H2 in $/kg | AV1: Fuel cost | AW1: H2 price in $/kwh | AY1: Fuel cost ($) | BA1: FUEL CONSUMPTION CALCULATION ALTERNATIVE | BF1: Fuel consumption (f(pfc)) for 1 FC (kW) | BH1: Total FC (kg)
A2: 0 | B2: 0 | C2: 12.350136 | D2: =$K$3*C2 -> 24.700273 | E2: 0 | F2: 0 | G2: =$J$3*E2 -> 0 | H2: 50 | J2: Nfc | K2: Nbat | AK2: 300 | AL2: =AK2/3600 -> 0.083333333 | AM2: =$AF$26*E2^2+$AG$26*E2+$AH$26 -> 0.8595 | AO2: =J3*AM365+AN2 -> 614573.19 | AQ2: =AO2*AL2 -> 51214.432 | AR2: 0.03 | AS2: =AQ2*AR2 -> 1536.433 | AU2: 4 | AV2: =AU2*AS2 -> 6145.7319 | AW2: =AU2/33.35 -> 0.11994003 | AY2: =AQ2*AW2 -> 6142.6605 | BF2: =$BB$5*E2^2+$BC$5*E2+$BD$5 -> 0.08 | BH2: =J3*BF365*AL2 -> 1549.9545
A3: 300 | B3: 0 | C3: -0.075000176 | D3: =$K$3*C3 -> -0.15000035 | E3: 0.016667063 | F3: =ABS(E3-E2) -> 0.016667063 | G3: =$J$3*E3 -> 0.15000356 | H3: 50.542869 | J3: 9 | K3: 2 | AM3: =$AF$26*E3^2+$AG$26*E3+$AH$26 -> 0.88475741 | BB3: FUNCTION OF Kg now the FC | BF3: =$BB$5*E3^2+$BC$5*E3+$BD$5 -> 0.080739545
A4: 600 | B4: 17 | C4: 8.4998959 | D4: =$K$3*C4 -> 16.999792 | E4: 2.9665391e-05 | F4: =ABS(E4-E3) -> 0.016637397 | G4: =$J$3*E4 -> 0.00026698852 | H4: 50.214615 | AG4: Fuel consumption | AM4: =$AF$26*E4^2+$AG$26*E4+$AH$26 -> 0.85954495 | AR4: *Source: Cost-effective control of Roll-on/Roll-off Emission-Free Ships | BB4: k1 | BC4: k2 | BD4: k3 | BF4: =$BB$5*E4^2+$BC$5*E4+$BD$5 -> 0.080001316
A5: 900 | B5: 67 | C5: 25.430634 | D5: =$K$3*C5 -> 50.861268 | E5: 1.7931813 | F5: =ABS(E5-E4) -> 1.7931516 | G5: =$J$3*E5 -> 16.138631 | H5: 48.691215 | AM5: =$AF$26*E5^2+$AG$26*E5+$AH$26 -> 3.5862188 | AR5: CHECK END OF LIFE INCREASE IN kg | AS5: =AS2+25.29%*AS2 -> 1924.9969 | BB5: 9.712e-05 | BC5: 0.04437 | BD5: 0.08 | BF5: =$BB$5*E5^2+$BC$5*E5+$BD$5 -> 0.15987574
A6: 1200 | B6: 135 | C6: 36.9834 | D6: =$K$3*C6 -> 73.966799 | E6: 6.7814191 | F6: =ABS(E6-E5) -> 4.9882378 | G6: =$J$3*E6 -> 61.032772 | H6: 46.237565 | K6: DC BUS VOLTAGE | AM6: =$AF$26*E6^2+$AG$26*E6+$AH$26 -> 11.270281 | AR6: 25.29% increase in kg due to FC degrad | BF6: =$BB$5*E6^2+$BC$5*E6+$BD$5 -> 0.38535788
A7: 1500 | B7: 135 | C7: 16.454043 | D7: =$K$3*C7 -> 32.908087 | E7: 11.343498 | F7: =ABS(E7-E6) -> 4.5620786 | G7: =$J$3*E7 -> 102.09148 | H7: 44.221444 | AM7: =$AF$26*E7^2+$AG$26*E7+$AH$26 -> 18.42529 | BF7: =$BB$5*E7^2+$BC$5*E7+$BD$5 -> 0.5958079
A8: 1800 | B8: 134 | C8: 3.9510781 | D8: =$K$3*C8 -> 7.9021563 | E8: 14.010817 | F8: =ABS(E8-E7) -> 2.6673189 | G8: =$J$3*E8 -> 126.09735 | H8: 43.473242 | AM8: =$AF$26*E8^2+$AG$26*E8+$AH$26 -> 22.665015 | BF8: =$BB$5*E8^2+$BC$5*E8+$BD$5 -> 0.72072488
A9: 2100 | B9: 133 | C9: -3.0605996 | D9: =$K$3*C9 -> -6.1211992 | E9: 15.457848 | F9: =ABS(E9-E8) -> 1.4470312 | G9: =$J$3*E9 -> 139.12063 | H9: 43.466138 | AM9: =$AF$26*E9^2+$AG$26*E9+$AH$26 -> 24.982494 | BF9: =$BB$5*E9^2+$BC$5*E9+$BD$5 -> 0.78907105
A10: 2400 | B10: 131 | C10: -7.0719494 | D10: =$K$3*C10 -> -14.143899 | E10: 16.127032 | F10: =ABS(E10-E9) -> 0.66918447 | G10: =$J$3*E10 -> 145.14329 | H10: 43.876686 | AM10: =$AF$26*E10^2+$AG$26*E10+$AH$26 -> 26.058362 | BF10: =$BB$5*E10^2+$BC$5*E10+$BD$5 -> 0.8208155
A11: 2700 | B11: 131 | C11: -8.1184903 | D11: =$K$3*C11 -> -16.236981 | E11: 16.359594 | F11: =ABS(E11-E10) -> 0.23256169 | G11: =$J$3*E11 -> 147.23635 | H11: 44.472285 | AM11: =$AF$26*E11^2+$AG$26*E11+$AH$26 -> 26.432871 | BF11: =$BB$5*E11^2+$BC$5*E11+$BD$5 -> 0.83186802
A12: 3000 | B12: 131 | C12: -8.2310451 | D12: =$K$3*C12 -> -16.46209 | E12: 16.384606 | F12: =ABS(E12-E11) -> 0.025011916 | G12: =$J$3*E12 -> 147.46145 | H12: 45.109161 | AM12: =$AF$26*E12^2+$AG$26*E12+$AH$26 -> 26.473169 | BF12: =$BB$5*E12^2+$BC$5*E12+$BD$5 -> 0.83305734
A13: 3300 | B13: 130 | C13: -8.1980512 | D13: =$K$3*C13 -> -16.396102 | E13: 16.266164 | F13: =ABS(E13-E12) -> 0.11844143 | G13: =$J$3*E13 -> 146.39548 | H13: 45.748427 | AM13: =$AF$26*E13^2+$AG$26*E13+$AH$26 -> 26.282378 | BF13: =$BB$5*E13^2+$BC$5*E13+$BD$5 -> 0.82742651
A14: 3600 | B14: 136 | C14: -5.1257223 | D14: =$K$3*C14 -> -10.251445 | E14: 16.250088 | F14: =ABS(E14-E13) -> 0.016076397 | G14: =$J$3*E14 -> 146.25079 | H14: 46.254982 | AM14: =$AF$26*E14^2+$AG$26*E14+$AH$26 -> 26.256487 | BF14: =$BB$5*E14^2+$BC$5*E14+$BD$5 -> 0.82666243
A15: 3900 | B15: 270 | C15: 44.212666 | D15: =$K$3*C15 -> 88.425332 | E15: 20.174735 | F15: =ABS(E15-E14) -> 3.9246465 | G15: =$J$3*E15 -> 181.57261 | H15: 44.525466 | AM15: =$AF$26*E15^2+$AG$26*E15+$AH$26 -> 32.621807 | BF15: =$BB$5*E15^2+$BC$5*E15+$BD$5 -> 1.0146827
A16: 4200 | B16: 328 | C16: 40.727335 | D16: =$K$3*C16 -> 81.454669 | E16: 27.393632 | F16: =ABS(E16-E15) -> 7.2188972 | G16: =$J$3*E16 -> 246.54269 | H16: 41.196189 | AM16: =$AF$26*E16^2+$AG$26*E16+$AH$26 -> 44.565276 | BF16: =$BB$5*E16^2+$BC$5*E16+$BD$5 -> 1.3683354
A17: 4500 | B17: 236 | C17: -19.115149 | D17: =$K$3*C17 -> -38.230299 | E17: 30.469901 | F17: =ABS(E17-E16) -> 3.0762688 | G17: =$J$3*E17 -> 274.2291 | H17: 40.575919 | AM17: =$AF$26*E17^2+$AG$26*E17+$AH$26 -> 49.747499 | BF17: =$BB$5*E17^2+$BC$5*E17+$BD$5 -> 1.5221171
A18: 4800 | B18: 157 | C18: -46.464684 | D18: =$K$3*C18 -> -92.929367 | E18: 27.769787 | F18: =ABS(E18-E17) -> 2.7001137 | G18: =$J$3*E18 -> 249.92808 | H18: 43.221054 | AM18: =$AF$26*E18^2+$AG$26*E18+$AH$26 -> 45.195969 | BF18: =$BB$5*E18^2+$BC$5*E18+$BD$5 -> 1.3870406
... A20: 5400 | B20: 215 | C20: 5.0207884 | D20: =$K$3*C20 -> 10.041577 | E20: 22.772966 | F20: =ABS(E20-E19) -> 0.95621076 | G20: =$J$3*E20 -> 204.9567 | H20: 47.169037 | AM20: =$AF$26*E20^2+$AG$26*E20+$AH$26 -> 36.885401 | BF20: =$BB$5*E20^2+$BC$5*E20+$BD$5 -> 1.1408037
A21: 5700 | B21: 482 | C21: 69.929758 | D21: =$K$3*C21 -> 139.85952 | E21: 35.710483 | F21: =ABS(E21-E20) -> 12.937517 | G21: =$J$3*E21 -> 321.39435 | H21: 43.063962 | AF21: Fuel consumption (kW) in y axis | AM21: =$AF$26*E21^2+$AG$26*E21+$AH$26 -> 58.703147 | BF21: =$BB$5*E21^2+$BC$5*E21+$BD$5 -> 1.7883253
A22: 6000 | B22: 444 | C22: 20.809988 | D22: =$K$3*C22 -> 41.619976 | E22: 44.708406 | F22: =ABS(E22-E21) -> 8.9979228 | G22: =$J$3*E22 -> 402.37565 | H22: 39.525694 | AF22: Power output (kW) in x axis | AM22: =$AF$26*E22^2+$AG$26*E22+$AH$26 -> 74.454402 | BF22: =$BB$5*E22^2+$BC$5*E22+$BD$5 -> 2.2578395
A23: 6300 | B23: 437 | C23: 1.6856617 | D23: =$K$3*C23 -> 3.3713235 | E23: 48.180334 | F23: =ABS(E23-E22) -> 3.471928 | G23: =$J$3*E23 -> 433.623 | H23: 38.715211 | AM23: =$AF$26*E23^2+$AG$26*E23+$AH$26 -> 80.658776 | BF23: =$BB$5*E23^2+$BC$5*E23+$BD$5 -> 2.4432104
A24: 6600 | B24: 434 | C24: -7.7979511 | D24: =$K$3*C24 -> -15.595902 | E24: 49.954408 | F24: =ABS(E24-E23) -> 1.7740744 | G24: =$J$3*E24 -> 449.58967 | H24: 38.987698 | AM24: =$AF$26*E24^2+$AG$26*E24+$AH$26 -> 83.856285 | BF24: =$BB$5*E24^2+$BC$5*E24+$BD$5 -> 2.5388345
A25: 6900 | B25: 437 | C25: -10.567782 | D25: =$K$3*C25 -> -21.135564 | E25: 50.903215 | F25: =ABS(E25-E24) -> 0.94880681 | G25: =$J$3*E25 -> 458.12893 | H25: 39.713322 | AF25: k1 | AG25: k2 | AH25: k3 | AM25: =$AF$26*E25^2+$AG$26*E25+$AH$26 -> 85.573925 | BF25: =$BB$5*E25^2+$BC$5*E25+$BD$5 -> 2.5902269
A26: 7200 | B26: 727 | C26: 56.172082 | D26: =$K$3*C26 -> 112.34416 | E26: 64.156632 | F26: =ABS(E26-E25) -> 13.253417 | G26: =$J$3*E26 -> 577.40969 | H26: 36.57214 | AF26: 0.00292448 | AG26: 1.51536 | AH26: 0.8595 | AM26: =$AF$26*E26^2+$AG$26*E26+$AH$26 -> 110.11727 | BF26: =$BB$5*E26^2+$BC$5*E26+$BD$5 -> 3.3263828
A27: 7500 | B27: 897 | C27: 47.491465 | D27: =$K$3*C27 -> 94.98293 | E27: 85.998057 | F27: =ABS(E27-E26) -> 21.841424 | G27: =$J$3*E27 -> 773.98251 | H27: 32.494061 | AM27: =$AF$26*E27^2+$AG$26*E27+$AH$26 -> 152.80599 | BF27: =$BB$5*E27^2+$BC$5*E27+$BD$5 -> 4.6140008
A28: 7800 | B28: 875 | C28: 16.190101 | D28: =$K$3*C28 -> 32.380201 | E28: 93.621521 | F28: =ABS(E28-E27) -> 7.6234647 | G28: =$J$3*E28 -> 842.59369 | H28: 29.837918 | AM28: =$AF$26*E28^2+$AG$26*E28+$AH$26 -> 168.36284 | BF28: =$BB$5*E28^2+$BC$5*E28+$BD$5 -> 5.0852427
A29: 8100 | B29: 875 | C29: -0.62365579 | D29: =$K$3*C29 -> -1.2473116 | E29: 97.357506 | F29: =ABS(E29-E28) -> 3.7359842 | G29: =$J$3*E29 -> 876.21755 | H29: 29.275602 | AM29: =$AF$26*E29^2+$AG$26*E29+$AH$26 -> 176.11081 | BF29: =$BB$5*E29^2+$BC$5*E29+$BD$5 -> 5.3203029
A30: 8400 | B30: 854 | C30: -20.076014 | D30: =$K$3*C30 -> -40.152028 | E30: 99.346847 | F30: =ABS(E30-E29) -> 1.9893416 | G30: =$J$3*E30 -> 894.12162 | H30: 30.136892 | AM30: =$AF$26*E30^2+$AG$26*E30+$AH$26 -> 180.26976 | BF30: =$BB$5*E30^2+$BC$5*E30+$BD$5 -> 5.4465742
A31: 8700 | B31: 878 | C31: -13.742013 | D31: =$K$3*C31 -> -27.484026 | E31: 100.60562 | F31: =ABS(E31-E30) -> 1.2587723 | G31: =$J$3*E31 -> 905.45057 | H31: 31.441021 | AM31: =$AF$26*E31^2+$AG$26*E31+$AH$26 -> 182.91333 | BF31: =$BB$5*E31^2+$BC$5*E31+$BD$5 -> 5.5268705
A32: 9000 | B32: 881 | C32: -17.491883 | D32: =$K$3*C32 -> -34.983765 | E32: 101.77225 | F32: =ABS(E32-E31) -> 1.1666303 | G32: =$J$3*E32 -> 915.95025 | H32: 32.66956 | AM32: =$AF$26*E32^2+$AG$26*E32+$AH$26 -> 185.37166 | BF32: =$BB$5*E32^2+$BC$5*E32+$BD$5 -> 5.6015639
A33: 9300 | B33: 880 | C33: -20.917502 | D33: =$K$3*C33 -> -41.835003 | E33: 102.42234 | F33: =ABS(E33-E32) -> 0.6500936 | G33: =$J$3*E33 -> 921.80109 | H33: 34.17472 | AM33: =$AF$26*E33^2+$AG$26*E33+$AH$26 -> 186.745 | BF33: =$BB$5*E33^2+$BC$5*E33+$BD$5 -> 5.6433008
A34: 9600 | B34: 873 | C34: -24.843188 | D34: =$K$3*C34 -> -49.686377 | E34: 102.51696 | F34: =ABS(E34-E33) -> 0.094616181 | G34: =$J$3*E34 -> 922.65263 | H34: 35.964557 | AF34: BATTERY DEGRADATION | AM34: =$AF$26*E34^2+$AG$26*E34+$AH$26 -> 186.94509 | BF34: =$BB$5*E34^2+$BC$5*E34+$BD$5 -> 5.6493822
A35: 9900 | B35: 397 | C35: -87.281584 | D35: =$K$3*C35 -> -174.56317 | E35: 69.207593 | F35: =ABS(E35-E34) -> 33.309366 | G35: =$J$3*E35 -> 622.86834 | H35: 41.997089 | AM35: =$AF$26*E35^2+$AG$26*E35+$AH$26 -> 119.74127 | BF35: =$BB$5*E35^2+$BC$5*E35+$BD$5 -> 3.6159157
A36: 10200 | B36: 958 | C36: 64.49821 | D36: =$K$3*C36 -> 128.99642 | E36: 80.953554 | F36: =ABS(E36-E35) -> 11.745961 | G36: =$J$3*E36 -> 728.58199 | H36: 40.464648 | AM36: =$AF$26*E36^2+$AG$26*E36+$AH$26 -> 142.69879 | BF36: =$BB$5*E36^2+$BC$5*E36+$BD$5 -> 4.308383
A37: 10500 | B37: 995 | C37: 54.410572 | D37: =$K$3*C37 -> 108.82114 | E37: 98.460688 | F37: =ABS(E37-E36) -> 17.507134 | G37: =$J$3*E37 -> 886.14619 | H37: 35.79411 | AM37: =$AF$26*E37^2+$AG$26*E37+$AH$26 -> 178.41428 | BF37: =$BB$5*E37^2+$BC$5*E37+$BD$5 -> 5.3902313
A38: 10800 | B38: 986 | C38: 24.105607 | D38: =$K$3*C38 -> 48.211215 | E38: 104.19482 | F38: =ABS(E38-E37) -> 5.7341348 | G38: =$J$3*E38 -> 937.75341 | H38: 32.784003 | AM38: =$AF$26*E38^2+$AG$26*E38+$AH$26 -> 190.50196 | BF38: =$BB$5*E38^2+$BC$5*E38+$BD$5 -> 5.7575135
A39: 11100 | B39: 989 | C39: 8.4589477 | D39: =$K$3*C39 -> 16.917895 | E39: 108.00474 | F39: =ABS(E39-E38) -> 3.8099185 | G39: =$J$3*E39 -> 972.04267 | H39: 31.547922 | AM39: =$AF$26*E39^2+$AG$26*E39+$AH$26 -> 198.6397 | BF39: =$BB$5*E39^2+$BC$5*E39+$BD$5 -> 6.0050775
A40: 11400 | B40: 730 | C40: -87.140163 | D40: =$K$3*C40 -> -174.28033 | E40: 103.78405 | F40: =ABS(E40-E39) -> 4.2206929 | G40: =$J$3*E40 -> 934.05644 | H40: 35.576132 | AM40: =$AF$26*E40^2+$AG$26*E40+$AH$26 -> 189.62965 | BF40: =$BB$5*E40^2+$BC$5*E40+$BD$5 -> 5.7309903
A41: 11700 | B41: 533 | C41: -87.317112 | D41: =$K$3*C41 -> -174.63422 | E41: 80.813117 | F41: =ABS(E41-E40) -> 22.970931 | G41: =$J$3*E41 -> 727.31805 | H41: 42.242482 | AM41: =$AF$26*E41^2+$AG$26*E41+$AH$26 -> 142.41954 | BF41: =$BB$5*E41^2+$BC$5*E41+$BD$5 -> 4.2999454
A42: 12000 | B42: 1164 | C42: 63.756054 | D42: =$K$3*C42 -> 127.51211 | E42: 98.771659 | F42: =ABS(E42-E41) -> 17.958542 | G42: =$J$3*E42 -> 888.94493 | H42: 40.11268 | AM42: =$AF$26*E42^2+$AG$26*E42+$AH$26 -> 179.06488 | BF42: =$BB$5*E42^2+$BC$5*E42+$BD$5 -> 5.4099857
A43: 12300 | B43: 1133 | C43: 44.25732 | D43: =$K$3*C43 -> 88.51464 | E43: 116.0487 | F43: =ABS(E43-E42) -> 17.277042 | G43: =$J$3*E43 -> 1044.4383 | H43: 35.614079 | AM43: =$AF$26*E43^2+$AG$26*E43+$AH$26 -> 216.09991 | BF43: =$BB$5*E43^2+$BC$5*E43+$BD$5 -> 6.5370251
A44: 12600 | B44: 1122 | C44: 19.619487 | D44: =$K$3*C44 -> 39.238975 | E44: 120.30088 | F44: =ABS(E44-E43) -> 4.2521821 | G44: =$J$3*E44 -> 1082.7079 | H44: 33.159632 | AM44: =$AF$26*E44^2+$AG$26*E44+$AH$26 -> 225.4826 | BF44: =$BB$5*E44^2+$BC$5*E44+$BD$5 -> 6.8233002
A45: 12900 | B45: 1138 | C45: 13.370838 | D45: =$K$3*C45 -> 26.741675 | E45: 123.4666 | F45: =ABS(E45-E44) -> 3.1657187 | G45: =$J$3*E45 -> 1111.1994 | H45: 31.881827 | AM45: =$AF$26*E45^2+$AG$26*E45+$AH$26 -> 232.53663 | BF45: =$BB$5*E45^2+$BC$5*E45+$BD$5 -> 7.0387105
A46: 13200 | B46: 1178 | C46: 19.172303 | D46: =$K$3*C46 -> 38.344605 | E46: 126.62113 | F46: =ABS(E46-E45) -> 3.1545279 | G46: =$J$3*E46 -> 1139.5902 | H46: 30.596028 | AM46: =$AF$26*E46^2+$AG$26*E46+$AH$26 -> 239.62402 | BF46: =$BB$5*E46^2+$BC$5*E46+$BD$5 -> 7.2552957
... A85: 24900 | B85: 981 | C85: 7.6593423 | D85: =$K$3*C85 -> 15.318685 | E85: 107.29367 | F85: =ABS(E85-E84) -> 0.75721151 | G85: =$J$3*E85 -> 965.64301 | H85: 50.417515 | AM85: =$AF$26*E85^2+$AG$26*E85+$AH$26 -> 197.11445 | BF85: =$BB$5*E85^2+$BC$5*E85+$BD$5 -> 5.9586588
A86: 25200 | B86: 980 | C86: 4.9112877 | D86: =$K$3*C86 -> 9.8225755 | E86: 107.79317 | F86: =ABS(E86-E85) -> 0.49949871 | G86: =$J$3*E86 -> 970.1385 | H86: 49.935477 | AB86: EC at 40.4% DoD | AD86: MAX CYCLES AT 40.4% DoD | AM86: =$AF$26*E86^2+$AG$26*E86+$AH$26 -> 198.18556 | BF86: =$BB$5*E86^2+$BC$5*E86+$BD$5 -> 5.9912557
A87: 25500 | B87: 974 | C87: 0.76417921 | D87: =$K$3*C87 -> 1.5283584 | E87: 108.04808 | F87: =ABS(E87-E86) -> 0.25491274 | G87: =$J$3*E87 -> 972.43272 | H87: 49.724974 | AB87: 3.5 | AD87: 70500 | AM87: =$AF$26*E87^2+$AG$26*E87+$AH$26 -> 198.73275 | BF87: =$BB$5*E87^2+$BC$5*E87+$BD$5 -> 6.0079098
A88: 25800 | B88: 976 | C88: 1.2039737 | D88: =$K$3*C88 -> 2.4079473 | E88: 108.17251 | F88: =ABS(E88-E87) -> 0.12443399 | G88: =$J$3*E88 -> 973.55262 | H88: 49.647483 | AM88: =$AF$26*E88^2+$AG$26*E88+$AH$26 -> 199 | BF88: =$BB$5*E88^2+$BC$5*E88+$BD$5 -> 6.016044
A89: 26100 | B89: 973 | C89: -0.61511578 | D89: =$K$3*C89 -> -1.2302316 | E89: 108.24344 | F89: =ABS(E89-E88) -> 0.070927863 | G89: =$J$3*E89 -> 974.19097 | H89: 49.628988 | AM89: =$AF$26*E89^2+$AG$26*E89+$AH$26 -> 199.15237 | BF89: =$BB$5*E89^2+$BC$5*E89+$BD$5 -> 6.0206818
A90: 26400 | B90: 968 | C90: -2.6740801 | D90: =$K$3*C90 -> -5.3481603 | E90: 108.14546 | F90: =ABS(E90-E89) -> 0.097986059 | G90: =$J$3*E90 -> 973.3091 | H90: 49.761653 | AM90: =$AF$26*E90^2+$AG$26*E90+$AH$26 -> 198.94188 | BF90: =$BB$5*E90^2+$BC$5*E90+$BD$5 -> 6.0142749
A91: 26700 | B91: 969 | C91: -1.4955946 | D91: =$K$3*C91 -> -2.9911892 | E91: 107.99467 | F91: =ABS(E91-E90) -> 0.15078978 | G91: =$J$3*E91 -> 971.95199 | H91: 49.920699 | AM91: =$AF$26*E91^2+$AG$26*E91+$AH$26 -> 198.61806 | BF91: =$BB$5*E91^2+$BC$5*E91+$BD$5 -> 6.0044191
A92: 27000 | B92: 980 | C92: 3.524493 | D92: =$K$3*C92 -> 7.048986 | E92: 108.10125 | F92: =ABS(E92-E91) -> 0.1065812 | G92: =$J$3*E92 -> 972.91122 | H92: 49.829725 | AM92: =$AF$26*E92^2+$AG$26*E92+$AH$26 -> 198.84693 | BF92: =$BB$5*E92^2+$BC$5*E92+$BD$5 -> 6.0113849
A93: 27300 | B93: 974 | C93: -0.21446302 | D93: =$K$3*C93 -> -0.42892604 | E93: 108.26553 | F93: =ABS(E93-E92) -> 0.16428522 | G93: =$J$3*E93 -> 974.38979 | H93: 49.710109 | W93: PRAXIS BATTERIES | AM93: =$AF$26*E93^2+$AG$26*E93+$AH$26 -> 199.19983 | BF93: =$BB$5*E93^2+$BC$5*E93+$BD$5 -> 6.0221265
A94: 27600 | B94: 975 | C94: 0.12622193 | D94: =$K$3*C94 -> 0.25244387 | E94: 108.30089 | F94: =ABS(E94-E93) -> 0.035362237 | G94: =$J$3*E94 -> 974.70805 | H94: 49.712735 | V94: 513.01 GreenBattery Rev1.12 A4.cdr (praxis-automation.eu) | AM94: =$AF$26*E94^2+$AG$26*E94+$AH$26 -> 199.27581 | BF94: =$BB$5*E94^2+$BC$5*E94+$BD$5 -> 6.0244393
A95: 27900 | B95: 971 | C95: -1.7200456 | D95: =$K$3*C95 -> -3.4400912 | E95: 108.26676 | F95: =ABS(E95-E94) -> 0.034132076 | G95: =$J$3*E95 -> 974.40086 | H95: 49.779061 | AM95: =$AF$26*E95^2+$AG$26*E95+$AH$26 -> 199.20247 | BF95: =$BB$5*E95^2+$BC$5*E95+$BD$5 -> 6.0222069
A96: 28200 | B96: 964 | C96: -4.1697664 | D96: =$K$3*C96 -> -8.3395328 | E96: 108.03341 | F96: =ABS(E96-E95) -> 0.23335337 | G96: =$J$3*E96 -> 972.30068 | H96: 50.013571 | AM96: =$AF$26*E96^2+$AG$26*E96+$AH$26 -> 198.70125 | BF96: =$BB$5*E96^2+$BC$5*E96+$BD$5 -> 6.006951
A97: 28500 | B97: 976 | C97: 2.1950385 | D97: =$K$3*C97 -> 4.390077 | E97: 107.95225 | F97: =ABS(E97-E96) -> 0.081160407 | G97: =$J$3*E97 -> 971.57024 | H97: 50.074849 | AM97: =$AF$26*E97^2+$AG$26*E97+$AH$26 -> 198.527 | BF97: =$BB$5*E97^2+$BC$5*E97+$BD$5 -> 6.0016474
A98: 28800 | B98: 972 | C98: -0.15247314 | D98: =$K$3*C98 -> -0.30494628 | E98: 108.02955 | F98: =ABS(E98-E97) -> 0.077301289 | G98: =$J$3*E98 -> 972.26595 | H98: 50.001141 | AM98: =$AF$26*E98^2+$AG$26*E98+$AH$26 -> 198.69296 | BF98: =$BB$5*E98^2+$BC$5*E98+$BD$5 -> 6.0066988
A99: 29100 | B99: 962 | C99: -4.2521271 | D99: =$K$3*C99 -> -8.5042542 | E99: 107.82953 | F99: =ABS(E99-E98) -> 0.20002257 | G99: =$J$3*E99 -> 970.46574 | H99: 50.182 | AM99: =$AF$26*E99^2+$AG$26*E99+$AH$26 -> 198.26359 | BF99: =$BB$5*E99^2+$BC$5*E99+$BD$5 -> 5.9936305
A100: 29400 | B100: 973 | C100: 1.8099692 | D100: =$K$3*C100 -> 3.6199384 | E100: 107.70452 | F100: =ABS(E100-E99) -> 0.12500833 | G100: =$J$3*E100 -> 969.34067 | H100: 50.262138 | AM100: =$AF$26*E100^2+$AG$26*E100+$AH$26 -> 197.99536 | BF100: =$BB$5*E100^2+$BC$5*E100+$BD$5 -> 5.9854671
A101: 29700 | B101: 972 | C101: 0.92788568 | D101: =$K$3*C101 -> 1.8557714 | E101: 107.78948 | F101: =ABS(E101-E100) -> 0.084961489 | G101: =$J$3*E101 -> 970.10532 | H101: 50.157893 | AM101: =$AF$26*E101^2+$AG$26*E101+$AH$26 -> 198.17765 | BF101: =$BB$5*E101^2+$BC$5*E101+$BD$5 -> 5.991015
A102: 30000 | B102: 969 | C102: -0.54479443 | D102: =$K$3*C102 -> -1.0895889 | E102: 107.78342 | F102: =ABS(E102-E101) -> 0.0060595374 | G102: =$J$3*E102 -> 970.05079 | H102: 50.146579 | AM102: =$AF$26*E102^2+$AG$26*E102+$AH$26 -> 198.16465 | BF102: =$BB$5*E102^2+$BC$5*E102+$BD$5 -> 5.9906192
A103: 30300 | B103: 975 | C103: 2.1982569 | D103: =$K$3*C103 -> 4.3965139 | E103: 107.84047 | F103: =ABS(E103-E102) -> 0.057045297 | G103: =$J$3*E103 -> 970.56419 | H103: 50.075717 | AM103: =$AF$26*E103^2+$AG$26*E103+$AH$26 -> 198.28706 | BF103: =$BB$5*E103^2+$BC$5*E103+$BD$5 -> 5.9943449
A104: 30600 | B104: 967 | C104: -1.8103791 | D104: =$K$3*C104 -> -3.6207582 | E104: 107.84246 | F104: =ABS(E104-E103) -> 0.0019936515 | G104: =$J$3*E104 -> 970.58214 | H104: 50.070307 | AM104: =$AF$26*E104^2+$AG$26*E104+$AH$26 -> 198.29134 | BF104: =$BB$5*E104^2+$BC$5*E104+$BD$5 -> 5.9944752
A105: 30900 | B105: 968 | C105: -0.76139541 | D105: =$K$3*C105 -> -1.5227908 | E105: 107.72043 | F105: =ABS(E105-E104) -> 0.12203072 | G105: =$J$3*E105 -> 969.48386 | H105: 50.167643 | V105: DoD(%) | W105: Cycles (1C) | AM105: =$AF$26*E105^2+$AG$26*E105+$AH$26 -> 198.02949 | BF105: =$BB$5*E105^2+$BC$5*E105+$BD$5 -> 5.9865059
A106: 31200 | B106: 959 | C106: -4.157838 | D106: =$K$3*C106 -> -8.315676 | E106: 107.47527 | F106: =ABS(E106-E105) -> 0.24515517 | G106: =$J$3*E106 -> 967.27746 | H106: 50.366787 | V106: 5 | W106: 180000 | AM106: =$AF$26*E106^2+$AG$26*E106+$AH$26 -> 197.50371 | BF106: =$BB$5*E106^2+$BC$5*E106+$BD$5 -> 5.9705047
A107: 31500 | B107: 956 | C107: -3.8357878 | D107: =$K$3*C107 -> -7.6715756 | E107: 107.07039 | F107: =ABS(E107-E106) -> 0.40488781 | G107: =$J$3*E107 -> 963.63347 | H107: 50.676223 | V107: 10 | W107: 130000 | AM107: =$AF$26*E107^2+$AG$26*E107+$AH$26 -> 196.63612 | BF107: =$BB$5*E107^2+$BC$5*E107+$BD$5 -> 5.9441033
A108: 31800 | B108: 968 | C108: 2.754988 | D108: =$K$3*C108 -> 5.509976 | E108: 106.93904 | F108: =ABS(E108-E107) -> 0.1313489 | G108: =$J$3*E108 -> 962.45133 | H108: 50.702074 | V108: 20 | W108: 80000 | AM108: =$AF$26*E108^2+$AG$26*E108+$AH$26 -> 196.35487 | BF108: =$BB$5*E108^2+$BC$5*E108+$BD$5 -> 5.9355453
A109: 32100 | B109: 964 | C109: 0.53507813 | D109: =$K$3*C109 -> 1.0701563 | E109: 106.98798 | F109: =ABS(E109-E108) -> 0.048947609 | G109: =$J$3*E109 -> 962.89186 | H109: 50.579654 | V109: 50 | W109: 24000 | AC109: at the REQUIRED DoD (%) | AM109: =$AF$26*E109^2+$AG$26*E109+$AH$26 -> 196.45966 | BF109: =$BB$5*E109^2+$BC$5*E109+$BD$5 -> 5.9387341
A110: 32400 | B110: 973 | C110: 4.3780044 | D110: =$K$3*C110 -> 8.7560087 | E110: 107.13392 | F110: =ABS(E110-E109) -> 0.14593155 | G110: =$J$3*E110 -> 964.20525 | H110: 50.379388 | V110: 80 | W110: 6200 | AC110: EC | AD110: MAX CYCLES | AM110: =$AF$26*E110^2+$AG$26*E110+$AH$26 -> 196.77219 | BF110: =$BB$5*E110^2+$BC$5*E110+$BD$5 -> 5.9482438
A111: 32700 | B111: 984 | C111: 7.6734437 | D111: =$K$3*C111 -> 15.346887 | E111: 107.62375 | F111: =ABS(E111-E110) -> 0.48983681 | G111: =$J$3*E111 -> 968.61378 | H111: 49.902761 | V111: 90 | W111: 5000 | AC111: 3.5 | AD111: =W117 -> 41920 | AM111: =$AF$26*E111^2+$AG$26*E111+$AH$26 -> 197.82211 | BF111: =$BB$5*E111^2+$BC$5*E111+$BD$5 -> 5.9801945
A112: 33000 | B112: 975 | C112: 1.3500365 | D112: =$K$3*C112 -> 2.700073 | E112: 108.02902 | F112: =ABS(E112-E111) -> 0.40526472 | G112: =$J$3*E112 -> 972.26116 | H112: 49.567286 | AM112: =$AF$26*E112^2+$AG$26*E112+$AH$26 -> 198.69182 | BF112: =$BB$5*E112^2+$BC$5*E112+$BD$5 -> 6.006664
A113: 33300 | B113: 972 | C113: -0.5584595 | D113: =$K$3*C113 -> -1.116919 | E113: 108.11975 | F113: =ABS(E113-E112) -> 0.09073575 | G113: =$J$3*E113 -> 973.07778 | H113: 49.541173 | AM113: =$AF$26*E113^2+$AG$26*E113+$AH$26 -> 198.88667 | BF113: =$BB$5*E113^2+$BC$5*E113+$BD$5 -> 6.0125947
A114: 33600 | B114: 973 | C114: -0.18878254 | D114: =$K$3*C114 -> -0.37756508 | E114: 108.14869 | F114: =ABS(E114-E113) -> 0.028936236 | G114: =$J$3*E114 -> 973.33821 | H114: 49.569313 | AM114: =$AF$26*E114^2+$AG$26*E114+$AH$26 -> 198.94882 | BF114: =$BB$5*E114^2+$BC$5*E114+$BD$5 -> 6.0144864
A115: 33900 | B115: 968 | C115: -2.4177918 | D115: =$K$3*C115 -> -4.8355837 | E115: 108.08851 | F115: =ABS(E115-E114) -> 0.060181287 | G115: =$J$3*E115 -> 972.79658 | H115: 49.675884 | V115: x | W115: y | AM115: =$AF$26*E115^2+$AG$26*E115+$AH$26 -> 198.81957 | BF115: =$BB$5*E115^2+$BC$5*E115+$BD$5 -> 6.0105523
A116: 34200 | B116: 969 | C116: -1.3666721 | D116: =$K$3*C116 -> -2.7333442 | E116: 107.96602 | F116: =ABS(E116-E115) -> 0.12248937 | G116: =$J$3*E116 -> 971.69417 | H116: 49.82029 | V116: 20 | W116: 80000 | AM116: =$AF$26*E116^2+$AG$26*E116+$AH$26 -> 198.55656 | BF116: =$BB$5*E116^2+$BC$5*E116+$BD$5 -> 6.0025472
A117: 34500 | B117: 973 | C117: 0.65518733 | D117: =$K$3*C117 -> 1.3103747 | E117: 107.96115 | F117: =ABS(E117-E116) -> 0.00487341 | G117: =$J$3*E117 -> 971.65031 | H117: 49.843028 | V117: 40.4 | W117: =W116+((V117-V116)*(W118-W116))/(V118-V116) -> 41920 | AM117: =$AF$26*E117^2+$AG$26*E117+$AH$26 -> 198.5461 | BF117: =$BB$5*E117^2+$BC$5*E117+$BD$5 -> 6.0022288
A118: 34800 | B118: 977 | C118: 2.0204442 | D118: =$K$3*C118 -> 4.0408883 | E118: 108.10218 | F118: =ABS(E118-E117) -> 0.14103804 | G118: =$J$3*E118 -> 972.91965 | H118: 49.735778 | V118: 50 | W118: 24000 | AM118: =$AF$26*E118^2+$AG$26*E118+$AH$26 -> 198.84894 | BF118: =$BB$5*E118^2+$BC$5*E118+$BD$5 -> 6.0114462
A119: 35100 | B119: 972 | C119: -0.854366 | D119: =$K$3*C119 -> -1.708732 | E119: 108.18551 | F119: =ABS(E119-E118) -> 0.083330287 | G119: =$J$3*E119 -> 973.66963 | H119: 49.6974 | AM119: =$AF$26*E119^2+$AG$26*E119+$AH$26 -> 199.02792 | BF119: =$BB$5*E119^2+$BC$5*E119+$BD$5 -> 6.016894
A120: 35400 | B120: 970 | C120: -1.5544928 | D120: =$K$3*C120 -> -3.1089857 | E120: 108.11887 | F120: =ABS(E120-E119) -> 0.066646811 | G120: =$J$3*E120 -> 973.0698 | H120: 49.792633 | AM120: =$AF$26*E120^2+$AG$26*E120+$AH$26 -> 198.88477 | BF120: =$BB$5*E120^2+$BC$5*E120+$BD$5 -> 6.0125368
A121: 35700 | B121: 970 | C121: -1.1451006 | D121: =$K$3*C121 -> -2.2902012 | E121: 108.02789 | F121: =ABS(E121-E120) -> 0.090976649 | G121: =$J$3*E121 -> 972.25101 | H121: 49.896467 | AM121: =$AF$26*E121^2+$AG$26*E121+$AH$26 -> 198.6894 | BF121: =$BB$5*E121^2+$BC$5*E121+$BD$5 -> 6.0065903
A122: 36000 | B122: 980 | C122: 3.3321164 | D122: =$K$3*C122 -> 6.6642328 | E122: 108.144 | F122: =ABS(E122-E121) -> 0.11610706 | G122: =$J$3*E122 -> 973.29598 | H122: 49.800675 | AM122: =$AF$26*E122^2+$AG$26*E122+$AH$26 -> 198.93875 | BF122: =$BB$5*E122^2+$BC$5*E122+$BD$5 -> 6.0141796
A123: 36300 | B123: 976 | C123: 0.47277218 | D123: =$K$3*C123 -> 0.94554436 | E123: 108.33502 | F123: =ABS(E123-E122) -> 0.1910191 | G123: =$J$3*E123 -> 975.01515 | H123: 49.659715 | AM123: =$AF$26*E123^2+$AG$26*E123+$AH$26 -> 199.34914 | BF123: =$BB$5*E123^2+$BC$5*E123+$BD$5 -> 6.0266712
A124: 36600 | B124: 964 | C124: -4.8369188 | D124: =$K$3*C124 -> -9.6738376 | E124: 108.18168 | F124: =ABS(E124-E123) -> 0.15334165 | G124: =$J$3*E124 -> 973.63508 | H124: 49.841877 | AM124: =$AF$26*E124^2+$AG$26*E124+$AH$26 -> 199.01968 | BF124: =$BB$5*E124^2+$BC$5*E124+$BD$5 -> 6.016643
A125: 36900 | B125: 959 | C125: -5.3944949 | D125: =$K$3*C125 -> -10.78899 | E125: 107.75004 | F125: =ABS(E125-E124) -> 0.43163939 | G125: =$J$3*E125 -> 969.75032 | H125: 50.240229 | AM125: =$AF$26*E125^2+$AG$26*E125+$AH$26 -> 198.09301 | BF125: =$BB$5*E125^2+$BC$5*E125+$BD$5 -> 5.9884391
A126: 37200 | B126: 961 | C126: -2.6562436 | D126: =$K$3*C126 -> -5.3124872 | E126: 107.36376 | F126: =ABS(E126-E125) -> 0.38627307 | G126: =$J$3*E126 -> 966.27386 | H126: 50.546022 | AM126: =$AF$26*E126^2+$AG$26*E126+$AH$26 -> 197.26467 | BF126: =$BB$5*E126^2+$BC$5*E126+$BD$5 -> 5.9632302
A127: 37500 | B127: 963 | C127: -0.66888849 | D127: =$K$3*C127 -> -1.337777 | E127: 107.14437 | F127: =ABS(E127-E126) -> 0.21938878 | G127: =$J$3*E127 -> 964.29936 | H127: 50.670264 | AM127: =$AF$26*E127^2+$AG$26*E127+$AH$26 -> 196.79459 | BF127: =$BB$5*E127^2+$BC$5*E127+$BD$5 -> 5.9489254
A128: 37800 | B128: 965 | C128: 0.72096969 | D128: =$K$3*C128 -> 1.4419394 | E128: 107.05775 | F128: =ABS(E128-E127) -> 0.086626086 | G128: =$J$3*E128 -> 963.51973 | H128: 50.664848 | AM128: =$AF$26*E128^2+$AG$26*E128+$AH$26 -> 196.60905 | BF128: =$BB$5*E128^2+$BC$5*E128+$BD$5 -> 5.9432797
A129: 38100 | B129: 967 | C129: 1.6453267 | D129: =$K$3*C129 -> 3.2906534 | E129: 107.07456 | F129: =ABS(E129-E128) -> 0.01680749 | G129: =$J$3*E129 -> 963.671 | H129: 50.570679 | AM129: =$AF$26*E129^2+$AG$26*E129+$AH$26 -> 196.64505 | BF129: =$BB$5*E129^2+$BC$5*E129+$BD$5 -> 5.944375
A130: 38400 | B130: 965 | C130: 0.55693952 | D130: =$K$3*C130 -> 1.113879 | E130: 107.09422 | F130: =ABS(E130-E129) -> 0.019660608 | G130: =$J$3*E130 -> 963.84794 | H130: 50.487789 | AM130: =$AF$26*E130^2+$AG$26*E130+$AH$26 -> 196.68715 | BF130: =$BB$5*E130^2+$BC$5*E130+$BD$5 -> 5.9456562
... A321: 95700 | B321: 1256 | C321: 0.79475671 | D321: =$K$3*C321 -> 1.5895134 | E321: 139.36922 | F321: =ABS(E321-E320) -> 0.10674755 | G321: =$J$3*E321 -> 1254.323 | H321: 50.902105 | AM321: =$AF$26*E321^2+$AG$26*E321+$AH$26 -> 268.85849 | BF321: =$BB$5*E321^2+$BC$5*E321+$BD$5 -> 8.1502496
A322: 96000 | B322: 1253 | C322: -0.41816989 | D322: =$K$3*C322 -> -0.83633978 | E322: 139.3055 | F322: =ABS(E322-E321) -> 0.063719771 | G322: =$J$3*E322 -> 1253.7495 | H322: 50.889271 | K322: =52*5 -> 260 | AM322: =$AF$26*E322^2+$AG$26*E322+$AH$26 -> 268.71 | BF322: =$BB$5*E322^2+$BC$5*E322+$BD$5 -> 8.1456978
A323: 96300 | B323: 1246 | C323: -3.1550876 | D323: =$K$3*C323 -> -6.3101753 | E323: 139.136 | F323: =ABS(E323-E322) -> 0.1694964 | G323: =$J$3*E323 -> 1252.224 | H323: 51.031785 | AM323: =$AF$26*E323^2+$AG$26*E323+$AH$26 -> 268.31513 | BF323: =$BB$5*E323^2+$BC$5*E323+$BD$5 -> 8.1335937
A324: 96600 | B324: 1249 | C324: -0.79161562 | D324: =$K$3*C324 -> -1.5832312 | E324: 138.9441 | F324: =ABS(E324-E323) -> 0.19190382 | G324: =$J$3*E324 -> 1250.4969 | H324: 51.181267 | AM324: =$AF$26*E324^2+$AG$26*E324+$AH$26 -> 267.86827 | BF324: =$BB$5*E324^2+$BC$5*E324+$BD$5 -> 8.1198962
A325: 96900 | B325: 1243 | C325: -2.8973748 | D325: =$K$3*C325 -> -5.7947496 | E325: 138.7455 | F325: =ABS(E325-E324) -> 0.19860242 | G325: =$J$3*E325 -> 1248.7095 | H325: 51.327355 | AM325: =$AF$26*E325^2+$AG$26*E325+$AH$26 -> 267.40603 | BF325: =$BB$5*E325^2+$BC$5*E325+$BD$5 -> 8.105728
A326: 97200 | B326: 1252 | C326: 2.1852589 | D326: =$K$3*C326 -> 4.3705178 | E326: 138.61594 | F326: =ABS(E326-E325) -> 0.12955098 | G326: =$J$3*E326 -> 1247.5435 | H326: 51.347359 | AM326: =$AF$26*E326^2+$AG$26*E326+$AH$26 -> 267.10463 | BF326: =$BB$5*E326^2+$BC$5*E326+$BD$5 -> 8.0964901
A327: 97500 | B327: 1254 | C327: 3.0448569 | D327: =$K$3*C327 -> 6.0897137 | E327: 138.64718 | F327: =ABS(E327-E326) -> 0.031238476 | G327: =$J$3*E327 -> 1247.8247 | H327: 51.143188 | AM327: =$AF$26*E327^2+$AG$26*E327+$AH$26 -> 267.1773 | BF327: =$BB$5*E327^2+$BC$5*E327+$BD$5 -> 8.0987173
A328: 97800 | B328: 1250 | C328: 0.97773929 | D328: =$K$3*C328 -> 1.9554786 | E328: 138.66214 | F328: =ABS(E328-E327) -> 0.014955263 | G328: =$J$3*E328 -> 1247.9592 | H328: 50.990261 | AM328: =$AF$26*E328^2+$AG$26*E328+$AH$26 -> 267.21209 | BF328: =$BB$5*E328^2+$BC$5*E328+$BD$5 -> 8.0997837
A329: 98100 | B329: 1250 | C329: 1.0930659 | D329: =$K$3*C329 -> 2.1861318 | E329: 138.63649 | F329: =ABS(E329-E328) -> 0.025649306 | G329: =$J$3*E329 -> 1247.7284 | H329: 50.9098 | AM329: =$AF$26*E329^2+$AG$26*E329+$AH$26 -> 267.15242 | BF329: =$BB$5*E329^2+$BC$5*E329+$BD$5 -> 8.0979548
...

Sheet Sweden_ports_600LPF_125Ah
A1: Time (sec) | B1: Load Profile (kW) | C1: Battery power (kW) | D1: Total Batt Power (kW) | E1: FC power (kW) | F1: Abs(Pfc(t)-Pfc(t-1) | G1: TotalFC power(kw) | H1: Battery SoC (%) | AK1: Sampling_dt(sec) | AL1: Sampling_dt(hrs) | AM1: Fuel consumption (f(pfc)) for 1 FC (kW) | AN1: Addit_Ploss(kW) | AO1: Fctotal(kw) | AQ1: FC_total*hrs(kwh) | AR1: Ke-m ( kg/kwh) | AS1: Fuel consumption (kg) | AU1: H2 in $/kg | AV1: Fuel cost | AW1: H2 price in $/kwh | AY1: Fuel cost ($)
A2: 0 | B2: 0 | C2: 12.350136 | D2: =$K$3*C2 -> 24.700273 | E2: 0 | F2: 0 | G2: =$J$3*E2 -> 0 | H2: 50 | J2: Nfc | K2: Nbat | AK2: 300 | AL2: =AK2/3600 -> 0.083333333 | AM2: =$AF$26*E2^2+$AG$26*E2+$AH$26 -> 0.8595 | AO2: =J3*AM266+AN2 -> 518756.49 | AQ2: =AO2*AL2 -> 43229.708 | AR2: 0.03 | AS2: =AQ2*AR2 -> 1296.8912 | AU2: 4 | AV2: =AU2*AS2 -> 5187.5649 | AW2: =AU2/33.35 -> 0.11994003 | AY2: =AQ2*AW2 -> 5184.9724
A3: 300 | B3: 0 | C3: -0.075000176 | D3: =$K$3*C3 -> -0.15000035 | E3: 0.016667063 | F3: =ABS(E3-E2) -> 0.016667063 | G3: =$J$3*E3 -> 0.15000356 | H3: 50.542869 | J3: 9 | K3: 2 | AM3: =$AF$26*E3^2+$AG$26*E3+$AH$26 -> 0.88475741
A4: 600 | B4: 52 | C4: 25.452054 | D4: =$K$3*C4 -> 50.904107 | E4: 0.12177412 | F4: =ABS(E4-E3) -> 0.10510706 | G4: =$J$3*E4 -> 1.0959671 | H4: 49.538949 | AG4: Fuel consumption | AM4: =$AF$26*E4^2+$AG$26*E4+$AH$26 -> 1.044075 | AR4: *Source: Cost-effective control of Roll-on/Roll-off Emission-Free Ships
A5: 900 | B5: 123 | C5: 38.399302 | D5: =$K$3*C5 -> 76.798603 | E5: 5.1334502 | F5: =ABS(E5-E4) -> 5.0116761 | G5: =$J$3*E5 -> 46.201052 | H5: 46.94471 | AM5: =$AF$26*E5^2+$AG$26*E5+$AH$26 -> 8.7155919 | AR5: CHECK END OF LIFE INCREASE IN kg | AS5: =AS2+25.29%*AS2 -> 1624.875
A6: 1200 | B6: 167 | C6: 33.965146 | D6: =$K$3*C6 -> 67.930291 | E6: 11.00767 | F6: =ABS(E6-E5) -> 5.8742198 | G6: =$J$3*E6 -> 99.069031 | H6: 44.114464 | K6: DC BUS VOLTAGE | AM6: =$AF$26*E6^2+$AG$26*E6+$AH$26 -> 17.894439 | AR6: 25.29% increase in kg due to FC degrad
A7: 1500 | B7: 183 | C7: 19.206215 | D7: =$K$3*C7 -> 38.41243 | E7: 16.065195 | F7: =ABS(E7-E6) -> 5.0575246 | G7: =$J$3*E7 -> 144.58675 | H7: 42.086644 | AM7: =$AF$26*E7^2+$AG$26*E7+$AH$26 -> 25.958834
A8: 1800 | B8: 174 | C8: 0.92242951 | D8: =$K$3*C8 -> 1.844859 | E8: 19.128257 | F8: =ABS(E8-E7) -> 3.063062 | G8: =$J$3*E8 -> 172.15431 | H8: 41.371447 | AM8: =$AF$26*E8^2+$AG$26*E8+$AH$26 -> 30.915734
A9: 2100 | B9: 222 | C9: 12.077322 | D9: =$K$3*C9 -> 24.154645 | E9: 21.982647 | F9: =ABS(E9-E8) -> 2.8543903 | G9: =$J$3*E9 -> 197.84382 | H9: 40.819748 | AM9: =$AF$26*E9^2+$AG$26*E9+$AH$26 -> 35.58434
A10: 2400 | B10: 481 | C10: 57.030696 | D10: =$K$3*C10 -> 114.06139 | E10: 38.590279 | F10: =ABS(E10-E9) -> 16.607632 | G10: =$J$3*E10 -> 347.31251 | H10: 36.992234 | AM10: =$AF$26*E10^2+$AG$26*E10+$AH$26 -> 63.69283
A11: 2700 | B11: 263 | C11: -57.446602 | D11: =$K$3*C11 -> -114.8932 | E11: 41.988032 | F11: =ABS(E11-E10) -> 3.3977529 | G11: =$J$3*E11 -> 377.89229 | H11: 37.191264 | AM11: =$AF$26*E11^2+$AG$26*E11+$AH$26 -> 69.642328
A12: 3000 | B12: 251 | C12: -44.705528 | D12: =$K$3*C12 -> -89.411056 | E12: 37.823051 | F12: =ABS(E12-E11) -> 4.1649815 | G12: =$J$3*E12 -> 340.40746 | H12: 41.100363 | AM12: =$AF$26*E12^2+$AG$26*E12+$AH$26 -> 62.35875
A13: 3300 | B13: 159 | C13: -65.063411 | D13: =$K$3*C13 -> -130.12682 | E13: 32.124985 | F13: =ABS(E13-E12) -> 5.6980659 | G13: =$J$3*E13 -> 289.12486 | H13: 45.41315 | AM13: =$AF$26*E13^2+$AG$26*E13+$AH$26 -> 52.558523
A14: 3600 | B14: 157 | C14: -38.68913 | D14: =$K$3*C14 -> -77.37826 | E14: 26.041822 | F14: =ABS(E14-E13) -> 6.0831627 | G14: =$J$3*E14 -> 234.3764 | H14: 49.319839 | AM14: =$AF$26*E14^2+$AG$26*E14+$AH$26 -> 42.305549
A15: 3900 | B15: 158 | C15: -20.504316 | D15: =$K$3*C15 -> -41.008632 | E15: 22.111932 | F15: =ABS(E15-E14) -> 3.9298905 | G15: =$J$3*E15 -> 199.00739 | H15: 51.542249 | AM15: =$AF$26*E15^2+$AG$26*E15+$AH$26 -> 35.796925
A16: 4200 | B16: 136 | C16: -17.796597 | D16: =$K$3*C16 -> -35.593195 | E16: 19.065824 | F16: =ABS(E16-E15) -> 3.0461082 | G16: =$J$3*E16 -> 171.59241 | H16: 53.016845 | AM16: =$AF$26*E16^2+$AG$26*E16+$AH$26 -> 30.814151
A17: 4500 | B17: 248 | C17: 34.420184 | D17: =$K$3*C17 -> 68.840369 | E17: 19.906436 | F17: =ABS(E17-E16) -> 0.84061252 | G17: =$J$3*E17 -> 179.15793 | H17: 52.160271 | AM17: =$AF$26*E17^2+$AG$26*E17+$AH$26 -> 32.18379
A18: 4800 | B18: 405 | C18: 77.798303 | D18: =$K$3*C18 -> 155.59661 | E18: 27.711034 | F18: =ABS(E18-E17) -> 7.8045983 | G18: =$J$3*E18 -> 249.39931 | H18: 47.564731 | AM18: =$AF$26*E18^2+$AG$26*E18+$AH$26 -> 45.097406
... A20: 5400 | B20: 398 | C20: 13.872118 | D20: =$K$3*C20 -> 27.744237 | E20: 41.139076 | F20: =ABS(E20-E19) -> 4.9170981 | G20: =$J$3*E20 -> 370.25168 | H20: 41.090268 | AM20: =$AF$26*E20^2+$AG$26*E20+$AH$26 -> 68.149469
A21: 5700 | B21: 458 | C21: 24.221056 | D21: =$K$3*C21 -> 48.442111 | E21: 45.505732 | F21: =ABS(E21-E20) -> 4.366656 | G21: =$J$3*E21 -> 409.55159 | H21: 39.560317 | AF21: Fuel consumption (kW) in y axis | AM21: =$AF$26*E21^2+$AG$26*E21+$AH$26 -> 75.872996
A22: 6000 | B22: 642 | C22: 54.446541 | D22: =$K$3*C22 -> 108.89308 | E22: 57.275099 | F22: =ABS(E22-E21) -> 11.769367 | G22: =$J$3*E22 -> 515.47589 | H22: 35.766646 | AF22: Power output (kW) in x axis | AM22: =$AF$26*E22^2+$AG$26*E22+$AH$26 -> 97.245466
A23: 6300 | B23: 1113 | C23: 46.053821 | D23: =$K$3*C23 -> 92.107642 | E23: 100.08404 | F23: =ABS(E23-E22) -> 42.808945 | G23: =$J$3*E23 -> 900.7564 | H23: 31.80604 | AM23: =$AF$26*E23^2+$AG$26*E23+$AH$26 -> 181.81683
A24: 6600 | B24: 1129 | C24: 38.914941 | D24: =$K$3*C24 -> 77.829882 | E24: 116.78681 | F24: =ABS(E24-E23) -> 16.702762 | G24: =$J$3*E24 -> 1051.0813 | H24: 28.465179 | AM24: =$AF$26*E24^2+$AG$26*E24+$AH$26 -> 217.721
A25: 6900 | B25: 1100 | C25: 5.1223709 | D25: =$K$3*C25 -> 10.244742 | E25: 121.07803 | F25: =ABS(E25-E24) -> 4.29122 | G25: =$J$3*E25 -> 1089.7022 | H25: 26.809607 | AF25: k1 | AG25: k2 | AH25: k3 | AM25: =$AF$26*E25^2+$AG$26*E25+$AH$26 -> 227.20885
A26: 7200 | B26: 1094 | C26: -8.9981832 | D26: =$K$3*C26 -> -17.996366 | E26: 123.54875 | F26: =ABS(E26-E25) -> 2.4707257 | G26: =$J$3*E26 -> 1111.9388 | H26: 26.993358 | AF26: 0.00292448 | AG26: 1.51536 | AH26: 0.8595 | AM26: =$AF$26*E26^2+$AG$26*E26+$AH$26 -> 232.72046
A27: 7500 | B27: 1096 | C27: -15.362956 | D27: =$K$3*C27 -> -30.725911 | E27: 125.18505 | F27: =ABS(E27-E26) -> 1.6363026 | G27: =$J$3*E27 -> 1126.6655 | H27: 27.960424 | AM27: =$AF$26*E27^2+$AG$26*E27+$AH$26 -> 236.39032
A28: 7800 | B28: 1018 | C28: -53.863419 | D28: =$K$3*C28 -> -107.72684 | E28: 125.07458 | F28: =ABS(E28-E27) -> 0.11047854 | G28: =$J$3*E28 -> 1125.6712 | H28: 30.727714 | AM28: =$AF$26*E28^2+$AG$26*E28+$AH$26 -> 236.14205
A29: 8100 | B29: 635 | C29: -87.097502 | D29: =$K$3*C29 -> -174.195 | E29: 98.5216 | F29: =ABS(E29-E28) -> 26.552976 | G29: =$J$3*E29 -> 886.6944 | H29: 37.174439 | AM29: =$AF$26*E29^2+$AG$26*E29+$AH$26 -> 178.54167
A30: 8400 | B30: 718 | C30: -38.433095 | D30: =$K$3*C30 -> -76.86619 | E30: 88.3155 | F30: =ABS(E30-E29) -> 10.206101 | G30: =$J$3*E30 -> 794.8395 | H30: 42.313346 | AM30: =$AF$26*E30^2+$AG$26*E30+$AH$26 -> 157.49913
A31: 8700 | B31: 1124 | C31: 62.052668 | D31: =$K$3*C31 -> 124.10534 | E31: 101.05363 | F31: =ABS(E31-E30) -> 12.738134 | G31: =$J$3*E31 -> 909.4827 | H31: 39.320657 | AM31: =$AF$26*E31^2+$AG$26*E31+$AH$26 -> 183.85645
A32: 9000 | B32: 1113 | C32: 44.057217 | D32: =$K$3*C32 -> 88.114433 | E32: 113.87112 | F32: =ABS(E32-E31) -> 12.817482 | G32: =$J$3*E32 -> 1024.84 | H32: 34.949056 | AM32: =$AF$26*E32^2+$AG$26*E32+$AH$26 -> 211.33589
A33: 9300 | B33: 1116 | C33: 24.664717 | D33: =$K$3*C33 -> 49.329433 | E33: 118.51322 | F33: =ABS(E33-E32) -> 4.6421061 | G33: =$J$3*E33 -> 1066.619 | H33: 32.29093 | AM33: =$AF$26*E33^2+$AG$26*E33+$AH$26 -> 221.52514
A34: 9600 | B34: 1119 | C34: 10.739725 | D34: =$K$3*C34 -> 21.47945 | E34: 121.94051 | F34: =ABS(E34-E33) -> 3.4272854 | G34: =$J$3*E34 -> 1097.4646 | H34: 30.934037 | AF34: BATTERY DEGRADATION | AM34: =$AF$26*E34^2+$AG$26*E34+$AH$26 -> 229.12879
A35: 9900 | B35: 1129 | C35: 3.7511349 | D35: =$K$3*C35 -> 7.5022698 | E35: 124.60417 | F35: =ABS(E35-E34) -> 2.6636672 | G35: =$J$3*E35 -> 1121.4376 | H35: 30.383331 | AM35: =$AF$26*E35^2+$AG$26*E35+$AH$26 -> 235.08574
A36: 10200 | B36: 1116 | C36: -11.069281 | D36: =$K$3*C36 -> -22.138561 | E36: 126.453 | F36: =ABS(E36-E35) -> 1.8488273 | G36: =$J$3*E36 -> 1138.077 | H36: 30.699906 | AM36: =$AF$26*E36^2+$AG$26*E36+$AH$26 -> 239.24481
A37: 10500 | B37: 1100 | C37: -22.883893 | D37: =$K$3*C37 -> -45.767785 | E37: 127.30057 | F37: =ABS(E37-E36) -> 0.84757214 | G37: =$J$3*E37 -> 1145.7052 | H37: 32.046181 | AM37: =$AF$26*E37^2+$AG$26*E37+$AH$26 -> 241.15817
A38: 10800 | B38: 1113 | C38: -18.422592 | D38: =$K$3*C38 -> -36.845185 | E38: 127.75335 | F38: =ABS(E38-E37) -> 0.45277664 | G38: =$J$3*E38 -> 1149.7802 | H38: 33.645521 | AM38: =$AF$26*E38^2+$AG$26*E38+$AH$26 -> 242.18202
A39: 11100 | B39: 1138 | C39: -9.2954864 | D39: =$K$3*C39 -> -18.590973 | E39: 128.50266 | F39: =ABS(E39-E38) -> 0.74931024 | G39: =$J$3*E39 -> 1156.5239 | H39: 34.707824 | AM39: =$AF$26*E39^2+$AG$26*E39+$AH$26 -> 243.87904
A40: 11400 | B40: 1107 | C40: -26.386009 | D40: =$K$3*C40 -> -52.772018 | E40: 128.85642 | F40: =ABS(E40-E39) -> 0.35375756 | G40: =$J$3*E40 -> 1159.7078 | H40: 36.126264 | AM40: =$AF$26*E40^2+$AG$26*E40+$AH$26 -> 244.68136
A41: 11700 | B41: 1128 | C41: -15.879936 | D41: =$K$3*C41 -> -31.759871 | E41: 128.85473 | F41: =ABS(E41-E40) -> 0.0016882208 | G41: =$J$3*E41 -> 1159.6926 | H41: 37.748098 | AM41: =$AF$26*E41^2+$AG$26*E41+$AH$26 -> 244.67753
A42: 12000 | B42: 1127 | C42: -17.021932 | D42: =$K$3*C42 -> -34.043864 | E42: 128.99751 | F42: =ABS(E42-E41) -> 0.14278238 | G42: =$J$3*E42 -> 1160.9776 | H42: 39.027864 | AM42: =$AF$26*E42^2+$AG$26*E42+$AH$26 -> 245.00156
A43: 12300 | B43: 1115 | C43: -22.127016 | D43: =$K$3*C43 -> -44.254032 | E43: 128.79875 | F43: =ABS(E43-E42) -> 0.19875768 | G43: =$J$3*E43 -> 1159.1888 | H43: 40.555707 | AM43: =$AF$26*E43^2+$AG$26*E43+$AH$26 -> 244.55053
A44: 12600 | B44: 1119 | C44: -18.340702 | D44: =$K$3*C44 -> -36.681403 | E44: 128.40177 | F44: =ABS(E44-E43) -> 0.3969879 | G44: =$J$3*E44 -> 1155.6159 | H44: 42.117386 | AM44: =$AF$26*E44^2+$AG$26*E44+$AH$26 -> 243.65034
A45: 12900 | B45: 1162 | C45: 1.9667295 | D45: =$K$3*C45 -> 3.933459 | E45: 128.66647 | F45: =ABS(E45-E44) -> 0.26469984 | G45: =$J$3*E45 -> 1157.9982 | H45: 42.715149 | AM45: =$AF$26*E45^2+$AG$26*E45+$AH$26 -> 244.25046
A46: 13200 | B46: 1109 | C46: -24.429885 | D46: =$K$3*C46 -> -48.85977 | E46: 128.64413 | F46: =ABS(E46-E45) -> 0.022335197 | G46: =$J$3*E46 -> 1157.7972 | H46: 43.634187 | AM46: =$AF$26*E46^2+$AG$26*E46+$AH$26 -> 244.1998
... A85: 24900 | B85: 1134 | C85: -1.0811505 | D85: =$K$3*C85 -> -2.1623011 | E85: 126.23339 | F85: =ABS(E85-E84) -> 0.0052312517 | G85: =$J$3*E85 -> 1136.1005 | H85: 49.557521 | AM85: =$AF$26*E85^2+$AG$26*E85+$AH$26 -> 238.74974
A86: 25200 | B86: 1136 | C86: -0.10790514 | D86: =$K$3*C86 -> -0.21581028 | E86: 126.23932 | F86: =ABS(E86-E85) -> 0.0059249602 | G86: =$J$3*E86 -> 1136.1539 | H86: 49.601792 | AF86: EC at 48.18% DoD | AG86: Max cycles at 48.18% DoD | AM86: =$AF$26*E86^2+$AG$26*E86+$AH$26 -> 238.7631
A87: 25500 | B87: 1140 | C87: 1.4795418 | D87: =$K$3*C87 -> 2.9590836 | E87: 126.33097 | F87: =ABS(E87-E86) -> 0.091648496 | G87: =$J$3*E87 -> 1136.9787 | H87: 49.545497 | AF87: 1.77 | AG87: 51000 | AM87: =$AF$26*E87^2+$AG$26*E87+$AH$26 -> 238.96967
A88: 25800 | B88: 1139 | C88: 0.45739985 | D88: =$K$3*C88 -> 0.9147997 | E88: 126.44701 | F88: =ABS(E88-E87) -> 0.11604336 | G88: =$J$3*E88 -> 1138.0231 | H88: 49.472269 | AM88: =$AF$26*E88^2+$AG$26*E88+$AH$26 -> 239.2313
A89: 26100 | B89: 1131 | C89: -3.3326677 | D89: =$K$3*C89 -> -6.6653355 | E89: 126.40041 | F89: =ABS(E89-E88) -> 0.046596367 | G89: =$J$3*E89 -> 1137.6037 | H89: 49.591066 | AM89: =$AF$26*E89^2+$AG$26*E89+$AH$26 -> 239.12624
A90: 26400 | B90: 1137 | C90: -0.0086688196 | D90: =$K$3*C90 -> -0.017337639 | E90: 126.32834 | F90: =ABS(E90-E89) -> 0.072077239 | G90: =$J$3*E90 -> 1136.955 | H90: 49.71433 | AM90: =$AF$26*E90^2+$AG$26*E90+$AH$26 -> 238.96374
A91: 26700 | B91: 1137 | C91: -0.1242126 | D91: =$K$3*C91 -> -0.2484252 | E91: 126.35405 | F91: =ABS(E91-E90) -> 0.025709441 | G91: =$J$3*E91 -> 1137.1864 | H91: 49.719692 | AM91: =$AF$26*E91^2+$AG$26*E91+$AH$26 -> 239.0217
A92: 27000 | B92: 1137 | C92: -0.20635321 | D92: =$K$3*C92 -> -0.41270642 | E92: 126.3723 | F92: =ABS(E92-E91) -> 0.018250389 | G92: =$J$3*E92 -> 1137.3507 | H92: 49.732678 | AA92: PRAXIS BATTERIES | AM92: =$AF$26*E92^2+$AG$26*E92+$AH$26 -> 239.06284
A93: 27300 | B93: 1134 | C93: -1.5531582 | D93: =$K$3*C93 -> -3.1063165 | E93: 126.33828 | F93: =ABS(E93-E92) -> 0.034017432 | G93: =$J$3*E93 -> 1137.0445 | H93: 49.803528 | Z93: 513.01 GreenBattery Rev1.12 A4.cdr (praxis-automation.eu) | AM93: =$AF$26*E93^2+$AG$26*E93+$AH$26 -> 238.98616
A94: 27600 | B94: 1136 | C94: -0.3493077 | D94: =$K$3*C94 -> -0.69861539 | E94: 126.29295 | F94: =ABS(E94-E93) -> 0.045324362 | G94: =$J$3*E94 -> 1136.6366 | H94: 49.875037 | AM94: =$AF$26*E94^2+$AG$26*E94+$AH$26 -> 238.88399
A95: 27900 | B95: 1133 | C95: -1.5977519 | D95: =$K$3*C95 -> -3.1955038 | E95: 126.2371 | F95: =ABS(E95-E94) -> 0.055859247 | G95: =$J$3*E95 -> 1136.1339 | H95: 49.952969 | AM95: =$AF$26*E95^2+$AG$26*E95+$AH$26 -> 238.75809
A96: 28200 | B96: 1133 | C96: -1.1807004 | D96: =$K$3*C96 -> -2.3614008 | E96: 126.14441 | F96: =ABS(E96-E95) -> 0.092680963 | G96: =$J$3*E96 -> 1135.2997 | H96: 50.059964 | AM96: =$AF$26*E96^2+$AG$26*E96+$AH$26 -> 238.54923
A97: 28500 | B97: 1135 | C97: 0.028427456 | D97: =$K$3*C97 -> 0.056854912 | E97: 126.09794 | F97: =ABS(E97-E96) -> 0.046478271 | G97: =$J$3*E97 -> 1134.8814 | H97: 50.102341 | AM97: =$AF$26*E97^2+$AG$26*E97+$AH$26 -> 238.44452
A98: 28800 | B98: 1132 | C98: -1.2282883 | D98: =$K$3*C98 -> -2.4565767 | E98: 126.04391 | F98: =ABS(E98-E97) -> 0.054021572 | G98: =$J$3*E98 -> 1134.3952 | H98: 50.151308 | AM98: =$AF$26*E98^2+$AG$26*E98+$AH$26 -> 238.32282
A99: 29100 | B99: 1133 | C99: -0.39847334 | D99: =$K$3*C99 -> -0.79694668 | E99: 125.97061 | F99: =ABS(E99-E98) -> 0.073305283 | G99: =$J$3*E99 -> 1133.7355 | H99: 50.212829 | AM99: =$AF$26*E99^2+$AG$26*E99+$AH$26 -> 238.15771
A100: 29400 | B100: 1159 | C100: 10.992024 | D100: =$K$3*C100 -> 21.984048 | E100: 126.32805 | F100: =ABS(E100-E99) -> 0.3574369 | G100: =$J$3*E100 -> 1136.9524 | H100: 49.779122 | AM100: =$AF$26*E100^2+$AG$26*E100+$AH$26 -> 238.96309
A101: 29700 | B101: 1165 | C101: 10.499641 | D101: =$K$3*C101 -> 20.999281 | E101: 127.10412 | F101: =ABS(E101-E100) -> 0.77607179 | G101: =$J$3*E101 -> 1143.9371 | H101: 48.944269 | AM101: =$AF$26*E101^2+$AG$26*E101+$AH$26 -> 240.71431
A102: 30000 | B102: 1165 | C102: 7.244669 | D102: =$K$3*C102 -> 14.489338 | E102: 127.82736 | F102: =ABS(E102-E101) -> 0.7232374 | G102: =$J$3*E102 -> 1150.4462 | H102: 48.260589 | AM102: =$AF$26*E102^2+$AG$26*E102+$AH$26 -> 242.34948
A103: 30300 | B103: 1176 | C103: 9.372404 | D103: =$K$3*C103 -> 18.744808 | E103: 128.57654 | F103: =ABS(E103-E102) -> 0.74918057 | G103: =$J$3*E103 -> 1157.1888 | H103: 47.610593 | AM103: =$AF$26*E103^2+$AG$26*E103+$AH$26 -> 244.04653
